Workbook

Sheet low avg budget & poplarity
A1: Years (Release Date) | B1: (Multiple Items)
A3: Row Labels | B3: Average of Movie FB Likes | C3: Average of IMDb Score (1-10) | D3: Average of Budget
A4: Horror | B4: 10134.938 | C4: 5.6148148 | D4: 13306914
A5: Biography | B5: 18670.169 | C5: 7.0788136 | D5: 25454237
A6: Drama | B6: 14965.734 | C6: 6.7473988 | D6: 31003423
A7: Comedy | B7: 7798.5207 | C7: 6.1074074 | D7: 50957133
A8: Crime | B8: 14144.435 | C8: 6.8194444 | D8: 64732557
A9: Adventure | B9: 22174.01 | C9: 6.5589744 | D9: 78553077
A10: Action | B10: 20679.96 | C10: 6.3162791 | D10: 82117926
A11: Grand Total | B11: 15270.921 | C11: 6.4245826 | D11: 55162719

Sheet Low-Risk Investment Indicators 
A1: Years (Release Date) | B1: (Multiple Items)
A2: IMDb Score (1-10) | B2: (Multiple Items) | C2: AVERAGE = 6.43
A4: Row Labels | B4: Count of Title | C4: Average of ROI | D4: Average of Lead Actor FB Likes | E4: Average of IMDb Score (1-10) | F4: =_xlfn.PERCENTILE.EXC(B4:B892,0.25) -> 1
A5: Robert Downey Jr. | B5: 15 | C5: 0.32498085 | D5: 21000 | E5: 7.22 | F5: =_xlfn.PERCENTILE.EXC(B4:B892,0.75) -> 2
A6: Matt Damon | B6: 13 | C6: 0.28724496 | D6: 13000 | E6: 7.0461538
A7: J.K. Simmons | B7: 13 | C7: 2.2867593 | D7: 24000 | E7: 7.1769231
A8: Jennifer Lawrence | B8: 12 | C8: 2.5739128 | D8: 34000 | E8: 7.1916667
A9: Leonardo DiCaprio | B9: 11 | C9: 0.20826122 | D9: 29000 | E9: 7.8636364
A10: Christian Bale | B10: 11 | C10: 0.14632248 | D10: 23000 | E10: 7.5909091
A11: Joseph Gordon-Levitt | B11: 10 | C11: 1.3438164 | D11: 23000 | E11: 7.08
A12: Jason Statham | B12: 10 | C12: 0.16937579 | D12: 26000 | E12: 6.74
A13: Hugh Jackman | B13: 10 | C13: 0.004065743 | D13: 20000 | E13: 7.12
A14: Johnny Depp | B14: 10 | C14: 0.17351894 | D14: 40000 | E14: 6.94
A15: Ryan Gosling | B15: 9 | C15: 1.124123 | D15: 33000 | E15: 7.3444444
A16: Denzel Washington | B16: 9 | C16: 0.65302025 | D16: 18000 | E16: 7.1888889
A17: Gerard Butler | B17: 9 | C17: 0.45611238 | D17: 18000 | E17: 7.2555556
... A121: Olivia Wilde | B121: 2 | C121: -0.2769055 | D121: 10000 | E121: 7.25
A122: (blank) | B122: 2 | C122: -0.98766887 | E122: 7.3
A123: Don Cheadle | B123: 2 | C123: 0.24530742 | D123: 3000 | E123: 7
A124: Jet Li | B124: 2 | C124: -0.77074875 | D124: 5000 | E124: 6.85
A125: Amy Poehler | B125: 2 | C125: 0.58510427 | D125: 1000 | E125: 7.4
A126: Bella Thorne | B126: 2 | C126: 1.5795566 | D126: 35000 | E126: 6.5
A127: Jimmy Bennett | B127: 2 | C127: -0.65391578 | D127: 87000 | E127: 6.65
A128: Al Pacino | B128: 2 | C128: -0.043499062 | D128: 14000 | E128: 7
A129: Hunter Parrish | B129: 2 | C129: -0.093465301 | D129: 2000 | E129: 7
A130: Billy Crudup | B130: 2 | C130: 0.1284485 | D130: 745 | E130: 7.8
A131: Jennifer Jason Leigh | B131: 2 | C131: -0.67618356 | D131: 1000 | E131: 7.2
A132: Bob Hoskins | B132: 2 | C132: -0.64811146 | D132: 5000 | E132: 7.15
A133: Jim Parsons | B133: 2 | C133: -0.044135574 | D133: 17000 | E133: 6.7
A134: Bojana Novakovic | B134: 2 | C134: -0.028475727 | D134: 2000 | E134: 6.6
... A527: Grand Total | B527: 994 | C527: 0.97648194 | D527: 9182.5202 | E527: 7.156841

Sheet Detail1
A1: Details for Count of Title - Director Name: Edward Burns
A3: Title | B3: Lead Actor | C3: Director Name | D3: Lead Actor FB Likes | E3: Cast FB Likes | F3: Director FB Likes | G3: Movie FB Likes | H3: IMDb Score (1-10) | I3: Total Reviews | J3: Duration (min) | K3: Gross Revenue | L3: Budget | M3: Release Date | N3: Color/B&W | O3: Genre | P3: Language | Q3: Country | R3: Rating | S3: Is _English | T3: Profit | U3: %Profit | V3: Duration_Class | W3: ROI
A4: The Brothers McMullen | B4: Shari Albert | C4: Edward Burns | D4: 138 | E4: 388 | F4: 0 | G4: 265 | H4: 6.6 | I4: 36 | J4: 98 | K4: 10246600 | L4: 25000 | M4: 34894 | N4: Color | O4: Comedy | P4: English | Q4: USA | R4: R | S4: English | T4: 10221600 | U4: 408.864 | V4: 90-110 minutes | W4: 408.864
A5: She's the One | B5: John Mahoney | C5: Edward Burns | D5: 385 | E5: 995 | F5: 0 | G5: 453 | H5: 6.1 | I5: 43 | J5: 96 | K5: 9449219 | L5: 3500000 | M5: 35418 | N5: Color | O5: Comedy | P5: English | Q5: USA | R5: R | S5: English | T5: 5949219 | U5: 1.6997769 | V5: 90-110 minutes | W5: 1.6997769
A6: Newlyweds | B6: Kerry BishÃ© | C6: Edward Burns | D6: 296 | E6: 690 | F6: 0 | G6: 413 | H6: 6.4 | I6: 14 | J6: 95 | K6: 4584 | L6: 9000 | M6: 40842 | N6: Color | O6: Comedy | P6: English | Q6: USA | R6: Not Rated | S6: English | T6: -4416 | U6: -0.49066667 | V6: 90-110 minutes | W6: -0.49066667

Sheet Director And IMDB Score
A1: Years (Release Date) | B1: (Multiple Items)
A3: Director Name | B3: Average of IMDb Score (1-10) | C3: Average of ROI | D3: StdDev of ROI | E3: Count of Title | H3: Years | I3: 1990-2015
A4: Clint Eastwood | B4: 7.2764706 | C4: 1.0862411 | D4: 2.0554456 | E4: 17 | H4: Min Number of Movies | I4: 4
A5: Steven Spielberg | B5: 7.4117647 | C5: 1.1340741 | D5: 1.3903771 | E5: 17 | H5: Min IMDB Score | I5: 6.5
A6: Woody Allen | B6: 6.93125 | C6: 0.010409785 | D6: 0.93657553 | E6: 16 | H6: Min ROI | I6: positive
A7: Steven Soderbergh | B7: 6.6428571 | C7: 1.3635791 | D7: 4.0598708 | E7: 14 | H7: Max Std of ROI | I7: 6.5
A8: Ron Howard | B8: 6.9916667 | C8: 0.28798214 | D8: 0.93598558 | E8: 12
A9: Spike Lee | B9: 6.7333333 | C9: 1.0449355 | D9: 3.4306194 | E9: 12
A10: Tim Burton | B10: 6.9666667 | C10: 0.33310321 | D10: 0.69465899 | E10: 12
A11: Martin Scorsese | B11: 7.7083333 | C11: 0.074941928 | D11: 0.63502066 | E11: 12
A12: Robert Zemeckis | B12: 7.1545455 | C12: 0.73393797 | D12: 1.7089597 | E12: 11
A13: Chris Columbus | B13: 6.6545455 | C13: 3.1116612 | D13: 5.0576461 | E13: 11
A14: Michael Bay | B14: 6.5454545 | C14: 0.68057582 | D14: 0.79293059 | E14: 11
A15: David Fincher | B15: 7.75 | C15: 0.5352296 | D15: 0.93079326 | E15: 10
A16: Peter Jackson | B16: 7.8888889 | C16: 0.91105002 | D16: 1.3628213 | E16: 9
A17: Sam Raimi | B17: 6.8666667 | C17: 0.30001014 | D17: 0.71659868 | E17: 9
A18: Brett Ratner | B18: 6.4555556 | C18: 0.22013405 | D18: 0.58333466 | E18: 9
A19: Phillip Noyce | B19: 6.7666667 | C19: 0.1947126 | D19: 0.60540533 | E19: 9
... A118: Grand Total | B118: 7.0144476 | C118: 0.88193795 | D118: 2.0242907 | E118: 706

Sheet Sheet4
A1: Years (Release Date) | B1: (Multiple Items)
A3: Row Labels | B3: Average of ROI | C3: StdDev of ROI | D3: Count of Title
A4: R | B4: 7.4212967 | C4: 213.35567 | D4: 1138
A5: PG | B5: 1.9363193 | C5: 13.161323 | D5: 377
A6: G | B6: 0.79352176 | C6: 1.7814767 | D6: 54
A7: PG-13 | B7: 0.74566813 | C7: 3.0877623 | D7: 1026
A8: NC-17 | B8: -0.14219128 | C8: 0.68513344 | D8: 3
A9: Grand Total | B9: 3.8425355 | C9: 141.31019 | D9: 2598

Sheet Budget tier good invetment
A1: Years (Release Date) | B1: (Multiple Items)
A3: Row Labels | B3: Count of Title | C3: Average of Good_Investment | D3: Average of ROI | E3: StdDev of ROI
A4: High | B4: 709 | C4: 0.24682652 | D4: 0.12221871 | E4: 0.8391676
A5: Mid | B5: 1386 | C5: 0.34776335 | D5: 0.42800722 | E5: 1.4814131
A6: Low | B6: 594 | C6: 0.39393939 | D6: 20.287267 | E6: 315.48691
A7: Grand Total | B7: 2689 | C7: 0.33134994 | D7: 4.7342908 | E7: 148.41734

Sheet Main
A1: Title | B1: Lead Actor | C1: Director Name | D1: Lead Actor FB Likes | E1: Cast FB Likes | F1: Director FB Likes | G1: Movie FB Likes | H1: IMDb Score (1-10) | I1: Total Reviews | J1: Duration (min) | K1: Gross Revenue | L1: Budget | M1: Release Date | N1: Color/B&W | O1: Genre | P1: Language | Q1: Country | R1: Rating | S1: Is _English | T1: Profit | U1: %Profit | V1: Duration_Class | W1: ROI | X1: Budget Tier | Y1: Good_Investment
A2: [Rec] 2 | B2: Jonathan D. Mellor | C2: Jaume BalaguerÃ³ | D2: 37 | E2: 73 | F2: 57 | G2: 4000 | H2: 6.6 | I2: 222 | J2: 85 | K2: 27024 | L2: 5600000 | M2: =VLOOKUP(A2,Sheet2!$A$1:G3726,2,0) -> 39921 | N2: =VLOOKUP(A2,Sheet2!$A$1:G3726,3,0) -> Color | O2: =VLOOKUP(A2,Sheet2!$A$1:G3726,4,0) -> Horror | P2: =VLOOKUP(A2,Sheet2!$A$1:G3726,5,0) -> Spanish | Q2: =VLOOKUP(A2,Sheet2!$A$1:G3726,6,0) -> Spain | R2: =VLOOKUP(A2,Sheet2!$A$1:G3726,7,0) -> R | S2: =IF(Table1[[#This Row],[Language]]="English","English","Other language") -> Other language | T2: =Table1[[#This Row],[Gross Revenue]]-Table1[[#This Row],[Budget]] -> -5572976 | U2: =(Table1[[#This Row],[Gross Revenue]]/Table1[[#This Row],[Budget]])-1 -> -0.99517429 | V2: =IF(J2="","",IF(J2<90,"<90 minutes",IF(J2<=110,"90-110 minutes",IF(J2<=130,"111-130 minutes",IF(J2<=150,"131-150 minutes",">150 minutes"))))) -> <90 minutes | W2: =Table1[[#This Row],[Profit]]/Table1[[#This Row],[Budget]] -> -0.99517429 | X2: =IF(L2="","", IF(L2<Predictability!$B$1,"Low", IF(L2<=Predictability!$B$2,"Mid","High"))) -> Low | Y2: =IF(W2>=0.5,1,0) -> 0 | Z2: =CORREL(Table1[IMDb Score (1-10)],Table1[ROI]) -> 0.0087393311
A3: 10 Days in a Madhouse | B3: Christopher Lambert | C3: Timothy Hines | D3: 1000 | E3: 2059 | F3: 0 | G3: 26000 | H3: 7.5 | I3: 1 | J3: 111 | K3: 14616 | L3: 12000000 | M3: =VLOOKUP(A3,Sheet2!$A$1:G3727,2,0) -> 42130 | N3: =VLOOKUP(A3,Sheet2!$A$1:G3727,3,0) -> Color | O3: =VLOOKUP(A3,Sheet2!$A$1:G3727,4,0) -> Drama | P3: =VLOOKUP(A3,Sheet2!$A$1:G3727,5,0) -> English | Q3: =VLOOKUP(A3,Sheet2!$A$1:G3727,6,0) -> USA | R3: =VLOOKUP(A3,Sheet2!$A$1:G3727,7,0) -> R | S3: =IF(Table1[[#This Row],[Language]]="English","English","Other language") -> English | T3: =Table1[[#This Row],[Gross Revenue]]-Table1[[#This Row],[Budget]] -> -11985384 | U3: =(Table1[[#This Row],[Gross Revenue]]/Table1[[#This Row],[Budget]])-1 -> -0.998782 | V3: =IF(J3="","",IF(J3<90,"<90 minutes",IF(J3<=110,"90-110 minutes",IF(J3<=130,"111-130 minutes",IF(J3<=150,"131-150 minutes",">150 minutes"))))) -> 111-130 minutes | W3: =Table1[[#This Row],[Profit]]/Table1[[#This Row],[Budget]] -> -0.998782 | X3: =IF(L3="","", IF(L3<Predictability!$B$1,"Low", IF(L3<=Predictability!$B$2,"Mid","High"))) -> Mid | Y3: =IF(W3>=0.5,1,0) -> 0
A4: 10 Things I Hate About You | B4: Joseph Gordon-Levitt | C4: Gil Junger | D4: 23000 | E4: 37907 | F4: 19 | G4: 10000 | H4: 7.2 | I4: 133 | J4: 97 | K4: 38176108 | L4: 16000000 | M4: =VLOOKUP(A4,Sheet2!$A$1:G3728,2,0) -> 36245 | N4: =VLOOKUP(A4,Sheet2!$A$1:G3728,3,0) -> Color | O4: =VLOOKUP(A4,Sheet2!$A$1:G3728,4,0) -> Comedy | P4: =VLOOKUP(A4,Sheet2!$A$1:G3728,5,0) -> English | Q4: =VLOOKUP(A4,Sheet2!$A$1:G3728,6,0) -> USA | R4: =VLOOKUP(A4,Sheet2!$A$1:G3728,7,0) -> PG-13 | S4: =IF(Table1[[#This Row],[Language]]="English","English","Other language") -> English | T4: =Table1[[#This Row],[Gross Revenue]]-Table1[[#This Row],[Budget]] -> 22176108 | U4: =(Table1[[#This Row],[Gross Revenue]]/Table1[[#This Row],[Budget]])-1 -> 1.3860067 | V4: =IF(J4="","",IF(J4<90,"<90 minutes",IF(J4<=110,"90-110 minutes",IF(J4<=130,"111-130 minutes",IF(J4<=150,"131-150 minutes",">150 minutes"))))) -> 90-110 minutes | W4: =Table1[[#This Row],[Profit]]/Table1[[#This Row],[Budget]] -> 1.3860067 | X4: =IF(L4="","", IF(L4<Predictability!$B$1,"Low", IF(L4<=Predictability!$B$2,"Mid","High"))) -> Mid | Y4: =IF(W4>=0.5,1,0) -> 1
A5: 102 Dalmatians | B5: Ioan Gruffudd | C5: Kevin Lima | D5: 2000 | E5: 4182 | F5: 36 | G5: 372 | H5: 4.8 | I5: 84 | J5: 100 | K5: 66941559 | L5: 85000000 | M5: =VLOOKUP(A5,Sheet2!$A$1:G3729,2,0) -> 36715 | N5: =VLOOKUP(A5,Sheet2!$A$1:G3729,3,0) -> Color | O5: =VLOOKUP(A5,Sheet2!$A$1:G3729,4,0) -> Adventure | P5: =VLOOKUP(A5,Sheet2!$A$1:G3729,5,0) -> English | Q5: =VLOOKUP(A5,Sheet2!$A$1:G3729,6,0) -> USA | R5: =VLOOKUP(A5,Sheet2!$A$1:G3729,7,0) -> G | S5: =IF(Table1[[#This Row],[Language]]="English","English","Other language") -> English | T5: =Table1[[#This Row],[Gross Revenue]]-Table1[[#This Row],[Budget]] -> -18058441 | U5: =(Table1[[#This Row],[Gross Revenue]]/Table1[[#This Row],[Budget]])-1 -> -0.21245225 | V5: =IF(J5="","",IF(J5<90,"<90 minutes",IF(J5<=110,"90-110 minutes",IF(J5<=130,"111-130 minutes",IF(J5<=150,"131-150 minutes",">150 minutes"))))) -> 90-110 minutes | W5: =Table1[[#This Row],[Profit]]/Table1[[#This Row],[Budget]] -> -0.21245225 | X5: =IF(L5="","", IF(L5<Predictability!$B$1,"Low", IF(L5<=Predictability!$B$2,"Mid","High"))) -> High | Y5: =IF(W5>=0.5,1,0) -> 0
A6: 10th & Wolf | B6: Brian Dennehy | C6: Robert Moresco | D6: 954 | E6: 2512 | F6: 53 | G6: 294 | H6: 6.4 | I6: 26 | J6: 107 | K6: 53481 | L6: 8000000 | M6: =VLOOKUP(A6,Sheet2!$A$1:G3730,2,0) -> 38850 | N6: =VLOOKUP(A6,Sheet2!$A$1:G3730,3,0) -> Color | O6: =VLOOKUP(A6,Sheet2!$A$1:G3730,4,0) -> Crime | P6: =VLOOKUP(A6,Sheet2!$A$1:G3730,5,0) -> English | Q6: =VLOOKUP(A6,Sheet2!$A$1:G3730,6,0) -> USA | R6: =VLOOKUP(A6,Sheet2!$A$1:G3730,7,0) -> R | S6: =IF(Table1[[#This Row],[Language]]="English","English","Other language") -> English | T6: =Table1[[#This Row],[Gross Revenue]]-Table1[[#This Row],[Budget]] -> -7946519 | U6: =(Table1[[#This Row],[Gross Revenue]]/Table1[[#This Row],[Budget]])-1 -> -0.99331488 | V6: =IF(J6="","",IF(J6<90,"<90 minutes",IF(J6<=110,"90-110 minutes",IF(J6<=130,"111-130 minutes",IF(J6<=150,"131-150 minutes",">150 minutes"))))) -> 90-110 minutes | W6: =Table1[[#This Row],[Profit]]/Table1[[#This Row],[Budget]] -> -0.99331488 | X6: =IF(L6="","", IF(L6<Predictability!$B$1,"Low", IF(L6<=Predictability!$B$2,"Mid","High"))) -> Low | Y6: =IF(W6>=0.5,1,0) -> 0
A7: 12 Rounds | B7: Taylor Cole | C7: Renny Harlin | D7: 969 | E7: 2799 | F7: 212 | G7: 0 | H7: 5.6 | I7: 113 | J7: 108 | K7: 12232937 | L7: 22000000 | M7: =VLOOKUP(A7,Sheet2!$A$1:G3731,2,0) -> 40137 | N7: =VLOOKUP(A7,Sheet2!$A$1:G3731,3,0) -> Color | O7: =VLOOKUP(A7,Sheet2!$A$1:G3731,4,0) -> Action | P7: =VLOOKUP(A7,Sheet2!$A$1:G3731,5,0) -> English | Q7: =VLOOKUP(A7,Sheet2!$A$1:G3731,6,0) -> USA | R7: =VLOOKUP(A7,Sheet2!$A$1:G3731,7,0) -> PG-13 | S7: =IF(Table1[[#This Row],[Language]]="English","English","Other language") -> English | T7: =Table1[[#This Row],[Gross Revenue]]-Table1[[#This Row],[Budget]] -> -9767063 | U7: =(Table1[[#This Row],[Gross Revenue]]/Table1[[#This Row],[Budget]])-1 -> -0.44395741 | V7: =IF(J7="","",IF(J7<90,"<90 minutes",IF(J7<=110,"90-110 minutes",IF(J7<=130,"111-130 minutes",IF(J7<=150,"131-150 minutes",">150 minutes"))))) -> 90-110 minutes | W7: =Table1[[#This Row],[Profit]]/Table1[[#This Row],[Budget]] -> -0.44395741 | X7: =IF(L7="","", IF(L7<Predictability!$B$1,"Low", IF(L7<=Predictability!$B$2,"Mid","High"))) -> Mid | Y7: =IF(W7>=0.5,1,0) -> 0
A8: 12 Years a Slave | B8: QuvenzhanÃ© Wallis | C8: Steve McQueen | D8: 2000 | E8: 4251 | F8: 0 | G8: 83000 | H8: 8.1 | I8: 597 | J8: 134 | K8: 56667870 | L8: 20000000 | M8: =VLOOKUP(A8,Sheet2!$A$1:G3732,2,0) -> 41587 | N8: =VLOOKUP(A8,Sheet2!$A$1:G3732,3,0) -> Color | O8: =VLOOKUP(A8,Sheet2!$A$1:G3732,4,0) -> Biography | P8: =VLOOKUP(A8,Sheet2!$A$1:G3732,5,0) -> English | Q8: =VLOOKUP(A8,Sheet2!$A$1:G3732,6,0) -> USA | R8: =VLOOKUP(A8,Sheet2!$A$1:G3732,7,0) -> R | S8: =IF(Table1[[#This Row],[Language]]="English","English","Other language") -> English | T8: =Table1[[#This Row],[Gross Revenue]]-Table1[[#This Row],[Budget]] -> 36667870 | U8: =(Table1[[#This Row],[Gross Revenue]]/Table1[[#This Row],[Budget]])-1 -> 1.8333935 | V8: =IF(J8="","",IF(J8<90,"<90 minutes",IF(J8<=110,"90-110 minutes",IF(J8<=130,"111-130 minutes",IF(J8<=150,"131-150 minutes",">150 minutes"))))) -> 131-150 minutes | W8: =Table1[[#This Row],[Profit]]/Table1[[#This Row],[Budget]] -> 1.8333935 | X8: =IF(L8="","", IF(L8<Predictability!$B$1,"Low", IF(L8<=Predictability!$B$2,"Mid","High"))) -> Mid | Y8: =IF(W8>=0.5,1,0) -> 1
A9: 127 Hours | B9: James Franco | C9: Danny Boyle | D9: 11000 | E9: 11984 | F9: 0 | G9: 63000 | H9: 7.6 | I9: 450 | J9: 94 | K9: 18329466 | L9: 18000000 | M9: =VLOOKUP(A9,Sheet2!$A$1:G3733,2,0) -> 40312 | N9: =VLOOKUP(A9,Sheet2!$A$1:G3733,3,0) -> Color | O9: =VLOOKUP(A9,Sheet2!$A$1:G3733,4,0) -> Adventure | P9: =VLOOKUP(A9,Sheet2!$A$1:G3733,5,0) -> English | Q9: =VLOOKUP(A9,Sheet2!$A$1:G3733,6,0) -> USA | R9: =VLOOKUP(A9,Sheet2!$A$1:G3733,7,0) -> R | S9: =IF(Table1[[#This Row],[Language]]="English","English","Other language") -> English | T9: =Table1[[#This Row],[Gross Revenue]]-Table1[[#This Row],[Budget]] -> 329466 | U9: =(Table1[[#This Row],[Gross Revenue]]/Table1[[#This Row],[Budget]])-1 -> 0.018303667 | V9: =IF(J9="","",IF(J9<90,"<90 minutes",IF(J9<=110,"90-110 minutes",IF(J9<=130,"111-130 minutes",IF(J9<=150,"131-150 minutes",">150 minutes"))))) -> 90-110 minutes | W9: =Table1[[#This Row],[Profit]]/Table1[[#This Row],[Budget]] -> 0.018303667 | X9: =IF(L9="","", IF(L9<Predictability!$B$1,"Low", IF(L9<=Predictability!$B$2,"Mid","High"))) -> Mid | Y9: =IF(W9>=0.5,1,0) -> 0
A10: 13 Going on 30 | B10: Jennifer Garner | C10: Gary Winick | D10: 3000 | E10: 6742 | F10: 56 | G10: 0 | H10: 6.1 | I10: 119 | J10: 98 | K10: 56044241 | L10: 37000000 | M10: =VLOOKUP(A10,Sheet2!$A$1:G3734,2,0) -> 38154 | N10: =VLOOKUP(A10,Sheet2!$A$1:G3734,3,0) -> Color | O10: =VLOOKUP(A10,Sheet2!$A$1:G3734,4,0) -> Comedy | P10: =VLOOKUP(A10,Sheet2!$A$1:G3734,5,0) -> English | Q10: =VLOOKUP(A10,Sheet2!$A$1:G3734,6,0) -> USA | R10: =VLOOKUP(A10,Sheet2!$A$1:G3734,7,0) -> PG-13 | S10: =IF(Table1[[#This Row],[Language]]="English","English","Other language") -> English | T10: =Table1[[#This Row],[Gross Revenue]]-Table1[[#This Row],[Budget]] -> 19044241 | U10: =(Table1[[#This Row],[Gross Revenue]]/Table1[[#This Row],[Budget]])-1 -> 0.51470922 | V10: =IF(J10="","",IF(J10<90,"<90 minutes",IF(J10<=110,"90-110 minutes",IF(J10<=130,"111-130 minutes",IF(J10<=150,"131-150 minutes",">150 minutes"))))) -> 90-110 minutes | W10: =Table1[[#This Row],[Profit]]/Table1[[#This Row],[Budget]] -> 0.51470922 | X10: =IF(L10="","", IF(L10<Predictability!$B$1,"Low", IF(L10<=Predictability!$B$2,"Mid","High"))) -> Mid | Y10: =IF(W10>=0.5,1,0) -> 1
A11: 1408 | B11: Drew Powell | C11: Mikael HÃ¥fstrÃ¶m | D11: 129 | E11: 214 | F11: 101 | G11: 11000 | H11: 6.8 | I11: 314 | J11: 114 | K11: 71975611 | L11: 25000000 | M11: =VLOOKUP(A11,Sheet2!$A$1:G3735,2,0) -> 39152 | N11: =VLOOKUP(A11,Sheet2!$A$1:G3735,3,0) -> Color | O11: =VLOOKUP(A11,Sheet2!$A$1:G3735,4,0) -> Fantasy | P11: =VLOOKUP(A11,Sheet2!$A$1:G3735,5,0) -> English | Q11: =VLOOKUP(A11,Sheet2!$A$1:G3735,6,0) -> USA | R11: =VLOOKUP(A11,Sheet2!$A$1:G3735,7,0) -> PG-13 | S11: =IF(Table1[[#This Row],[Language]]="English","English","Other language") -> English | T11: =Table1[[#This Row],[Gross Revenue]]-Table1[[#This Row],[Budget]] -> 46975611 | U11: =(Table1[[#This Row],[Gross Revenue]]/Table1[[#This Row],[Budget]])-1 -> 1.8790244 | V11: =IF(J11="","",IF(J11<90,"<90 minutes",IF(J11<=110,"90-110 minutes",IF(J11<=130,"111-130 minutes",IF(J11<=150,"131-150 minutes",">150 minutes"))))) -> 111-130 minutes | W11: =Table1[[#This Row],[Profit]]/Table1[[#This Row],[Budget]] -> 1.8790244 | X11: =IF(L11="","", IF(L11<Predictability!$B$1,"Low", IF(L11<=Predictability!$B$2,"Mid","High"))) -> Mid | Y11: =IF(W11>=0.5,1,0) -> 1
A12: 15 Minutes | B12: Robert De Niro | C12: John Herzfeld | D12: 22000 | E12: 33585 | F12: 17 | G12: 748 | H12: 6.1 | I12: 151 | J12: 120 | K12: 24375436 | L12: 42000000 | M12: =VLOOKUP(A12,Sheet2!$A$1:G3736,2,0) -> 36908 | N12: =VLOOKUP(A12,Sheet2!$A$1:G3736,3,0) -> Color | O12: =VLOOKUP(A12,Sheet2!$A$1:G3736,4,0) -> Action | P12: =VLOOKUP(A12,Sheet2!$A$1:G3736,5,0) -> English | Q12: =VLOOKUP(A12,Sheet2!$A$1:G3736,6,0) -> USA | R12: =VLOOKUP(A12,Sheet2!$A$1:G3736,7,0) -> R | S12: =IF(Table1[[#This Row],[Language]]="English","English","Other language") -> English | T12: =Table1[[#This Row],[Gross Revenue]]-Table1[[#This Row],[Budget]] -> -17624564 | U12: =(Table1[[#This Row],[Gross Revenue]]/Table1[[#This Row],[Budget]])-1 -> -0.41963248 | V12: =IF(J12="","",IF(J12<90,"<90 minutes",IF(J12<=110,"90-110 minutes",IF(J12<=130,"111-130 minutes",IF(J12<=150,"131-150 minutes",">150 minutes"))))) -> 111-130 minutes | W12: =Table1[[#This Row],[Profit]]/Table1[[#This Row],[Budget]] -> -0.41963248 | X12: =IF(L12="","", IF(L12<Predictability!$B$1,"Low", IF(L12<=Predictability!$B$2,"Mid","High"))) -> Mid | Y12: =IF(W12>=0.5,1,0) -> 0
A13: 16 Blocks | B13: Bruce Willis | C13: Richard Donner | D13: 13000 | E13: 15053 | F13: 503 | G13: 0 | H13: 6.6 | I13: 199 | J13: 102 | K13: 36883539 | L13: 52000000 | M13: =VLOOKUP(A13,Sheet2!$A$1:G3737,2,0) -> 39029 | N13: =VLOOKUP(A13,Sheet2!$A$1:G3737,3,0) -> Color | O13: =VLOOKUP(A13,Sheet2!$A$1:G3737,4,0) -> Action | P13: =VLOOKUP(A13,Sheet2!$A$1:G3737,5,0) -> English | Q13: =VLOOKUP(A13,Sheet2!$A$1:G3737,6,0) -> Germany | R13: =VLOOKUP(A13,Sheet2!$A$1:G3737,7,0) -> PG-13 | S13: =IF(Table1[[#This Row],[Language]]="English","English","Other language") -> English | T13: =Table1[[#This Row],[Gross Revenue]]-Table1[[#This Row],[Budget]] -> -15116461 | U13: =(Table1[[#This Row],[Gross Revenue]]/Table1[[#This Row],[Budget]])-1 -> -0.29070117 | V13: =IF(J13="","",IF(J13<90,"<90 minutes",IF(J13<=110,"90-110 minutes",IF(J13<=130,"111-130 minutes",IF(J13<=150,"131-150 minutes",">150 minutes"))))) -> 90-110 minutes | W13: =Table1[[#This Row],[Profit]]/Table1[[#This Row],[Budget]] -> -0.29070117 | X13: =IF(L13="","", IF(L13<Predictability!$B$1,"Low", IF(L13<=Predictability!$B$2,"Mid","High"))) -> High | Y13: =IF(W13>=0.5,1,0) -> 0
A14: 17 Again | B14: Matthew Perry | C14: Burr Steers | D14: 2000 | E14: 7009 | F14: 23 | G14: 0 | H14: 6.4 | I14: 191 | J14: 102 | K14: 64149837 | L14: 20000000 | M14: =VLOOKUP(A14,Sheet2!$A$1:G3738,2,0) -> 39958 | N14: =VLOOKUP(A14,Sheet2!$A$1:G3738,3,0) -> Color | O14: =VLOOKUP(A14,Sheet2!$A$1:G3738,4,0) -> Comedy | P14: =VLOOKUP(A14,Sheet2!$A$1:G3738,5,0) -> English | Q14: =VLOOKUP(A14,Sheet2!$A$1:G3738,6,0) -> USA | R14: =VLOOKUP(A14,Sheet2!$A$1:G3738,7,0) -> PG-13 | S14: =IF(Table1[[#This Row],[Language]]="English","English","Other language") -> English | T14: =Table1[[#This Row],[Gross Revenue]]-Table1[[#This Row],[Budget]] -> 44149837 | U14: =(Table1[[#This Row],[Gross Revenue]]/Table1[[#This Row],[Budget]])-1 -> 2.2074918 | V14: =IF(J14="","",IF(J14<90,"<90 minutes",IF(J14<=110,"90-110 minutes",IF(J14<=130,"111-130 minutes",IF(J14<=150,"131-150 minutes",">150 minutes"))))) -> 90-110 minutes | W14: =Table1[[#This Row],[Profit]]/Table1[[#This Row],[Budget]] -> 2.2074918 | X14: =IF(L14="","", IF(L14<Predictability!$B$1,"Low", IF(L14<=Predictability!$B$2,"Mid","High"))) -> Mid | Y14: =IF(W14>=0.5,1,0) -> 1
... A268: Army of Darkness | B268: Patricia Tallman | C268: Sam Raimi | D268: 901 | E268: 3913 | F268: 0 | G268: 10000 | H268: 7.6 | I268: 221 | J268: 88 | K268: 11501093 | L268: 13000000 | M268: =VLOOKUP(A268,Sheet2!$A$1:G3992,2,0) -> 33605 | N268: =VLOOKUP(A268,Sheet2!$A$1:G3992,3,0) -> Color | O268: =VLOOKUP(A268,Sheet2!$A$1:G3992,4,0) -> Comedy | P268: =VLOOKUP(A268,Sheet2!$A$1:G3992,5,0) -> English | Q268: =VLOOKUP(A268,Sheet2!$A$1:G3992,6,0) -> USA | R268: =VLOOKUP(A268,Sheet2!$A$1:G3992,7,0) -> R | S268: =IF(Table1[[#This Row],[Language]]="English","English","Other language") -> English | T268: =Table1[[#This Row],[Gross Revenue]]-Table1[[#This Row],[Budget]] -> -1498907 | U268: =(Table1[[#This Row],[Gross Revenue]]/Table1[[#This Row],[Budget]])-1 -> -0.11530054 | V268: =IF(J268="","",IF(J268<90,"<90 minutes",IF(J268<=110,"90-110 minutes",IF(J268<=130,"111-130 minutes",IF(J268<=150,"131-150 minutes",">150 minutes"))))) -> <90 minutes | W268: =Table1[[#This Row],[Profit]]/Table1[[#This Row],[Budget]] -> -0.11530054 | X268: =IF(L268="","", IF(L268<Predictability!$B$1,"Low", IF(L268<=Predictability!$B$2,"Mid","High"))) -> Mid | Y268: =IF(W268>=0.5,1,0) -> 0
A269: Arnolds Park | B269: Kendyl Joi | C269: Gene Teigland | D269: 23 | E269: 85 | F269: 0 | G269: 11 | H269: 5.6 | J269: 103 | K269: 23616 | L269: 600000 | M269: =VLOOKUP(A269,Sheet2!$A$1:G3993,2,0) -> 39322 | N269: =VLOOKUP(A269,Sheet2!$A$1:G3993,3,0) -> Color | O269: =VLOOKUP(A269,Sheet2!$A$1:G3993,4,0) -> Mystery | P269: =VLOOKUP(A269,Sheet2!$A$1:G3993,5,0) -> English | Q269: =VLOOKUP(A269,Sheet2!$A$1:G3993,6,0) -> USA | R269: =VLOOKUP(A269,Sheet2!$A$1:G3993,7,0) -> PG-13 | S269: =IF(Table1[[#This Row],[Language]]="English","English","Other language") -> English | T269: =Table1[[#This Row],[Gross Revenue]]-Table1[[#This Row],[Budget]] -> -576384 | U269: =(Table1[[#This Row],[Gross Revenue]]/Table1[[#This Row],[Budget]])-1 -> -0.96064 | V269: =IF(J269="","",IF(J269<90,"<90 minutes",IF(J269<=110,"90-110 minutes",IF(J269<=130,"111-130 minutes",IF(J269<=150,"131-150 minutes",">150 minutes"))))) -> 90-110 minutes | W269: =Table1[[#This Row],[Profit]]/Table1[[#This Row],[Budget]] -> -0.96064 | X269: =IF(L269="","", IF(L269<Predictability!$B$1,"Low", IF(L269<=Predictability!$B$2,"Mid","High"))) -> Low | Y269: =IF(W269>=0.5,1,0) -> 0
A270: Around the World in 80 Days | B270: Jim Broadbent | C270: Frank Coraci | D270: 1000 | E270: 3175 | F270: 153 | G270: 0 | H270: 5.8 | I270: 188 | J270: 120 | K270: 24004159 | L270: 110000000 | M270: =VLOOKUP(A270,Sheet2!$A$1:G3994,2,0) -> 38020 | N270: =VLOOKUP(A270,Sheet2!$A$1:G3994,3,0) -> Color | O270: =VLOOKUP(A270,Sheet2!$A$1:G3994,4,0) -> Action | P270: =VLOOKUP(A270,Sheet2!$A$1:G3994,5,0) -> English | Q270: =VLOOKUP(A270,Sheet2!$A$1:G3994,6,0) -> USA | R270: =VLOOKUP(A270,Sheet2!$A$1:G3994,7,0) -> PG | S270: =IF(Table1[[#This Row],[Language]]="English","English","Other language") -> English | T270: =Table1[[#This Row],[Gross Revenue]]-Table1[[#This Row],[Budget]] -> -85995841 | U270: =(Table1[[#This Row],[Gross Revenue]]/Table1[[#This Row],[Budget]])-1 -> -0.78178037 | V270: =IF(J270="","",IF(J270<90,"<90 minutes",IF(J270<=110,"90-110 minutes",IF(J270<=130,"111-130 minutes",IF(J270<=150,"131-150 minutes",">150 minutes"))))) -> 111-130 minutes | W270: =Table1[[#This Row],[Profit]]/Table1[[#This Row],[Budget]] -> -0.78178037 | X270: =IF(L270="","", IF(L270<Predictability!$B$1,"Low", IF(L270<=Predictability!$B$2,"Mid","High"))) -> High | Y270: =IF(W270>=0.5,1,0) -> 0
A271: Arthur and the Invisibles | B271: Mia Farrow | C271: Luc Besson | D271: 563 | E271: 683 | F271: 0 | G271: 941 | H271: 6 | I271: 101 | J271: 94 | K271: 15131330 | L271: 86000000 | M271: =VLOOKUP(A271,Sheet2!$A$1:G3995,2,0) -> 39041 | N271: =VLOOKUP(A271,Sheet2!$A$1:G3995,3,0) -> Color | O271: =VLOOKUP(A271,Sheet2!$A$1:G3995,4,0) -> Adventure | P271: =VLOOKUP(A271,Sheet2!$A$1:G3995,5,0) -> English | Q271: =VLOOKUP(A271,Sheet2!$A$1:G3995,6,0) -> France | R271: =VLOOKUP(A271,Sheet2!$A$1:G3995,7,0) -> PG | S271: =IF(Table1[[#This Row],[Language]]="English","English","Other language") -> English | T271: =Table1[[#This Row],[Gross Revenue]]-Table1[[#This Row],[Budget]] -> -70868670 | U271: =(Table1[[#This Row],[Gross Revenue]]/Table1[[#This Row],[Budget]])-1 -> -0.8240543 | V271: =IF(J271="","",IF(J271<90,"<90 minutes",IF(J271<=110,"90-110 minutes",IF(J271<=130,"111-130 minutes",IF(J271<=150,"131-150 minutes",">150 minutes"))))) -> 90-110 minutes | W271: =Table1[[#This Row],[Profit]]/Table1[[#This Row],[Budget]] -> -0.8240543 | X271: =IF(L271="","", IF(L271<Predictability!$B$1,"Low", IF(L271<=Predictability!$B$2,"Mid","High"))) -> High | Y271: =IF(W271>=0.5,1,0) -> 0
A272: Arthur Christmas | B272: Jim Broadbent | C272: Sarah Smith | D272: 1000 | E272: 2707 | F272: 6 | G272: 0 | H272: 7.1 | I272: 190 | J272: 97 | K272: 46440491 | L272: 100000000 | M272: =VLOOKUP(A272,Sheet2!$A$1:G3996,2,0) -> 40761 | N272: =VLOOKUP(A272,Sheet2!$A$1:G3996,3,0) -> Color | O272: =VLOOKUP(A272,Sheet2!$A$1:G3996,4,0) -> Adventure | P272: =VLOOKUP(A272,Sheet2!$A$1:G3996,5,0) -> English | Q272: =VLOOKUP(A272,Sheet2!$A$1:G3996,6,0) -> UK | R272: =VLOOKUP(A272,Sheet2!$A$1:G3996,7,0) -> PG | S272: =IF(Table1[[#This Row],[Language]]="English","English","Other language") -> English | T272: =Table1[[#This Row],[Gross Revenue]]-Table1[[#This Row],[Budget]] -> -53559509 | U272: =(Table1[[#This Row],[Gross Revenue]]/Table1[[#This Row],[Budget]])-1 -> -0.53559509 | V272: =IF(J272="","",IF(J272<90,"<90 minutes",IF(J272<=110,"90-110 minutes",IF(J272<=130,"111-130 minutes",IF(J272<=150,"131-150 minutes",">150 minutes"))))) -> 90-110 minutes | W272: =Table1[[#This Row],[Profit]]/Table1[[#This Row],[Budget]] -> -0.53559509 | X272: =IF(L272="","", IF(L272<Predictability!$B$1,"Low", IF(L272<=Predictability!$B$2,"Mid","High"))) -> High | Y272: =IF(W272>=0.5,1,0) -> 0
A273: As Above, So Below | B273: Ben Feldman | C273: John Erick Dowdle | D273: 1000 | E273: 1410 | F273: 66 | G273: 14000 | H273: 6.1 | I273: 196 | J273: 93 | K273: 21197315 | L273: 5000000 | M273: =VLOOKUP(A273,Sheet2!$A$1:G3997,2,0) -> 41977 | N273: =VLOOKUP(A273,Sheet2!$A$1:G3997,3,0) -> Color | O273: =VLOOKUP(A273,Sheet2!$A$1:G3997,4,0) -> Horror | P273: =VLOOKUP(A273,Sheet2!$A$1:G3997,5,0) -> English | Q273: =VLOOKUP(A273,Sheet2!$A$1:G3997,6,0) -> USA | R273: =VLOOKUP(A273,Sheet2!$A$1:G3997,7,0) -> R | S273: =IF(Table1[[#This Row],[Language]]="English","English","Other language") -> English | T273: =Table1[[#This Row],[Gross Revenue]]-Table1[[#This Row],[Budget]] -> 16197315 | U273: =(Table1[[#This Row],[Gross Revenue]]/Table1[[#This Row],[Budget]])-1 -> 3.239463 | V273: =IF(J273="","",IF(J273<90,"<90 minutes",IF(J273<=110,"90-110 minutes",IF(J273<=130,"111-130 minutes",IF(J273<=150,"131-150 minutes",">150 minutes"))))) -> 90-110 minutes | W273: =Table1[[#This Row],[Profit]]/Table1[[#This Row],[Budget]] -> 3.239463 | X273: =IF(L273="","", IF(L273<Predictability!$B$1,"Low", IF(L273<=Predictability!$B$2,"Mid","High"))) -> Low | Y273: =IF(W273>=0.5,1,0) -> 1
A274: As Good as It Gets | B274: Lupe Ontiveros | C274: James L. Brooks | D274: 625 | E274: 1474 | F274: 274 | G274: 11000 | H274: 7.7 | I274: 156 | J274: 139 | K274: 147637474 | L274: 50000000 | M274: =VLOOKUP(A274,Sheet2!$A$1:G3998,2,0) -> 35778 | N274: =VLOOKUP(A274,Sheet2!$A$1:G3998,3,0) -> Color | O274: =VLOOKUP(A274,Sheet2!$A$1:G3998,4,0) -> Comedy | P274: =VLOOKUP(A274,Sheet2!$A$1:G3998,5,0) -> English | Q274: =VLOOKUP(A274,Sheet2!$A$1:G3998,6,0) -> USA | R274: =VLOOKUP(A274,Sheet2!$A$1:G3998,7,0) -> PG-13 | S274: =IF(Table1[[#This Row],[Language]]="English","English","Other language") -> English | T274: =Table1[[#This Row],[Gross Revenue]]-Table1[[#This Row],[Budget]] -> 97637474 | U274: =(Table1[[#This Row],[Gross Revenue]]/Table1[[#This Row],[Budget]])-1 -> 1.9527495 | V274: =IF(J274="","",IF(J274<90,"<90 minutes",IF(J274<=110,"90-110 minutes",IF(J274<=130,"111-130 minutes",IF(J274<=150,"131-150 minutes",">150 minutes"))))) -> 131-150 minutes | W274: =Table1[[#This Row],[Profit]]/Table1[[#This Row],[Budget]] -> 1.9527495 | X274: =IF(L274="","", IF(L274<Predictability!$B$1,"Low", IF(L274<=Predictability!$B$2,"Mid","High"))) -> Mid | Y274: =IF(W274>=0.5,1,0) -> 1
A275: As It Is in Heaven | B275: Michael Nyqvist | C275: Kay Pollak | D275: 690 | E275: 774 | F275: 10 | G275: 0 | H275: 7.6 | I275: 34 | J275: 133 | K275: 9910 | L275: 25000000 | M275: =VLOOKUP(A275,Sheet2!$A$1:G3999,2,0) -> 38117 | N275: =VLOOKUP(A275,Sheet2!$A$1:G3999,3,0) -> Color | O275: =VLOOKUP(A275,Sheet2!$A$1:G3999,4,0) -> Comedy | P275: =VLOOKUP(A275,Sheet2!$A$1:G3999,5,0) -> Swedish | Q275: =VLOOKUP(A275,Sheet2!$A$1:G3999,6,0) -> Sweden | R275: =VLOOKUP(A275,Sheet2!$A$1:G3999,7,0) -> 0 | S275: =IF(Table1[[#This Row],[Language]]="English","English","Other language") -> Other language | T275: =Table1[[#This Row],[Gross Revenue]]-Table1[[#This Row],[Budget]] -> -24990090 | U275: =(Table1[[#This Row],[Gross Revenue]]/Table1[[#This Row],[Budget]])-1 -> -0.9996036 | V275: =IF(J275="","",IF(J275<90,"<90 minutes",IF(J275<=110,"90-110 minutes",IF(J275<=130,"111-130 minutes",IF(J275<=150,"131-150 minutes",">150 minutes"))))) -> 131-150 minutes | W275: =Table1[[#This Row],[Profit]]/Table1[[#This Row],[Budget]] -> -0.9996036 | X275: =IF(L275="","", IF(L275<Predictability!$B$1,"Low", IF(L275<=Predictability!$B$2,"Mid","High"))) -> Mid | Y275: =IF(W275>=0.5,1,0) -> 0
A276: Assassins | B276: Muse Watson | C276: Richard Donner | D276: 45000 | E276: 58528 | F276: 503 | G276: 0 | H276: 6.3 | I276: 61 | J276: 132 | K276: 30306268 | L276: 50000000 | M276: =VLOOKUP(A276,Sheet2!$A$1:G4000,2,0) -> 34751 | N276: =VLOOKUP(A276,Sheet2!$A$1:G4000,3,0) -> Black and White | O276: =VLOOKUP(A276,Sheet2!$A$1:G4000,4,0) -> Action | P276: =VLOOKUP(A276,Sheet2!$A$1:G4000,5,0) -> English | Q276: =VLOOKUP(A276,Sheet2!$A$1:G4000,6,0) -> France | R276: =VLOOKUP(A276,Sheet2!$A$1:G4000,7,0) -> R | S276: =IF(Table1[[#This Row],[Language]]="English","English","Other language") -> English | T276: =Table1[[#This Row],[Gross Revenue]]-Table1[[#This Row],[Budget]] -> -19693732 | U276: =(Table1[[#This Row],[Gross Revenue]]/Table1[[#This Row],[Budget]])-1 -> -0.39387464 | V276: =IF(J276="","",IF(J276<90,"<90 minutes",IF(J276<=110,"90-110 minutes",IF(J276<=130,"111-130 minutes",IF(J276<=150,"131-150 minutes",">150 minutes"))))) -> 131-150 minutes | W276: =Table1[[#This Row],[Profit]]/Table1[[#This Row],[Budget]] -> -0.39387464 | X276: =IF(L276="","", IF(L276<Predictability!$B$1,"Low", IF(L276<=Predictability!$B$2,"Mid","High"))) -> Mid | Y276: =IF(W276>=0.5,1,0) -> 0
A277: Assault on Precinct 13 | B277: Brian Dennehy | C277: Jean-FranÃ§ois Richet | D277: 954 | E277: 3148 | F277: 25 | G277: 999 | H277: 6.3 | I277: 152 | J277: 109 | K277: 19976073 | L277: 20000000 | M277: =VLOOKUP(A277,Sheet2!$A$1:G4001,2,0) -> 38390 | N277: =VLOOKUP(A277,Sheet2!$A$1:G4001,3,0) -> Color | O277: =VLOOKUP(A277,Sheet2!$A$1:G4001,4,0) -> Action | P277: =VLOOKUP(A277,Sheet2!$A$1:G4001,5,0) -> English | Q277: =VLOOKUP(A277,Sheet2!$A$1:G4001,6,0) -> USA | R277: =VLOOKUP(A277,Sheet2!$A$1:G4001,7,0) -> R | S277: =IF(Table1[[#This Row],[Language]]="English","English","Other language") -> English | T277: =Table1[[#This Row],[Gross Revenue]]-Table1[[#This Row],[Budget]] -> -23927 | U277: =(Table1[[#This Row],[Gross Revenue]]/Table1[[#This Row],[Budget]])-1 -> -0.00119635 | V277: =IF(J277="","",IF(J277<90,"<90 minutes",IF(J277<=110,"90-110 minutes",IF(J277<=130,"111-130 minutes",IF(J277<=150,"131-150 minutes",">150 minutes"))))) -> 90-110 minutes | W277: =Table1[[#This Row],[Profit]]/Table1[[#This Row],[Budget]] -> -0.00119635 | X277: =IF(L277="","", IF(L277<Predictability!$B$1,"Low", IF(L277<=Predictability!$B$2,"Mid","High"))) -> Mid | Y277: =IF(W277>=0.5,1,0) -> 0
A278: Astro Boy | B278: Nicolas Cage | C278: David Bowers | D278: 12000 | E278: 23365 | F278: 42 | G278: 0 | H278: 6.3 | I278: 138 | J278: 94 | K278: 19548064 | L278: 65000000 | M278: =VLOOKUP(A278,Sheet2!$A$1:G4002,2,0) -> 39881 | N278: =VLOOKUP(A278,Sheet2!$A$1:G4002,3,0) -> Color | O278: =VLOOKUP(A278,Sheet2!$A$1:G4002,4,0) -> Action | P278: =VLOOKUP(A278,Sheet2!$A$1:G4002,5,0) -> English | Q278: =VLOOKUP(A278,Sheet2!$A$1:G4002,6,0) -> Hong Kong | R278: =VLOOKUP(A278,Sheet2!$A$1:G4002,7,0) -> PG | S278: =IF(Table1[[#This Row],[Language]]="English","English","Other language") -> English | T278: =Table1[[#This Row],[Gross Revenue]]-Table1[[#This Row],[Budget]] -> -45451936 | U278: =(Table1[[#This Row],[Gross Revenue]]/Table1[[#This Row],[Budget]])-1 -> -0.69926055 | V278: =IF(J278="","",IF(J278<90,"<90 minutes",IF(J278<=110,"90-110 minutes",IF(J278<=130,"111-130 minutes",IF(J278<=150,"131-150 minutes",">150 minutes"))))) -> 90-110 minutes | W278: =Table1[[#This Row],[Profit]]/Table1[[#This Row],[Budget]] -> -0.69926055 | X278: =IF(L278="","", IF(L278<Predictability!$B$1,"Low", IF(L278<=Predictability!$B$2,"Mid","High"))) -> High | Y278: =IF(W278>=0.5,1,0) -> 0
A279: At First Sight | B279: Mira Sorvino | C279: Irwin Winkler | D279: 978 | E279: 3821 | F279: 34 | G279: 0 | H279: 5.9 | I279: 55 | J279: 128 | K279: 22326247 | L279: 60000000 | M279: =VLOOKUP(A279,Sheet2!$A$1:G4003,2,0) -> 36284 | N279: =VLOOKUP(A279,Sheet2!$A$1:G4003,3,0) -> Black and White | O279: =VLOOKUP(A279,Sheet2!$A$1:G4003,4,0) -> Drama | P279: =VLOOKUP(A279,Sheet2!$A$1:G4003,5,0) -> English | Q279: =VLOOKUP(A279,Sheet2!$A$1:G4003,6,0) -> USA | R279: =VLOOKUP(A279,Sheet2!$A$1:G4003,7,0) -> PG-13 | S279: =IF(Table1[[#This Row],[Language]]="English","English","Other language") -> English | T279: =Table1[[#This Row],[Gross Revenue]]-Table1[[#This Row],[Budget]] -> -37673753 | U279: =(Table1[[#This Row],[Gross Revenue]]/Table1[[#This Row],[Budget]])-1 -> -0.62789588 | V279: =IF(J279="","",IF(J279<90,"<90 minutes",IF(J279<=110,"90-110 minutes",IF(J279<=130,"111-130 minutes",IF(J279<=150,"131-150 minutes",">150 minutes"))))) -> 111-130 minutes | W279: =Table1[[#This Row],[Profit]]/Table1[[#This Row],[Budget]] -> -0.62789588 | X279: =IF(L279="","", IF(L279<Predictability!$B$1,"Low", IF(L279<=Predictability!$B$2,"Mid","High"))) -> High | Y279: =IF(W279>=0.5,1,0) -> 0
A280: Atlantis: The Lost Empire | B280: Leonard Nimoy | C280: Gary Trousdale | D280: 12000 | E280: 15237 | F280: 21 | G280: 0 | H280: 6.8 | I280: 146 | J280: 95 | K280: 84037039 | L280: 120000000 | M280: =VLOOKUP(A280,Sheet2!$A$1:G4004,2,0) -> 37085 | N280: =VLOOKUP(A280,Sheet2!$A$1:G4004,3,0) -> Color | O280: =VLOOKUP(A280,Sheet2!$A$1:G4004,4,0) -> Action | P280: =VLOOKUP(A280,Sheet2!$A$1:G4004,5,0) -> English | Q280: =VLOOKUP(A280,Sheet2!$A$1:G4004,6,0) -> USA | R280: =VLOOKUP(A280,Sheet2!$A$1:G4004,7,0) -> PG | S280: =IF(Table1[[#This Row],[Language]]="English","English","Other language") -> English | T280: =Table1[[#This Row],[Gross Revenue]]-Table1[[#This Row],[Budget]] -> -35962961 | U280: =(Table1[[#This Row],[Gross Revenue]]/Table1[[#This Row],[Budget]])-1 -> -0.29969134 | V280: =IF(J280="","",IF(J280<90,"<90 minutes",IF(J280<=110,"90-110 minutes",IF(J280<=130,"111-130 minutes",IF(J280<=150,"131-150 minutes",">150 minutes"))))) -> 90-110 minutes | W280: =Table1[[#This Row],[Profit]]/Table1[[#This Row],[Budget]] -> -0.29969134 | X280: =IF(L280="","", IF(L280<Predictability!$B$1,"Low", IF(L280<=Predictability!$B$2,"Mid","High"))) -> High | Y280: =IF(W280>=0.5,1,0) -> 0
A281: Atlas Shrugged II: The Strike | B281: Robert Picardo | C281: John Putch | D281: 823 | E281: 5262 | F281: 60 | G281: 0 | H281: 5.5 | I281: 23 | J281: 111 | K281: 3333823 | L281: 10000000 | M281: =VLOOKUP(A281,Sheet2!$A$1:G4005,2,0) -> 41026 | N281: =VLOOKUP(A281,Sheet2!$A$1:G4005,3,0) -> Color | O281: =VLOOKUP(A281,Sheet2!$A$1:G4005,4,0) -> Drama | P281: =VLOOKUP(A281,Sheet2!$A$1:G4005,5,0) -> English | Q281: =VLOOKUP(A281,Sheet2!$A$1:G4005,6,0) -> USA | R281: =VLOOKUP(A281,Sheet2!$A$1:G4005,7,0) -> PG-13 | S281: =IF(Table1[[#This Row],[Language]]="English","English","Other language") -> English | T281: =Table1[[#This Row],[Gross Revenue]]-Table1[[#This Row],[Budget]] -> -6666177 | U281: =(Table1[[#This Row],[Gross Revenue]]/Table1[[#This Row],[Budget]])-1 -> -0.6666177 | V281: =IF(J281="","",IF(J281<90,"<90 minutes",IF(J281<=110,"90-110 minutes",IF(J281<=130,"111-130 minutes",IF(J281<=150,"131-150 minutes",">150 minutes"))))) -> 111-130 minutes | W281: =Table1[[#This Row],[Profit]]/Table1[[#This Row],[Budget]] -> -0.6666177 | X281: =IF(L281="","", IF(L281<Predictability!$B$1,"Low", IF(L281<=Predictability!$B$2,"Mid","High"))) -> Mid | Y281: =IF(W281>=0.5,1,0) -> 0
... A297: Away We Go | B297: Catherine O'Hara | C297: Sam Mendes | D297: 925 | E297: 1997 | F297: 0 | G297: 7000 | H297: 7.1 | I297: 217 | J297: 98 | K297: 9430988 | L297: 17000000 | M297: =VLOOKUP(A297,Sheet2!$A$1:G4021,2,0) -> 40118 | N297: =VLOOKUP(A297,Sheet2!$A$1:G4021,3,0) -> Color | O297: =VLOOKUP(A297,Sheet2!$A$1:G4021,4,0) -> Comedy | P297: =VLOOKUP(A297,Sheet2!$A$1:G4021,5,0) -> English | Q297: =VLOOKUP(A297,Sheet2!$A$1:G4021,6,0) -> USA | R297: =VLOOKUP(A297,Sheet2!$A$1:G4021,7,0) -> R | S297: =IF(Table1[[#This Row],[Language]]="English","English","Other language") -> English | T297: =Table1[[#This Row],[Gross Revenue]]-Table1[[#This Row],[Budget]] -> -7569012 | U297: =(Table1[[#This Row],[Gross Revenue]]/Table1[[#This Row],[Budget]])-1 -> -0.445236 | V297: =IF(J297="","",IF(J297<90,"<90 minutes",IF(J297<=110,"90-110 minutes",IF(J297<=130,"111-130 minutes",IF(J297<=150,"131-150 minutes",">150 minutes"))))) -> 90-110 minutes | W297: =Table1[[#This Row],[Profit]]/Table1[[#This Row],[Budget]] -> -0.445236 | X297: =IF(L297="","", IF(L297<Predictability!$B$1,"Low", IF(L297<=Predictability!$B$2,"Mid","High"))) -> Mid | Y297: =IF(W297>=0.5,1,0) -> 0
A298: Ayurveda: Art of Being | C298: Pan Nalin | E298: 0 | F298: 95 | G298: 379 | H298: 7.6 | I298: 15 | J298: 102 | K298: 16892 | L298: 300000 | M298: =VLOOKUP(A298,Sheet2!$A$1:G4022,2,0) -> 37138 | N298: =VLOOKUP(A298,Sheet2!$A$1:G4022,3,0) -> Color | O298: =VLOOKUP(A298,Sheet2!$A$1:G4022,4,0) -> Documentary | P298: =VLOOKUP(A298,Sheet2!$A$1:G4022,5,0) -> English | Q298: =VLOOKUP(A298,Sheet2!$A$1:G4022,6,0) -> India | R298: =VLOOKUP(A298,Sheet2!$A$1:G4022,7,0) -> 0 | S298: =IF(Table1[[#This Row],[Language]]="English","English","Other language") -> English | T298: =Table1[[#This Row],[Gross Revenue]]-Table1[[#This Row],[Budget]] -> -283108 | U298: =(Table1[[#This Row],[Gross Revenue]]/Table1[[#This Row],[Budget]])-1 -> -0.94369333 | V298: =IF(J298="","",IF(J298<90,"<90 minutes",IF(J298<=110,"90-110 minutes",IF(J298<=130,"111-130 minutes",IF(J298<=150,"131-150 minutes",">150 minutes"))))) -> 90-110 minutes | W298: =Table1[[#This Row],[Profit]]/Table1[[#This Row],[Budget]] -> -0.94369333 | X298: =IF(L298="","", IF(L298<Predictability!$B$1,"Low", IF(L298<=Predictability!$B$2,"Mid","High"))) -> Low | Y298: =IF(W298>=0.5,1,0) -> 0
A299: Baahubali: The Beginning | B299: Tamannaah Bhatia | C299: S.S. Rajamouli | D299: 218 | E299: 554 | F299: 50 | G299: 21000 | H299: 8.4 | I299: 44 | J299: 159 | K299: 6498000 | L299: 18026148 | M299: =VLOOKUP(A299,Sheet2!$A$1:G4023,2,0) -> 42182 | N299: =VLOOKUP(A299,Sheet2!$A$1:G4023,3,0) -> Color | O299: =VLOOKUP(A299,Sheet2!$A$1:G4023,4,0) -> Action | P299: =VLOOKUP(A299,Sheet2!$A$1:G4023,5,0) -> Telugu | Q299: =VLOOKUP(A299,Sheet2!$A$1:G4023,6,0) -> India | R299: =VLOOKUP(A299,Sheet2!$A$1:G4023,7,0) -> 0 | S299: =IF(Table1[[#This Row],[Language]]="English","English","Other language") -> Other language | T299: =Table1[[#This Row],[Gross Revenue]]-Table1[[#This Row],[Budget]] -> -11528148 | U299: =(Table1[[#This Row],[Gross Revenue]]/Table1[[#This Row],[Budget]])-1 -> -0.63952365 | V299: =IF(J299="","",IF(J299<90,"<90 minutes",IF(J299<=110,"90-110 minutes",IF(J299<=130,"111-130 minutes",IF(J299<=150,"131-150 minutes",">150 minutes"))))) -> >150 minutes | W299: =Table1[[#This Row],[Profit]]/Table1[[#This Row],[Budget]] -> -0.63952365 | X299: =IF(L299="","", IF(L299<Predictability!$B$1,"Low", IF(L299<=Predictability!$B$2,"Mid","High"))) -> Mid | Y299: =IF(W299>=0.5,1,0) -> 0
A300: Babe | B300: Miriam Margolyes | C300: Chris Noonan | D300: 405 | E300: 1185 | F300: 108 | G300: 5000 | H300: 6.8 | I300: 79 | J300: 91 | K300: 66600000 | L300: 30000000 | M300: =VLOOKUP(A300,Sheet2!$A$1:G4024,2,0) -> 34858 | N300: =VLOOKUP(A300,Sheet2!$A$1:G4024,3,0) -> Color | O300: =VLOOKUP(A300,Sheet2!$A$1:G4024,4,0) -> Comedy | P300: =VLOOKUP(A300,Sheet2!$A$1:G4024,5,0) -> English | Q300: =VLOOKUP(A300,Sheet2!$A$1:G4024,6,0) -> Australia | R300: =VLOOKUP(A300,Sheet2!$A$1:G4024,7,0) -> G | S300: =IF(Table1[[#This Row],[Language]]="English","English","Other language") -> English | T300: =Table1[[#This Row],[Gross Revenue]]-Table1[[#This Row],[Budget]] -> 36600000 | U300: =(Table1[[#This Row],[Gross Revenue]]/Table1[[#This Row],[Budget]])-1 -> 1.22 | V300: =IF(J300="","",IF(J300<90,"<90 minutes",IF(J300<=110,"90-110 minutes",IF(J300<=130,"111-130 minutes",IF(J300<=150,"131-150 minutes",">150 minutes"))))) -> 90-110 minutes | W300: =Table1[[#This Row],[Profit]]/Table1[[#This Row],[Budget]] -> 1.22 | X300: =IF(L300="","", IF(L300<Predictability!$B$1,"Low", IF(L300<=Predictability!$B$2,"Mid","High"))) -> Mid | Y300: =IF(W300>=0.5,1,0) -> 1
A301: Babe: Pig in the City | B301: Adam Goldberg | C301: George Miller | D301: 1000 | E301: 2521 | F301: 750 | G301: 964 | H301: 5.8 | I301: 61 | J301: 97 | K301: 18318000 | L301: 80000000 | M301: =VLOOKUP(A301,Sheet2!$A$1:G4025,2,0) -> 35864 | N301: =VLOOKUP(A301,Sheet2!$A$1:G4025,3,0) -> Color | O301: =VLOOKUP(A301,Sheet2!$A$1:G4025,4,0) -> Adventure | P301: =VLOOKUP(A301,Sheet2!$A$1:G4025,5,0) -> English | Q301: =VLOOKUP(A301,Sheet2!$A$1:G4025,6,0) -> Australia | R301: =VLOOKUP(A301,Sheet2!$A$1:G4025,7,0) -> G | S301: =IF(Table1[[#This Row],[Language]]="English","English","Other language") -> English | T301: =Table1[[#This Row],[Gross Revenue]]-Table1[[#This Row],[Budget]] -> -61682000 | U301: =(Table1[[#This Row],[Gross Revenue]]/Table1[[#This Row],[Budget]])-1 -> -0.771025 | V301: =IF(J301="","",IF(J301<90,"<90 minutes",IF(J301<=110,"90-110 minutes",IF(J301<=130,"111-130 minutes",IF(J301<=150,"131-150 minutes",">150 minutes"))))) -> 90-110 minutes | W301: =Table1[[#This Row],[Profit]]/Table1[[#This Row],[Budget]] -> -0.771025 | X301: =IF(L301="","", IF(L301<Predictability!$B$1,"Low", IF(L301<=Predictability!$B$2,"Mid","High"))) -> High | Y301: =IF(W301>=0.5,1,0) -> 0
A302: Babel | B302: Brad Pitt | C302: Alejandro G. IÃ±Ã¡rritu | D302: 11000 | E302: 11248 | F302: 0 | G302: 0 | H302: 7.5 | I302: 285 | J302: 143 | K302: 34300771 | L302: 25000000 | M302: =VLOOKUP(A302,Sheet2!$A$1:G4026,2,0) -> 38804 | N302: =VLOOKUP(A302,Sheet2!$A$1:G4026,3,0) -> Color | O302: =VLOOKUP(A302,Sheet2!$A$1:G4026,4,0) -> Drama | P302: =VLOOKUP(A302,Sheet2!$A$1:G4026,5,0) -> English | Q302: =VLOOKUP(A302,Sheet2!$A$1:G4026,6,0) -> France | R302: =VLOOKUP(A302,Sheet2!$A$1:G4026,7,0) -> R | S302: =IF(Table1[[#This Row],[Language]]="English","English","Other language") -> English | T302: =Table1[[#This Row],[Gross Revenue]]-Table1[[#This Row],[Budget]] -> 9300771 | U302: =(Table1[[#This Row],[Gross Revenue]]/Table1[[#This Row],[Budget]])-1 -> 0.37203084 | V302: =IF(J302="","",IF(J302<90,"<90 minutes",IF(J302<=110,"90-110 minutes",IF(J302<=130,"111-130 minutes",IF(J302<=150,"131-150 minutes",">150 minutes"))))) -> 131-150 minutes | W302: =Table1[[#This Row],[Profit]]/Table1[[#This Row],[Budget]] -> 0.37203084 | X302: =IF(L302="","", IF(L302<Predictability!$B$1,"Low", IF(L302<=Predictability!$B$2,"Mid","High"))) -> Mid | Y302: =IF(W302>=0.5,1,0) -> 0
A303: Baby Boy | B303: Mo'Nique | C303: John Singleton | D303: 939 | E303: 3107 | F303: 309 | G303: 1000 | H303: 6.4 | I303: 41 | J303: 130 | K303: 28734552 | L303: 16000000 | M303: =VLOOKUP(A303,Sheet2!$A$1:G4027,2,0) -> 37100 | N303: =VLOOKUP(A303,Sheet2!$A$1:G4027,3,0) -> Black and White | O303: =VLOOKUP(A303,Sheet2!$A$1:G4027,4,0) -> Crime | P303: =VLOOKUP(A303,Sheet2!$A$1:G4027,5,0) -> English | Q303: =VLOOKUP(A303,Sheet2!$A$1:G4027,6,0) -> USA | R303: =VLOOKUP(A303,Sheet2!$A$1:G4027,7,0) -> R | S303: =IF(Table1[[#This Row],[Language]]="English","English","Other language") -> English | T303: =Table1[[#This Row],[Gross Revenue]]-Table1[[#This Row],[Budget]] -> 12734552 | U303: =(Table1[[#This Row],[Gross Revenue]]/Table1[[#This Row],[Budget]])-1 -> 0.7959095 | V303: =IF(J303="","",IF(J303<90,"<90 minutes",IF(J303<=110,"90-110 minutes",IF(J303<=130,"111-130 minutes",IF(J303<=150,"131-150 minutes",">150 minutes"))))) -> 111-130 minutes | W303: =Table1[[#This Row],[Profit]]/Table1[[#This Row],[Budget]] -> 0.7959095 | X303: =IF(L303="","", IF(L303<Predictability!$B$1,"Low", IF(L303<=Predictability!$B$2,"Mid","High"))) -> Mid | Y303: =IF(W303>=0.5,1,0) -> 1
A304: Baby Geniuses | B304: Kathleen Turner | C304: Bob Clark | D304: 899 | E304: 2936 | F304: 84 | G304: 0 | H304: 2.5 | I304: 45 | J304: 97 | K304: 27141959 | L304: 18000000 | M304: =VLOOKUP(A304,Sheet2!$A$1:G4028,2,0) -> 36362 | N304: =VLOOKUP(A304,Sheet2!$A$1:G4028,3,0) -> Color | O304: =VLOOKUP(A304,Sheet2!$A$1:G4028,4,0) -> Comedy | P304: =VLOOKUP(A304,Sheet2!$A$1:G4028,5,0) -> English | Q304: =VLOOKUP(A304,Sheet2!$A$1:G4028,6,0) -> USA | R304: =VLOOKUP(A304,Sheet2!$A$1:G4028,7,0) -> PG | S304: =IF(Table1[[#This Row],[Language]]="English","English","Other language") -> English | T304: =Table1[[#This Row],[Gross Revenue]]-Table1[[#This Row],[Budget]] -> 9141959 | U304: =(Table1[[#This Row],[Gross Revenue]]/Table1[[#This Row],[Budget]])-1 -> 0.50788661 | V304: =IF(J304="","",IF(J304<90,"<90 minutes",IF(J304<=110,"90-110 minutes",IF(J304<=130,"111-130 minutes",IF(J304<=150,"131-150 minutes",">150 minutes"))))) -> 90-110 minutes | W304: =Table1[[#This Row],[Profit]]/Table1[[#This Row],[Budget]] -> 0.50788661 | X304: =IF(L304="","", IF(L304<Predictability!$B$1,"Low", IF(L304<=Predictability!$B$2,"Mid","High"))) -> Mid | Y304: =IF(W304>=0.5,1,0) -> 1
A305: Baby Mama | B305: Tina Fey | C305: Michael McCullers | D305: 2000 | E305: 6930 | F305: 5 | G305: 0 | H305: 6 | I305: 145 | J305: 99 | K305: 60269340 | L305: 30000000 | M305: =VLOOKUP(A305,Sheet2!$A$1:G4029,2,0) -> 39645 | N305: =VLOOKUP(A305,Sheet2!$A$1:G4029,3,0) -> Color | O305: =VLOOKUP(A305,Sheet2!$A$1:G4029,4,0) -> Comedy | P305: =VLOOKUP(A305,Sheet2!$A$1:G4029,5,0) -> English | Q305: =VLOOKUP(A305,Sheet2!$A$1:G4029,6,0) -> USA | R305: =VLOOKUP(A305,Sheet2!$A$1:G4029,7,0) -> PG-13 | S305: =IF(Table1[[#This Row],[Language]]="English","English","Other language") -> English | T305: =Table1[[#This Row],[Gross Revenue]]-Table1[[#This Row],[Budget]] -> 30269340 | U305: =(Table1[[#This Row],[Gross Revenue]]/Table1[[#This Row],[Budget]])-1 -> 1.008978 | V305: =IF(J305="","",IF(J305<90,"<90 minutes",IF(J305<=110,"90-110 minutes",IF(J305<=130,"111-130 minutes",IF(J305<=150,"131-150 minutes",">150 minutes"))))) -> 90-110 minutes | W305: =Table1[[#This Row],[Profit]]/Table1[[#This Row],[Budget]] -> 1.008978 | X305: =IF(L305="","", IF(L305<Predictability!$B$1,"Low", IF(L305<=Predictability!$B$2,"Mid","High"))) -> Mid | Y305: =IF(W305>=0.5,1,0) -> 1
A306: Babylon A.D. | B306: Vin Diesel | C306: Mathieu Kassovitz | D306: 14000 | E306: 15990 | F306: 326 | G306: 0 | H306: 5.6 | I306: 164 | J306: 101 | K306: 22531698 | L306: 70000000 | M306: =VLOOKUP(A306,Sheet2!$A$1:G4030,2,0) -> 39601 | N306: =VLOOKUP(A306,Sheet2!$A$1:G4030,3,0) -> Color | O306: =VLOOKUP(A306,Sheet2!$A$1:G4030,4,0) -> Action | P306: =VLOOKUP(A306,Sheet2!$A$1:G4030,5,0) -> English | Q306: =VLOOKUP(A306,Sheet2!$A$1:G4030,6,0) -> France | R306: =VLOOKUP(A306,Sheet2!$A$1:G4030,7,0) -> PG-13 | S306: =IF(Table1[[#This Row],[Language]]="English","English","Other language") -> English | T306: =Table1[[#This Row],[Gross Revenue]]-Table1[[#This Row],[Budget]] -> -47468302 | U306: =(Table1[[#This Row],[Gross Revenue]]/Table1[[#This Row],[Budget]])-1 -> -0.6781186 | V306: =IF(J306="","",IF(J306<90,"<90 minutes",IF(J306<=110,"90-110 minutes",IF(J306<=130,"111-130 minutes",IF(J306<=150,"131-150 minutes",">150 minutes"))))) -> 90-110 minutes | W306: =Table1[[#This Row],[Profit]]/Table1[[#This Row],[Budget]] -> -0.6781186 | X306: =IF(L306="","", IF(L306<Predictability!$B$1,"Low", IF(L306<=Predictability!$B$2,"Mid","High"))) -> High | Y306: =IF(W306>=0.5,1,0) -> 0
A307: Baby's Day Out | B307: Joe Mantegna | C307: Patrick Read Johnson | D307: 1000 | E307: 2949 | F307: 32 | G307: 0 | H307: 5.9 | I307: 22 | J307: 99 | K307: 16671505 | L307: 50000000 | M307: =VLOOKUP(A307,Sheet2!$A$1:G4031,2,0) -> 34530 | N307: =VLOOKUP(A307,Sheet2!$A$1:G4031,3,0) -> Color | O307: =VLOOKUP(A307,Sheet2!$A$1:G4031,4,0) -> Adventure | P307: =VLOOKUP(A307,Sheet2!$A$1:G4031,5,0) -> English | Q307: =VLOOKUP(A307,Sheet2!$A$1:G4031,6,0) -> USA | R307: =VLOOKUP(A307,Sheet2!$A$1:G4031,7,0) -> PG | S307: =IF(Table1[[#This Row],[Language]]="English","English","Other language") -> English | T307: =Table1[[#This Row],[Gross Revenue]]-Table1[[#This Row],[Budget]] -> -33328495 | U307: =(Table1[[#This Row],[Gross Revenue]]/Table1[[#This Row],[Budget]])-1 -> -0.6665699 | V307: =IF(J307="","",IF(J307<90,"<90 minutes",IF(J307<=110,"90-110 minutes",IF(J307<=130,"111-130 minutes",IF(J307<=150,"131-150 minutes",">150 minutes"))))) -> 90-110 minutes | W307: =Table1[[#This Row],[Profit]]/Table1[[#This Row],[Budget]] -> -0.6665699 | X307: =IF(L307="","", IF(L307<Predictability!$B$1,"Low", IF(L307<=Predictability!$B$2,"Mid","High"))) -> Mid | Y307: =IF(W307>=0.5,1,0) -> 0
A308: Bachelorette | B308: Kirsten Dunst | C308: Leslye Headland | D308: 4000 | E308: 8353 | F308: 21 | G308: 0 | H308: 5.3 | I308: 156 | J308: 87 | K308: 418268 | L308: 3000000 | M308: =VLOOKUP(A308,Sheet2!$A$1:G4032,2,0) -> 41185 | N308: =VLOOKUP(A308,Sheet2!$A$1:G4032,3,0) -> Color | O308: =VLOOKUP(A308,Sheet2!$A$1:G4032,4,0) -> Comedy | P308: =VLOOKUP(A308,Sheet2!$A$1:G4032,5,0) -> English | Q308: =VLOOKUP(A308,Sheet2!$A$1:G4032,6,0) -> USA | R308: =VLOOKUP(A308,Sheet2!$A$1:G4032,7,0) -> R | S308: =IF(Table1[[#This Row],[Language]]="English","English","Other language") -> English | T308: =Table1[[#This Row],[Gross Revenue]]-Table1[[#This Row],[Budget]] -> -2581732 | U308: =(Table1[[#This Row],[Gross Revenue]]/Table1[[#This Row],[Budget]])-1 -> -0.86057733 | V308: =IF(J308="","",IF(J308<90,"<90 minutes",IF(J308<=110,"90-110 minutes",IF(J308<=130,"111-130 minutes",IF(J308<=150,"131-150 minutes",">150 minutes"))))) -> <90 minutes | W308: =Table1[[#This Row],[Profit]]/Table1[[#This Row],[Budget]] -> -0.86057733 | X308: =IF(L308="","", IF(L308<Predictability!$B$1,"Low", IF(L308<=Predictability!$B$2,"Mid","High"))) -> Low | Y308: =IF(W308>=0.5,1,0) -> 0
A309: Back to the Future | B309: Lea Thompson | C309: Robert Zemeckis | D309: 1000 | E309: 3230 | F309: 0 | G309: 39000 | H309: 8.5 | I309: 198 | J309: 116 | K309: 210609762 | L309: 19000000 | M309: =VLOOKUP(A309,Sheet2!$A$1:G4033,2,0) -> 31386 | N309: =VLOOKUP(A309,Sheet2!$A$1:G4033,3,0) -> Color | O309: =VLOOKUP(A309,Sheet2!$A$1:G4033,4,0) -> Adventure | P309: =VLOOKUP(A309,Sheet2!$A$1:G4033,5,0) -> English | Q309: =VLOOKUP(A309,Sheet2!$A$1:G4033,6,0) -> USA | R309: =VLOOKUP(A309,Sheet2!$A$1:G4033,7,0) -> PG | S309: =IF(Table1[[#This Row],[Language]]="English","English","Other language") -> English | T309: =Table1[[#This Row],[Gross Revenue]]-Table1[[#This Row],[Budget]] -> 191609762 | U309: =(Table1[[#This Row],[Gross Revenue]]/Table1[[#This Row],[Budget]])-1 -> 10.084724 | V309: =IF(J309="","",IF(J309<90,"<90 minutes",IF(J309<=110,"90-110 minutes",IF(J309<=130,"111-130 minutes",IF(J309<=150,"131-150 minutes",">150 minutes"))))) -> 111-130 minutes | W309: =Table1[[#This Row],[Profit]]/Table1[[#This Row],[Budget]] -> 10.084724 | X309: =IF(L309="","", IF(L309<Predictability!$B$1,"Low", IF(L309<=Predictability!$B$2,"Mid","High"))) -> Mid | Y309: =IF(W309>=0.5,1,0) -> 1
A310: Back to the Future Part II | B310: Lea Thompson | C310: Robert Zemeckis | D310: 1000 | E310: 3660 | F310: 0 | G310: 12000 | H310: 7.8 | I310: 125 | J310: 108 | K310: 118500000 | L310: 40000000 | M310: =VLOOKUP(A310,Sheet2!$A$1:G4034,2,0) -> 32698 | N310: =VLOOKUP(A310,Sheet2!$A$1:G4034,3,0) -> Color | O310: =VLOOKUP(A310,Sheet2!$A$1:G4034,4,0) -> Adventure | P310: =VLOOKUP(A310,Sheet2!$A$1:G4034,5,0) -> English | Q310: =VLOOKUP(A310,Sheet2!$A$1:G4034,6,0) -> USA | R310: =VLOOKUP(A310,Sheet2!$A$1:G4034,7,0) -> PG | S310: =IF(Table1[[#This Row],[Language]]="English","English","Other language") -> English | T310: =Table1[[#This Row],[Gross Revenue]]-Table1[[#This Row],[Budget]] -> 78500000 | U310: =(Table1[[#This Row],[Gross Revenue]]/Table1[[#This Row],[Budget]])-1 -> 1.9625 | V310: =IF(J310="","",IF(J310<90,"<90 minutes",IF(J310<=110,"90-110 minutes",IF(J310<=130,"111-130 minutes",IF(J310<=150,"131-150 minutes",">150 minutes"))))) -> 90-110 minutes | W310: =Table1[[#This Row],[Profit]]/Table1[[#This Row],[Budget]] -> 1.9625 | X310: =IF(L310="","", IF(L310<Predictability!$B$1,"Low", IF(L310<=Predictability!$B$2,"Mid","High"))) -> Mid | Y310: =IF(W310>=0.5,1,0) -> 1
... A778: Digimon: The Movie | B778: Lara Jill Miller | C778: Mamoru Hosoda | D778: 93 | E778: 315 | F778: 99 | G778: 207 | H778: 5.9 | I778: 29 | J778: 82 | K778: 9628751 | L778: 5000000 | M778: =VLOOKUP(A778,Sheet2!$A$1:G4502,2,0) -> 36545 | N778: =VLOOKUP(A778,Sheet2!$A$1:G4502,3,0) -> Color | O778: =VLOOKUP(A778,Sheet2!$A$1:G4502,4,0) -> Action | P778: =VLOOKUP(A778,Sheet2!$A$1:G4502,5,0) -> English | Q778: =VLOOKUP(A778,Sheet2!$A$1:G4502,6,0) -> USA | R778: =VLOOKUP(A778,Sheet2!$A$1:G4502,7,0) -> PG | S778: =IF(Table1[[#This Row],[Language]]="English","English","Other language") -> English | T778: =Table1[[#This Row],[Gross Revenue]]-Table1[[#This Row],[Budget]] -> 4628751 | U778: =(Table1[[#This Row],[Gross Revenue]]/Table1[[#This Row],[Budget]])-1 -> 0.9257502 | V778: =IF(J778="","",IF(J778<90,"<90 minutes",IF(J778<=110,"90-110 minutes",IF(J778<=130,"111-130 minutes",IF(J778<=150,"131-150 minutes",">150 minutes"))))) -> <90 minutes | W778: =Table1[[#This Row],[Profit]]/Table1[[#This Row],[Budget]] -> 0.9257502 | X778: =IF(L778="","", IF(L778<Predictability!$B$1,"Low", IF(L778<=Predictability!$B$2,"Mid","High"))) -> Low | Y778: =IF(W778>=0.5,1,0) -> 1
A779: Dil Jo Bhi Kahey... | B779: Annabelle Wallis | C779: Romesh Sharma | D779: 421 | E779: 622 | F779: 0 | G779: 9 | H779: 5.1 | I779: 4 | K779: 129319 | L779: 70000000 | M779: =VLOOKUP(A779,Sheet2!$A$1:G4503,2,0) -> 38483 | N779: =VLOOKUP(A779,Sheet2!$A$1:G4503,3,0) -> Color | O779: =VLOOKUP(A779,Sheet2!$A$1:G4503,4,0) -> Romance | P779: =VLOOKUP(A779,Sheet2!$A$1:G4503,5,0) -> English | Q779: =VLOOKUP(A779,Sheet2!$A$1:G4503,6,0) -> India | R779: =VLOOKUP(A779,Sheet2!$A$1:G4503,7,0) -> 0 | S779: =IF(Table1[[#This Row],[Language]]="English","English","Other language") -> English | T779: =Table1[[#This Row],[Gross Revenue]]-Table1[[#This Row],[Budget]] -> -69870681 | U779: =(Table1[[#This Row],[Gross Revenue]]/Table1[[#This Row],[Budget]])-1 -> -0.99815259 | V779: =IF(J779="","",IF(J779<90,"<90 minutes",IF(J779<=110,"90-110 minutes",IF(J779<=130,"111-130 minutes",IF(J779<=150,"131-150 minutes",">150 minutes"))))) | W779: =Table1[[#This Row],[Profit]]/Table1[[#This Row],[Budget]] -> -0.99815259 | X779: =IF(L779="","", IF(L779<Predictability!$B$1,"Low", IF(L779<=Predictability!$B$2,"Mid","High"))) -> High | Y779: =IF(W779>=0.5,1,0) -> 0
A780: Diner | B780: Steve Guttenberg | C780: Barry Levinson | D780: 801 | E780: 2943 | F780: 272 | G780: 0 | H780: 7.2 | I780: 42 | J780: 110 | K780: 14100000 | L780: 5000000 | M780: =VLOOKUP(A780,Sheet2!$A$1:G4504,2,0) -> 30068 | N780: =VLOOKUP(A780,Sheet2!$A$1:G4504,3,0) -> Color | O780: =VLOOKUP(A780,Sheet2!$A$1:G4504,4,0) -> Comedy | P780: =VLOOKUP(A780,Sheet2!$A$1:G4504,5,0) -> English | Q780: =VLOOKUP(A780,Sheet2!$A$1:G4504,6,0) -> USA | R780: =VLOOKUP(A780,Sheet2!$A$1:G4504,7,0) -> R | S780: =IF(Table1[[#This Row],[Language]]="English","English","Other language") -> English | T780: =Table1[[#This Row],[Gross Revenue]]-Table1[[#This Row],[Budget]] -> 9100000 | U780: =(Table1[[#This Row],[Gross Revenue]]/Table1[[#This Row],[Budget]])-1 -> 1.82 | V780: =IF(J780="","",IF(J780<90,"<90 minutes",IF(J780<=110,"90-110 minutes",IF(J780<=130,"111-130 minutes",IF(J780<=150,"131-150 minutes",">150 minutes"))))) -> 90-110 minutes | W780: =Table1[[#This Row],[Profit]]/Table1[[#This Row],[Budget]] -> 1.82 | X780: =IF(L780="","", IF(L780<Predictability!$B$1,"Low", IF(L780<=Predictability!$B$2,"Mid","High"))) -> Low | Y780: =IF(W780>=0.5,1,0) -> 1
A781: Dinosaur | B781: Alfre Woodard | C781: Eric Leighton | D781: 1000 | E781: 2945 | F781: 0 | G781: 0 | H781: 6.5 | I781: 145 | J781: 82 | K781: 137748063 | L781: 127500000 | M781: =VLOOKUP(A781,Sheet2!$A$1:G4505,2,0) -> 36545 | N781: =VLOOKUP(A781,Sheet2!$A$1:G4505,3,0) -> Color | O781: =VLOOKUP(A781,Sheet2!$A$1:G4505,4,0) -> Adventure | P781: =VLOOKUP(A781,Sheet2!$A$1:G4505,5,0) -> English | Q781: =VLOOKUP(A781,Sheet2!$A$1:G4505,6,0) -> USA | R781: =VLOOKUP(A781,Sheet2!$A$1:G4505,7,0) -> PG | S781: =IF(Table1[[#This Row],[Language]]="English","English","Other language") -> English | T781: =Table1[[#This Row],[Gross Revenue]]-Table1[[#This Row],[Budget]] -> 10248063 | U781: =(Table1[[#This Row],[Gross Revenue]]/Table1[[#This Row],[Budget]])-1 -> 0.080376965 | V781: =IF(J781="","",IF(J781<90,"<90 minutes",IF(J781<=110,"90-110 minutes",IF(J781<=130,"111-130 minutes",IF(J781<=150,"131-150 minutes",">150 minutes"))))) -> <90 minutes | W781: =Table1[[#This Row],[Profit]]/Table1[[#This Row],[Budget]] -> 0.080376965 | X781: =IF(L781="","", IF(L781<Predictability!$B$1,"Low", IF(L781<=Predictability!$B$2,"Mid","High"))) -> High | Y781: =IF(W781>=0.5,1,0) -> 0
A782: Dirty Pretty Things | B782: Sophie Okonedo | C782: Stephen Frears | D782: 460 | E782: 1334 | F782: 350 | G782: 0 | H782: 7.4 | I782: 137 | J782: 97 | K782: 8111360 | L782: 10000000 | M782: =VLOOKUP(A782,Sheet2!$A$1:G4506,2,0) -> 37324 | N782: =VLOOKUP(A782,Sheet2!$A$1:G4506,3,0) -> Color | O782: =VLOOKUP(A782,Sheet2!$A$1:G4506,4,0) -> Crime | P782: =VLOOKUP(A782,Sheet2!$A$1:G4506,5,0) -> English | Q782: =VLOOKUP(A782,Sheet2!$A$1:G4506,6,0) -> UK | R782: =VLOOKUP(A782,Sheet2!$A$1:G4506,7,0) -> R | S782: =IF(Table1[[#This Row],[Language]]="English","English","Other language") -> English | T782: =Table1[[#This Row],[Gross Revenue]]-Table1[[#This Row],[Budget]] -> -1888640 | U782: =(Table1[[#This Row],[Gross Revenue]]/Table1[[#This Row],[Budget]])-1 -> -0.188864 | V782: =IF(J782="","",IF(J782<90,"<90 minutes",IF(J782<=110,"90-110 minutes",IF(J782<=130,"111-130 minutes",IF(J782<=150,"131-150 minutes",">150 minutes"))))) -> 90-110 minutes | W782: =Table1[[#This Row],[Profit]]/Table1[[#This Row],[Budget]] -> -0.188864 | X782: =IF(L782="","", IF(L782<Predictability!$B$1,"Low", IF(L782<=Predictability!$B$2,"Mid","High"))) -> Mid | Y782: =IF(W782>=0.5,1,0) -> 0
A783: Dirty Work | B783: Don Rickles | C783: Bob Saget | D783: 721 | E783: 1805 | F783: 799 | G783: 679 | H783: 6.4 | I783: 32 | J783: 82 | K783: 9975684 | L783: 13000000 | M783: =VLOOKUP(A783,Sheet2!$A$1:G4507,2,0) -> 35940 | N783: =VLOOKUP(A783,Sheet2!$A$1:G4507,3,0) -> Color | O783: =VLOOKUP(A783,Sheet2!$A$1:G4507,4,0) -> Comedy | P783: =VLOOKUP(A783,Sheet2!$A$1:G4507,5,0) -> English | Q783: =VLOOKUP(A783,Sheet2!$A$1:G4507,6,0) -> Canada | R783: =VLOOKUP(A783,Sheet2!$A$1:G4507,7,0) -> PG-13 | S783: =IF(Table1[[#This Row],[Language]]="English","English","Other language") -> English | T783: =Table1[[#This Row],[Gross Revenue]]-Table1[[#This Row],[Budget]] -> -3024316 | U783: =(Table1[[#This Row],[Gross Revenue]]/Table1[[#This Row],[Budget]])-1 -> -0.23263969 | V783: =IF(J783="","",IF(J783<90,"<90 minutes",IF(J783<=110,"90-110 minutes",IF(J783<=130,"111-130 minutes",IF(J783<=150,"131-150 minutes",">150 minutes"))))) -> <90 minutes | W783: =Table1[[#This Row],[Profit]]/Table1[[#This Row],[Budget]] -> -0.23263969 | X783: =IF(L783="","", IF(L783<Predictability!$B$1,"Low", IF(L783<=Predictability!$B$2,"Mid","High"))) -> Mid | Y783: =IF(W783>=0.5,1,0) -> 0
A784: Disaster Movie | B784: Carmen Electra | C784: Jason Friedberg | D784: 869 | E784: 2857 | F784: 82 | G784: 0 | H784: 1.9 | I784: 111 | J784: 88 | K784: 14174654 | L784: 25000000 | M784: =VLOOKUP(A784,Sheet2!$A$1:G4508,2,0) -> 39500 | N784: =VLOOKUP(A784,Sheet2!$A$1:G4508,3,0) -> Color | O784: =VLOOKUP(A784,Sheet2!$A$1:G4508,4,0) -> Comedy | P784: =VLOOKUP(A784,Sheet2!$A$1:G4508,5,0) -> English | Q784: =VLOOKUP(A784,Sheet2!$A$1:G4508,6,0) -> USA | R784: =VLOOKUP(A784,Sheet2!$A$1:G4508,7,0) -> PG-13 | S784: =IF(Table1[[#This Row],[Language]]="English","English","Other language") -> English | T784: =Table1[[#This Row],[Gross Revenue]]-Table1[[#This Row],[Budget]] -> -10825346 | U784: =(Table1[[#This Row],[Gross Revenue]]/Table1[[#This Row],[Budget]])-1 -> -0.43301384 | V784: =IF(J784="","",IF(J784<90,"<90 minutes",IF(J784<=110,"90-110 minutes",IF(J784<=130,"111-130 minutes",IF(J784<=150,"131-150 minutes",">150 minutes"))))) -> <90 minutes | W784: =Table1[[#This Row],[Profit]]/Table1[[#This Row],[Budget]] -> -0.43301384 | X784: =IF(L784="","", IF(L784<Predictability!$B$1,"Low", IF(L784<=Predictability!$B$2,"Mid","High"))) -> Mid | Y784: =IF(W784>=0.5,1,0) -> 0
A785: Disclosure | B785: Demi Moore | C785: Barry Levinson | D785: 2000 | E785: 3888 | F785: 272 | G785: 0 | H785: 6 | I785: 55 | J785: 128 | K785: 83000000 | L785: 55000000 | M785: =VLOOKUP(A785,Sheet2!$A$1:G4509,2,0) -> 34364 | N785: =VLOOKUP(A785,Sheet2!$A$1:G4509,3,0) -> Color | O785: =VLOOKUP(A785,Sheet2!$A$1:G4509,4,0) -> Drama | P785: =VLOOKUP(A785,Sheet2!$A$1:G4509,5,0) -> English | Q785: =VLOOKUP(A785,Sheet2!$A$1:G4509,6,0) -> USA | R785: =VLOOKUP(A785,Sheet2!$A$1:G4509,7,0) -> R | S785: =IF(Table1[[#This Row],[Language]]="English","English","Other language") -> English | T785: =Table1[[#This Row],[Gross Revenue]]-Table1[[#This Row],[Budget]] -> 28000000 | U785: =(Table1[[#This Row],[Gross Revenue]]/Table1[[#This Row],[Budget]])-1 -> 0.50909091 | V785: =IF(J785="","",IF(J785<90,"<90 minutes",IF(J785<=110,"90-110 minutes",IF(J785<=130,"111-130 minutes",IF(J785<=150,"131-150 minutes",">150 minutes"))))) -> 111-130 minutes | W785: =Table1[[#This Row],[Profit]]/Table1[[#This Row],[Budget]] -> 0.50909091 | X785: =IF(L785="","", IF(L785<Predictability!$B$1,"Low", IF(L785<=Predictability!$B$2,"Mid","High"))) -> High | Y785: =IF(W785>=0.5,1,0) -> 1
A786: District 9 | B786: Sharlto Copley | C786: Neill Blomkamp | D786: 2000 | E786: 2639 | F786: 662 | G786: 22000 | H786: 8 | I786: 472 | J786: 112 | K786: 115646235 | L786: 30000000 | M786: =VLOOKUP(A786,Sheet2!$A$1:G4510,2,0) -> 39846 | N786: =VLOOKUP(A786,Sheet2!$A$1:G4510,3,0) -> Color | O786: =VLOOKUP(A786,Sheet2!$A$1:G4510,4,0) -> Action | P786: =VLOOKUP(A786,Sheet2!$A$1:G4510,5,0) -> English | Q786: =VLOOKUP(A786,Sheet2!$A$1:G4510,6,0) -> South Africa | R786: =VLOOKUP(A786,Sheet2!$A$1:G4510,7,0) -> R | S786: =IF(Table1[[#This Row],[Language]]="English","English","Other language") -> English | T786: =Table1[[#This Row],[Gross Revenue]]-Table1[[#This Row],[Budget]] -> 85646235 | U786: =(Table1[[#This Row],[Gross Revenue]]/Table1[[#This Row],[Budget]])-1 -> 2.8548745 | V786: =IF(J786="","",IF(J786<90,"<90 minutes",IF(J786<=110,"90-110 minutes",IF(J786<=130,"111-130 minutes",IF(J786<=150,"131-150 minutes",">150 minutes"))))) -> 111-130 minutes | W786: =Table1[[#This Row],[Profit]]/Table1[[#This Row],[Budget]] -> 2.8548745 | X786: =IF(L786="","", IF(L786<Predictability!$B$1,"Low", IF(L786<=Predictability!$B$2,"Mid","High"))) -> Mid | Y786: =IF(W786>=0.5,1,0) -> 1
A787: District B13 | B787: David Belle | C787: Pierre Morel | D787: 510 | E787: 962 | F787: 180 | G787: 0 | H787: 7.2 | I787: 141 | J787: 84 | K787: 1197786 | L787: 12000000 | M787: =VLOOKUP(A787,Sheet2!$A$1:G4511,2,0) -> 38286 | N787: =VLOOKUP(A787,Sheet2!$A$1:G4511,3,0) -> Color | O787: =VLOOKUP(A787,Sheet2!$A$1:G4511,4,0) -> Action | P787: =VLOOKUP(A787,Sheet2!$A$1:G4511,5,0) -> French | Q787: =VLOOKUP(A787,Sheet2!$A$1:G4511,6,0) -> France | R787: =VLOOKUP(A787,Sheet2!$A$1:G4511,7,0) -> R | S787: =IF(Table1[[#This Row],[Language]]="English","English","Other language") -> Other language | T787: =Table1[[#This Row],[Gross Revenue]]-Table1[[#This Row],[Budget]] -> -10802214 | U787: =(Table1[[#This Row],[Gross Revenue]]/Table1[[#This Row],[Budget]])-1 -> -0.9001845 | V787: =IF(J787="","",IF(J787<90,"<90 minutes",IF(J787<=110,"90-110 minutes",IF(J787<=130,"111-130 minutes",IF(J787<=150,"131-150 minutes",">150 minutes"))))) -> <90 minutes | W787: =Table1[[#This Row],[Profit]]/Table1[[#This Row],[Budget]] -> -0.9001845 | X787: =IF(L787="","", IF(L787<Predictability!$B$1,"Low", IF(L787<=Predictability!$B$2,"Mid","High"))) -> Mid | Y787: =IF(W787>=0.5,1,0) -> 0
A788: Disturbia | B788: Sarah Roemer | C788: D.J. Caruso | D788: 884 | E788: 2288 | F788: 154 | G788: 0 | H788: 6.9 | I788: 253 | J788: 105 | K788: 80050171 | L788: 20000000 | M788: =VLOOKUP(A788,Sheet2!$A$1:G4512,2,0) -> 39153 | N788: =VLOOKUP(A788,Sheet2!$A$1:G4512,3,0) -> Color | O788: =VLOOKUP(A788,Sheet2!$A$1:G4512,4,0) -> Drama | P788: =VLOOKUP(A788,Sheet2!$A$1:G4512,5,0) -> English | Q788: =VLOOKUP(A788,Sheet2!$A$1:G4512,6,0) -> USA | R788: =VLOOKUP(A788,Sheet2!$A$1:G4512,7,0) -> PG-13 | S788: =IF(Table1[[#This Row],[Language]]="English","English","Other language") -> English | T788: =Table1[[#This Row],[Gross Revenue]]-Table1[[#This Row],[Budget]] -> 60050171 | U788: =(Table1[[#This Row],[Gross Revenue]]/Table1[[#This Row],[Budget]])-1 -> 3.0025085 | V788: =IF(J788="","",IF(J788<90,"<90 minutes",IF(J788<=110,"90-110 minutes",IF(J788<=130,"111-130 minutes",IF(J788<=150,"131-150 minutes",">150 minutes"))))) -> 90-110 minutes | W788: =Table1[[#This Row],[Profit]]/Table1[[#This Row],[Budget]] -> 3.0025085 | X788: =IF(L788="","", IF(L788<Predictability!$B$1,"Low", IF(L788<=Predictability!$B$2,"Mid","High"))) -> Mid | Y788: =IF(W788>=0.5,1,0) -> 1
A789: Disturbing Behavior | B789: Bruce Greenwood | C789: David Nutter | D789: 989 | E789: 4660 | F789: 119 | G789: 673 | H789: 5.5 | I789: 96 | J789: 84 | K789: 17411331 | L789: 15000000 | M789: =VLOOKUP(A789,Sheet2!$A$1:G4513,2,0) -> 36121 | N789: =VLOOKUP(A789,Sheet2!$A$1:G4513,3,0) -> Color | O789: =VLOOKUP(A789,Sheet2!$A$1:G4513,4,0) -> Horror | P789: =VLOOKUP(A789,Sheet2!$A$1:G4513,5,0) -> English | Q789: =VLOOKUP(A789,Sheet2!$A$1:G4513,6,0) -> Australia | R789: =VLOOKUP(A789,Sheet2!$A$1:G4513,7,0) -> R | S789: =IF(Table1[[#This Row],[Language]]="English","English","Other language") -> English | T789: =Table1[[#This Row],[Gross Revenue]]-Table1[[#This Row],[Budget]] -> 2411331 | U789: =(Table1[[#This Row],[Gross Revenue]]/Table1[[#This Row],[Budget]])-1 -> 0.1607554 | V789: =IF(J789="","",IF(J789<90,"<90 minutes",IF(J789<=110,"90-110 minutes",IF(J789<=130,"111-130 minutes",IF(J789<=150,"131-150 minutes",">150 minutes"))))) -> <90 minutes | W789: =Table1[[#This Row],[Profit]]/Table1[[#This Row],[Budget]] -> 0.1607554 | X789: =IF(L789="","", IF(L789<Predictability!$B$1,"Low", IF(L789<=Predictability!$B$2,"Mid","High"))) -> Mid | Y789: =IF(W789>=0.5,1,0) -> 0
A790: Divergent | B790: Kate Winslet | C790: Neil Burger | D790: 14000 | E790: 22226 | F790: 168 | G790: 49000 | H790: 6.7 | I790: 459 | J790: 139 | K790: 150832203 | L790: 85000000 | M790: =VLOOKUP(A790,Sheet2!$A$1:G4514,2,0) -> 41864 | N790: =VLOOKUP(A790,Sheet2!$A$1:G4514,3,0) -> Color | O790: =VLOOKUP(A790,Sheet2!$A$1:G4514,4,0) -> Adventure | P790: =VLOOKUP(A790,Sheet2!$A$1:G4514,5,0) -> English | Q790: =VLOOKUP(A790,Sheet2!$A$1:G4514,6,0) -> USA | R790: =VLOOKUP(A790,Sheet2!$A$1:G4514,7,0) -> PG-13 | S790: =IF(Table1[[#This Row],[Language]]="English","English","Other language") -> English | T790: =Table1[[#This Row],[Gross Revenue]]-Table1[[#This Row],[Budget]] -> 65832203 | U790: =(Table1[[#This Row],[Gross Revenue]]/Table1[[#This Row],[Budget]])-1 -> 0.77449651 | V790: =IF(J790="","",IF(J790<90,"<90 minutes",IF(J790<=110,"90-110 minutes",IF(J790<=130,"111-130 minutes",IF(J790<=150,"131-150 minutes",">150 minutes"))))) -> 131-150 minutes | W790: =Table1[[#This Row],[Profit]]/Table1[[#This Row],[Budget]] -> 0.77449651 | X790: =IF(L790="","", IF(L790<Predictability!$B$1,"Low", IF(L790<=Predictability!$B$2,"Mid","High"))) -> High | Y790: =IF(W790>=0.5,1,0) -> 1
A791: Divine Secrets of the Ya-Ya Sisterhood | B791: Ellen Burstyn | C791: Callie Khouri | D791: 1000 | E791: 3845 | F791: 144 | G791: 0 | H791: 6 | I791: 93 | J791: 116 | K791: 69586544 | L791: 27000000 | M791: =VLOOKUP(A791,Sheet2!$A$1:G4515,2,0) -> 37588 | N791: =VLOOKUP(A791,Sheet2!$A$1:G4515,3,0) -> Color | O791: =VLOOKUP(A791,Sheet2!$A$1:G4515,4,0) -> Drama | P791: =VLOOKUP(A791,Sheet2!$A$1:G4515,5,0) -> English | Q791: =VLOOKUP(A791,Sheet2!$A$1:G4515,6,0) -> USA | R791: =VLOOKUP(A791,Sheet2!$A$1:G4515,7,0) -> PG-13 | S791: =IF(Table1[[#This Row],[Language]]="English","English","Other language") -> English | T791: =Table1[[#This Row],[Gross Revenue]]-Table1[[#This Row],[Budget]] -> 42586544 | U791: =(Table1[[#This Row],[Gross Revenue]]/Table1[[#This Row],[Budget]])-1 -> 1.5772794 | V791: =IF(J791="","",IF(J791<90,"<90 minutes",IF(J791<=110,"90-110 minutes",IF(J791<=130,"111-130 minutes",IF(J791<=150,"131-150 minutes",">150 minutes"))))) -> 111-130 minutes | W791: =Table1[[#This Row],[Profit]]/Table1[[#This Row],[Budget]] -> 1.5772794 | X791: =IF(L791="","", IF(L791<Predictability!$B$1,"Low", IF(L791<=Predictability!$B$2,"Mid","High"))) -> Mid | Y791: =IF(W791>=0.5,1,0) -> 1
... A2064: Pink Narcissus | B2064: Don Brooks | C2064: James Bidgood | D2064: 0 | E2064: 0 | F2064: 0 | G2064: 85 | H2064: 6.7 | I2064: 8 | J2064: 65 | K2064: 8231 | L2064: 27000 | M2064: =VLOOKUP(A2064,Sheet2!$A$1:G5788,2,0) -> 26083 | N2064: =VLOOKUP(A2064,Sheet2!$A$1:G5788,3,0) -> Color | O2064: =VLOOKUP(A2064,Sheet2!$A$1:G5788,4,0) -> Drama | P2064: =VLOOKUP(A2064,Sheet2!$A$1:G5788,5,0) -> English | Q2064: =VLOOKUP(A2064,Sheet2!$A$1:G5788,6,0) -> USA | R2064: =VLOOKUP(A2064,Sheet2!$A$1:G5788,7,0) -> Not Rated | S2064: =IF(Table1[[#This Row],[Language]]="English","English","Other language") -> English | T2064: =Table1[[#This Row],[Gross Revenue]]-Table1[[#This Row],[Budget]] -> -18769 | U2064: =(Table1[[#This Row],[Gross Revenue]]/Table1[[#This Row],[Budget]])-1 -> -0.69514815 | V2064: =IF(J2064="","",IF(J2064<90,"<90 minutes",IF(J2064<=110,"90-110 minutes",IF(J2064<=130,"111-130 minutes",IF(J2064<=150,"131-150 minutes",">150 minutes"))))) -> <90 minutes | W2064: =Table1[[#This Row],[Profit]]/Table1[[#This Row],[Budget]] -> -0.69514815 | X2064: =IF(L2064="","", IF(L2064<Predictability!$B$1,"Low", IF(L2064<=Predictability!$B$2,"Mid","High"))) -> Low | Y2064: =IF(W2064>=0.5,1,0) -> 0
A2065: Pink Ribbons, Inc. | C2065: LÃ©a Pool | E2065: 0 | F2065: 4 | G2065: 5000 | H2065: 7.4 | I2065: 23 | J2065: 97 | K2065: 24784 | L2065: 1200000 | M2065: =VLOOKUP(A2065,Sheet2!$A$1:G5789,2,0) -> 40828 | N2065: =VLOOKUP(A2065,Sheet2!$A$1:G5789,3,0) -> Color | O2065: =VLOOKUP(A2065,Sheet2!$A$1:G5789,4,0) -> Documentary | P2065: =VLOOKUP(A2065,Sheet2!$A$1:G5789,5,0) -> English | Q2065: =VLOOKUP(A2065,Sheet2!$A$1:G5789,6,0) -> Canada | R2065: =VLOOKUP(A2065,Sheet2!$A$1:G5789,7,0) -> Not Rated | S2065: =IF(Table1[[#This Row],[Language]]="English","English","Other language") -> English | T2065: =Table1[[#This Row],[Gross Revenue]]-Table1[[#This Row],[Budget]] -> -1175216 | U2065: =(Table1[[#This Row],[Gross Revenue]]/Table1[[#This Row],[Budget]])-1 -> -0.97934667 | V2065: =IF(J2065="","",IF(J2065<90,"<90 minutes",IF(J2065<=110,"90-110 minutes",IF(J2065<=130,"111-130 minutes",IF(J2065<=150,"131-150 minutes",">150 minutes"))))) -> 90-110 minutes | W2065: =Table1[[#This Row],[Profit]]/Table1[[#This Row],[Budget]] -> -0.97934667 | X2065: =IF(L2065="","", IF(L2065<Predictability!$B$1,"Low", IF(L2065<=Predictability!$B$2,"Mid","High"))) -> Low | Y2065: =IF(W2065>=0.5,1,0) -> 0
A2066: Pinocchio | B2066: Mel Blanc | C2066: Norman Ferguson | D2066: 1000 | E2066: 1178 | F2066: 3 | G2066: 0 | H2066: 7.5 | I2066: 105 | J2066: 88 | K2066: 84300000 | L2066: 2600000 | M2066: =VLOOKUP(A2066,Sheet2!$A$1:G5790,2,0) -> 14896 | N2066: =VLOOKUP(A2066,Sheet2!$A$1:G5790,3,0) -> Color | O2066: =VLOOKUP(A2066,Sheet2!$A$1:G5790,4,0) -> Animation | P2066: =VLOOKUP(A2066,Sheet2!$A$1:G5790,5,0) -> English | Q2066: =VLOOKUP(A2066,Sheet2!$A$1:G5790,6,0) -> USA | R2066: =VLOOKUP(A2066,Sheet2!$A$1:G5790,7,0) -> Approved | S2066: =IF(Table1[[#This Row],[Language]]="English","English","Other language") -> English | T2066: =Table1[[#This Row],[Gross Revenue]]-Table1[[#This Row],[Budget]] -> 81700000 | U2066: =(Table1[[#This Row],[Gross Revenue]]/Table1[[#This Row],[Budget]])-1 -> 31.423077 | V2066: =IF(J2066="","",IF(J2066<90,"<90 minutes",IF(J2066<=110,"90-110 minutes",IF(J2066<=130,"111-130 minutes",IF(J2066<=150,"131-150 minutes",">150 minutes"))))) -> <90 minutes | W2066: =Table1[[#This Row],[Profit]]/Table1[[#This Row],[Budget]] -> 31.423077 | X2066: =IF(L2066="","", IF(L2066<Predictability!$B$1,"Low", IF(L2066<=Predictability!$B$2,"Mid","High"))) -> Low | Y2066: =IF(W2066>=0.5,1,0) -> 1
A2067: Piranha 3D | B2067: Adam Scott | C2067: Alexandre Aja | D2067: 3000 | E2067: 5737 | F2067: 192 | G2067: 13000 | H2067: 5.5 | I2067: 365 | J2067: 88 | K2067: 25003072 | L2067: 24000000 | M2067: =VLOOKUP(A2067,Sheet2!$A$1:G5791,2,0) -> 40311 | N2067: =VLOOKUP(A2067,Sheet2!$A$1:G5791,3,0) -> Color | O2067: =VLOOKUP(A2067,Sheet2!$A$1:G5791,4,0) -> Comedy | P2067: =VLOOKUP(A2067,Sheet2!$A$1:G5791,5,0) -> English | Q2067: =VLOOKUP(A2067,Sheet2!$A$1:G5791,6,0) -> USA | R2067: =VLOOKUP(A2067,Sheet2!$A$1:G5791,7,0) -> R | S2067: =IF(Table1[[#This Row],[Language]]="English","English","Other language") -> English | T2067: =Table1[[#This Row],[Gross Revenue]]-Table1[[#This Row],[Budget]] -> 1003072 | U2067: =(Table1[[#This Row],[Gross Revenue]]/Table1[[#This Row],[Budget]])-1 -> 0.041794667 | V2067: =IF(J2067="","",IF(J2067<90,"<90 minutes",IF(J2067<=110,"90-110 minutes",IF(J2067<=130,"111-130 minutes",IF(J2067<=150,"131-150 minutes",">150 minutes"))))) -> <90 minutes | W2067: =Table1[[#This Row],[Profit]]/Table1[[#This Row],[Budget]] -> 0.041794667 | X2067: =IF(L2067="","", IF(L2067<Predictability!$B$1,"Low", IF(L2067<=Predictability!$B$2,"Mid","High"))) -> Mid | Y2067: =IF(W2067>=0.5,1,0) -> 0
A2068: Pirates of the Caribbean: At World's End | B2068: Johnny Depp | C2068: Gore Verbinski | D2068: 40000 | E2068: 48350 | F2068: 563 | G2068: 0 | H2068: 7.1 | I2068: 302 | J2068: 169 | K2068: 309404152 | L2068: 300000000 | M2068: =VLOOKUP(A2068,Sheet2!$A$1:G5792,2,0) -> 39409 | N2068: =VLOOKUP(A2068,Sheet2!$A$1:G5792,3,0) -> Color | O2068: =VLOOKUP(A2068,Sheet2!$A$1:G5792,4,0) -> Action | P2068: =VLOOKUP(A2068,Sheet2!$A$1:G5792,5,0) -> English | Q2068: =VLOOKUP(A2068,Sheet2!$A$1:G5792,6,0) -> USA | R2068: =VLOOKUP(A2068,Sheet2!$A$1:G5792,7,0) -> PG-13 | S2068: =IF(Table1[[#This Row],[Language]]="English","English","Other language") -> English | T2068: =Table1[[#This Row],[Gross Revenue]]-Table1[[#This Row],[Budget]] -> 9404152 | U2068: =(Table1[[#This Row],[Gross Revenue]]/Table1[[#This Row],[Budget]])-1 -> 0.031347173 | V2068: =IF(J2068="","",IF(J2068<90,"<90 minutes",IF(J2068<=110,"90-110 minutes",IF(J2068<=130,"111-130 minutes",IF(J2068<=150,"131-150 minutes",">150 minutes"))))) -> >150 minutes | W2068: =Table1[[#This Row],[Profit]]/Table1[[#This Row],[Budget]] -> 0.031347173 | X2068: =IF(L2068="","", IF(L2068<Predictability!$B$1,"Low", IF(L2068<=Predictability!$B$2,"Mid","High"))) -> High | Y2068: =IF(W2068>=0.5,1,0) -> 0
A2069: Pirates of the Caribbean: Dead Man's Chest | B2069: Johnny Depp | C2069: Gore Verbinski | D2069: 40000 | E2069: 48486 | F2069: 563 | G2069: 5000 | H2069: 7.3 | I2069: 313 | J2069: 151 | K2069: 423032628 | L2069: 225000000 | M2069: =VLOOKUP(A2069,Sheet2!$A$1:G5793,2,0) -> 39081 | N2069: =VLOOKUP(A2069,Sheet2!$A$1:G5793,3,0) -> Color | O2069: =VLOOKUP(A2069,Sheet2!$A$1:G5793,4,0) -> Action | P2069: =VLOOKUP(A2069,Sheet2!$A$1:G5793,5,0) -> English | Q2069: =VLOOKUP(A2069,Sheet2!$A$1:G5793,6,0) -> USA | R2069: =VLOOKUP(A2069,Sheet2!$A$1:G5793,7,0) -> PG-13 | S2069: =IF(Table1[[#This Row],[Language]]="English","English","Other language") -> English | T2069: =Table1[[#This Row],[Gross Revenue]]-Table1[[#This Row],[Budget]] -> 198032628 | U2069: =(Table1[[#This Row],[Gross Revenue]]/Table1[[#This Row],[Budget]])-1 -> 0.88014501 | V2069: =IF(J2069="","",IF(J2069<90,"<90 minutes",IF(J2069<=110,"90-110 minutes",IF(J2069<=130,"111-130 minutes",IF(J2069<=150,"131-150 minutes",">150 minutes"))))) -> >150 minutes | W2069: =Table1[[#This Row],[Profit]]/Table1[[#This Row],[Budget]] -> 0.88014501 | X2069: =IF(L2069="","", IF(L2069<Predictability!$B$1,"Low", IF(L2069<=Predictability!$B$2,"Mid","High"))) -> High | Y2069: =IF(W2069>=0.5,1,0) -> 1
A2070: Pirates of the Caribbean: On Stranger Tides | B2070: Johnny Depp | C2070: Rob Marshall | D2070: 40000 | E2070: 54083 | F2070: 252 | G2070: 58000 | H2070: 6.7 | I2070: 448 | J2070: 136 | K2070: 241063875 | L2070: 250000000 | M2070: =VLOOKUP(A2070,Sheet2!$A$1:G5794,2,0) -> 40865 | N2070: =VLOOKUP(A2070,Sheet2!$A$1:G5794,3,0) -> Color | O2070: =VLOOKUP(A2070,Sheet2!$A$1:G5794,4,0) -> Action | P2070: =VLOOKUP(A2070,Sheet2!$A$1:G5794,5,0) -> English | Q2070: =VLOOKUP(A2070,Sheet2!$A$1:G5794,6,0) -> USA | R2070: =VLOOKUP(A2070,Sheet2!$A$1:G5794,7,0) -> PG-13 | S2070: =IF(Table1[[#This Row],[Language]]="English","English","Other language") -> English | T2070: =Table1[[#This Row],[Gross Revenue]]-Table1[[#This Row],[Budget]] -> -8936125 | U2070: =(Table1[[#This Row],[Gross Revenue]]/Table1[[#This Row],[Budget]])-1 -> -0.0357445 | V2070: =IF(J2070="","",IF(J2070<90,"<90 minutes",IF(J2070<=110,"90-110 minutes",IF(J2070<=130,"111-130 minutes",IF(J2070<=150,"131-150 minutes",">150 minutes"))))) -> 131-150 minutes | W2070: =Table1[[#This Row],[Profit]]/Table1[[#This Row],[Budget]] -> -0.0357445 | X2070: =IF(L2070="","", IF(L2070<Predictability!$B$1,"Low", IF(L2070<=Predictability!$B$2,"Mid","High"))) -> High | Y2070: =IF(W2070>=0.5,1,0) -> 0
A2071: Pirates of the Caribbean: The Curse of the Black Pearl | B2071: Johnny Depp | C2071: Gore Verbinski | D2071: 40000 | E2071: 48184 | F2071: 563 | G2071: 10000 | H2071: 8.1 | I2071: 271 | J2071: 143 | K2071: 305388685 | L2071: 140000000 | M2071: =VLOOKUP(A2071,Sheet2!$A$1:G5795,2,0) -> 37951 | N2071: =VLOOKUP(A2071,Sheet2!$A$1:G5795,3,0) -> Color | O2071: =VLOOKUP(A2071,Sheet2!$A$1:G5795,4,0) -> Action | P2071: =VLOOKUP(A2071,Sheet2!$A$1:G5795,5,0) -> English | Q2071: =VLOOKUP(A2071,Sheet2!$A$1:G5795,6,0) -> USA | R2071: =VLOOKUP(A2071,Sheet2!$A$1:G5795,7,0) -> PG-13 | S2071: =IF(Table1[[#This Row],[Language]]="English","English","Other language") -> English | T2071: =Table1[[#This Row],[Gross Revenue]]-Table1[[#This Row],[Budget]] -> 165388685 | U2071: =(Table1[[#This Row],[Gross Revenue]]/Table1[[#This Row],[Budget]])-1 -> 1.1813478 | V2071: =IF(J2071="","",IF(J2071<90,"<90 minutes",IF(J2071<=110,"90-110 minutes",IF(J2071<=130,"111-130 minutes",IF(J2071<=150,"131-150 minutes",">150 minutes"))))) -> 131-150 minutes | W2071: =Table1[[#This Row],[Profit]]/Table1[[#This Row],[Budget]] -> 1.1813478 | X2071: =IF(L2071="","", IF(L2071<Predictability!$B$1,"Low", IF(L2071<=Predictability!$B$2,"Mid","High"))) -> High | Y2071: =IF(W2071>=0.5,1,0) -> 1
A2072: Pitch Black | B2072: Vin Diesel | C2072: David Twohy | D2072: 14000 | E2072: 16196 | F2072: 123 | G2072: 5000 | H2072: 7.1 | I2072: 214 | J2072: 112 | K2072: 39235088 | L2072: 23000000 | M2072: =VLOOKUP(A2072,Sheet2!$A$1:G5796,2,0) -> 36746 | N2072: =VLOOKUP(A2072,Sheet2!$A$1:G5796,3,0) -> Color | O2072: =VLOOKUP(A2072,Sheet2!$A$1:G5796,4,0) -> Horror | P2072: =VLOOKUP(A2072,Sheet2!$A$1:G5796,5,0) -> English | Q2072: =VLOOKUP(A2072,Sheet2!$A$1:G5796,6,0) -> USA | R2072: =VLOOKUP(A2072,Sheet2!$A$1:G5796,7,0) -> R | S2072: =IF(Table1[[#This Row],[Language]]="English","English","Other language") -> English | T2072: =Table1[[#This Row],[Gross Revenue]]-Table1[[#This Row],[Budget]] -> 16235088 | U2072: =(Table1[[#This Row],[Gross Revenue]]/Table1[[#This Row],[Budget]])-1 -> 0.70587339 | V2072: =IF(J2072="","",IF(J2072<90,"<90 minutes",IF(J2072<=110,"90-110 minutes",IF(J2072<=130,"111-130 minutes",IF(J2072<=150,"131-150 minutes",">150 minutes"))))) -> 111-130 minutes | W2072: =Table1[[#This Row],[Profit]]/Table1[[#This Row],[Budget]] -> 0.70587339 | X2072: =IF(L2072="","", IF(L2072<Predictability!$B$1,"Low", IF(L2072<=Predictability!$B$2,"Mid","High"))) -> Mid | Y2072: =IF(W2072>=0.5,1,0) -> 1
A2073: Pitch Perfect | B2073: Anna Kendrick | C2073: Jason Moore | D2073: 10000 | E2073: 12676 | F2073: 36 | G2073: 36000 | H2073: 7.2 | I2073: 223 | J2073: 112 | K2073: 64998368 | L2073: 17000000 | M2073: =VLOOKUP(A2073,Sheet2!$A$1:G5797,2,0) -> 41016 | N2073: =VLOOKUP(A2073,Sheet2!$A$1:G5797,3,0) -> Color | O2073: =VLOOKUP(A2073,Sheet2!$A$1:G5797,4,0) -> Comedy | P2073: =VLOOKUP(A2073,Sheet2!$A$1:G5797,5,0) -> English | Q2073: =VLOOKUP(A2073,Sheet2!$A$1:G5797,6,0) -> USA | R2073: =VLOOKUP(A2073,Sheet2!$A$1:G5797,7,0) -> PG-13 | S2073: =IF(Table1[[#This Row],[Language]]="English","English","Other language") -> English | T2073: =Table1[[#This Row],[Gross Revenue]]-Table1[[#This Row],[Budget]] -> 47998368 | U2073: =(Table1[[#This Row],[Gross Revenue]]/Table1[[#This Row],[Budget]])-1 -> 2.8234334 | V2073: =IF(J2073="","",IF(J2073<90,"<90 minutes",IF(J2073<=110,"90-110 minutes",IF(J2073<=130,"111-130 minutes",IF(J2073<=150,"131-150 minutes",">150 minutes"))))) -> 111-130 minutes | W2073: =Table1[[#This Row],[Profit]]/Table1[[#This Row],[Budget]] -> 2.8234334 | X2073: =IF(L2073="","", IF(L2073<Predictability!$B$1,"Low", IF(L2073<=Predictability!$B$2,"Mid","High"))) -> Mid | Y2073: =IF(W2073>=0.5,1,0) -> 1
A2074: Pitch Perfect 2 | B2074: Anna Kendrick | C2074: Elizabeth Banks | D2074: 10000 | E2074: 13159 | F2074: 0 | G2074: 40000 | H2074: 6.5 | I2074: 221 | J2074: 115 | K2074: 183436380 | L2074: 29000000 | M2074: =VLOOKUP(A2074,Sheet2!$A$1:G5798,2,0) -> 42106 | N2074: =VLOOKUP(A2074,Sheet2!$A$1:G5798,3,0) -> Color | O2074: =VLOOKUP(A2074,Sheet2!$A$1:G5798,4,0) -> Comedy | P2074: =VLOOKUP(A2074,Sheet2!$A$1:G5798,5,0) -> English | Q2074: =VLOOKUP(A2074,Sheet2!$A$1:G5798,6,0) -> USA | R2074: =VLOOKUP(A2074,Sheet2!$A$1:G5798,7,0) -> PG-13 | S2074: =IF(Table1[[#This Row],[Language]]="English","English","Other language") -> English | T2074: =Table1[[#This Row],[Gross Revenue]]-Table1[[#This Row],[Budget]] -> 154436380 | U2074: =(Table1[[#This Row],[Gross Revenue]]/Table1[[#This Row],[Budget]])-1 -> 5.3253924 | V2074: =IF(J2074="","",IF(J2074<90,"<90 minutes",IF(J2074<=110,"90-110 minutes",IF(J2074<=130,"111-130 minutes",IF(J2074<=150,"131-150 minutes",">150 minutes"))))) -> 111-130 minutes | W2074: =Table1[[#This Row],[Profit]]/Table1[[#This Row],[Budget]] -> 5.3253924 | X2074: =IF(L2074="","", IF(L2074<Predictability!$B$1,"Low", IF(L2074<=Predictability!$B$2,"Mid","High"))) -> Mid | Y2074: =IF(W2074>=0.5,1,0) -> 1
A2075: Pixels | B2075: Peter Dinklage | C2075: Chris Columbus | D2075: 22000 | E2075: 35367 | F2075: 0 | G2075: 39000 | H2075: 5.6 | I2075: 253 | J2075: 106 | K2075: 78747585 | L2075: 88000000 | M2075: =VLOOKUP(A2075,Sheet2!$A$1:G5799,2,0) -> 42164 | N2075: =VLOOKUP(A2075,Sheet2!$A$1:G5799,3,0) -> Color | O2075: =VLOOKUP(A2075,Sheet2!$A$1:G5799,4,0) -> Action | P2075: =VLOOKUP(A2075,Sheet2!$A$1:G5799,5,0) -> English | Q2075: =VLOOKUP(A2075,Sheet2!$A$1:G5799,6,0) -> USA | R2075: =VLOOKUP(A2075,Sheet2!$A$1:G5799,7,0) -> PG-13 | S2075: =IF(Table1[[#This Row],[Language]]="English","English","Other language") -> English | T2075: =Table1[[#This Row],[Gross Revenue]]-Table1[[#This Row],[Budget]] -> -9252415 | U2075: =(Table1[[#This Row],[Gross Revenue]]/Table1[[#This Row],[Budget]])-1 -> -0.10514108 | V2075: =IF(J2075="","",IF(J2075<90,"<90 minutes",IF(J2075<=110,"90-110 minutes",IF(J2075<=130,"111-130 minutes",IF(J2075<=150,"131-150 minutes",">150 minutes"))))) -> 90-110 minutes | W2075: =Table1[[#This Row],[Profit]]/Table1[[#This Row],[Budget]] -> -0.10514108 | X2075: =IF(L2075="","", IF(L2075<Predictability!$B$1,"Low", IF(L2075<=Predictability!$B$2,"Mid","High"))) -> High | Y2075: =IF(W2075>=0.5,1,0) -> 0
A2076: Planet 51 | B2076: Dwayne Johnson | C2076: Jorge Blanco | D2076: 12000 | E2076: 22668 | F2076: 2 | G2076: 0 | H2076: 6.1 | I2076: 156 | J2076: 91 | K2076: 42194060 | L2076: 70000000 | M2076: =VLOOKUP(A2076,Sheet2!$A$1:G5800,2,0) -> 39882 | N2076: =VLOOKUP(A2076,Sheet2!$A$1:G5800,3,0) -> Color | O2076: =VLOOKUP(A2076,Sheet2!$A$1:G5800,4,0) -> Adventure | P2076: =VLOOKUP(A2076,Sheet2!$A$1:G5800,5,0) -> English | Q2076: =VLOOKUP(A2076,Sheet2!$A$1:G5800,6,0) -> Spain | R2076: =VLOOKUP(A2076,Sheet2!$A$1:G5800,7,0) -> PG | S2076: =IF(Table1[[#This Row],[Language]]="English","English","Other language") -> English | T2076: =Table1[[#This Row],[Gross Revenue]]-Table1[[#This Row],[Budget]] -> -27805940 | U2076: =(Table1[[#This Row],[Gross Revenue]]/Table1[[#This Row],[Budget]])-1 -> -0.39722771 | V2076: =IF(J2076="","",IF(J2076<90,"<90 minutes",IF(J2076<=110,"90-110 minutes",IF(J2076<=130,"111-130 minutes",IF(J2076<=150,"131-150 minutes",">150 minutes"))))) -> 90-110 minutes | W2076: =Table1[[#This Row],[Profit]]/Table1[[#This Row],[Budget]] -> -0.39722771 | X2076: =IF(L2076="","", IF(L2076<Predictability!$B$1,"Low", IF(L2076<=Predictability!$B$2,"Mid","High"))) -> High | Y2076: =IF(W2076>=0.5,1,0) -> 0
A2077: Planet of the Apes | B2077: Cary-Hiroyuki Tagawa | C2077: Tim Burton | D2077: 1000 | E2077: 2776 | F2077: 13000 | G2077: 0 | H2077: 5.7 | I2077: 230 | J2077: 119 | K2077: 180011740 | L2077: 100000000 | M2077: =VLOOKUP(A2077,Sheet2!$A$1:G5801,2,0) -> 37138 | N2077: =VLOOKUP(A2077,Sheet2!$A$1:G5801,3,0) -> Color | O2077: =VLOOKUP(A2077,Sheet2!$A$1:G5801,4,0) -> Action | P2077: =VLOOKUP(A2077,Sheet2!$A$1:G5801,5,0) -> English | Q2077: =VLOOKUP(A2077,Sheet2!$A$1:G5801,6,0) -> USA | R2077: =VLOOKUP(A2077,Sheet2!$A$1:G5801,7,0) -> PG-13 | S2077: =IF(Table1[[#This Row],[Language]]="English","English","Other language") -> English | T2077: =Table1[[#This Row],[Gross Revenue]]-Table1[[#This Row],[Budget]] -> 80011740 | U2077: =(Table1[[#This Row],[Gross Revenue]]/Table1[[#This Row],[Budget]])-1 -> 0.8001174 | V2077: =IF(J2077="","",IF(J2077<90,"<90 minutes",IF(J2077<=110,"90-110 minutes",IF(J2077<=130,"111-130 minutes",IF(J2077<=150,"131-150 minutes",">150 minutes"))))) -> 111-130 minutes | W2077: =Table1[[#This Row],[Profit]]/Table1[[#This Row],[Budget]] -> 0.8001174 | X2077: =IF(L2077="","", IF(L2077<Predictability!$B$1,"Low", IF(L2077<=Predictability!$B$2,"Mid","High"))) -> High | Y2077: =IF(W2077>=0.5,1,0) -> 1
... A2921: The Happening | B2921: Zooey Deschanel | C2921: M. Night Shyamalan | D2921: 11000 | E2921: 13654 | F2921: 0 | G2921: 6000 | H2921: 5 | I2921: 323 | J2921: 91 | K2921: 64505912 | L2921: 48000000 | M2921: =VLOOKUP(A2921,Sheet2!$A$1:G6645,2,0) -> 39668 | N2921: =VLOOKUP(A2921,Sheet2!$A$1:G6645,3,0) -> Color | O2921: =VLOOKUP(A2921,Sheet2!$A$1:G6645,4,0) -> Sci-Fi | P2921: =VLOOKUP(A2921,Sheet2!$A$1:G6645,5,0) -> English | Q2921: =VLOOKUP(A2921,Sheet2!$A$1:G6645,6,0) -> USA | R2921: =VLOOKUP(A2921,Sheet2!$A$1:G6645,7,0) -> R | S2921: =IF(Table1[[#This Row],[Language]]="English","English","Other language") -> English | T2921: =Table1[[#This Row],[Gross Revenue]]-Table1[[#This Row],[Budget]] -> 16505912 | U2921: =(Table1[[#This Row],[Gross Revenue]]/Table1[[#This Row],[Budget]])-1 -> 0.34387317 | V2921: =IF(J2921="","",IF(J2921<90,"<90 minutes",IF(J2921<=110,"90-110 minutes",IF(J2921<=130,"111-130 minutes",IF(J2921<=150,"131-150 minutes",">150 minutes"))))) -> 90-110 minutes | W2921: =Table1[[#This Row],[Profit]]/Table1[[#This Row],[Budget]] -> 0.34387317 | X2921: =IF(L2921="","", IF(L2921<Predictability!$B$1,"Low", IF(L2921<=Predictability!$B$2,"Mid","High"))) -> Mid | Y2921: =IF(W2921>=0.5,1,0) -> 0
A2922: The Harvest/La Cosecha | C2922: U. Roberto Romano | E2922: 0 | F2922: 6 | G2922: 88 | H2922: 7.2 | I2922: 3 | J2922: 80 | K2922: 2245 | L2922: 560000 | M2922: =VLOOKUP(A2922,Sheet2!$A$1:G6646,2,0) -> 40624 | N2922: =VLOOKUP(A2922,Sheet2!$A$1:G6646,3,0) -> Color | O2922: =VLOOKUP(A2922,Sheet2!$A$1:G6646,4,0) -> Documentary | P2922: =VLOOKUP(A2922,Sheet2!$A$1:G6646,5,0) -> English | Q2922: =VLOOKUP(A2922,Sheet2!$A$1:G6646,6,0) -> USA | R2922: =VLOOKUP(A2922,Sheet2!$A$1:G6646,7,0) -> 0 | S2922: =IF(Table1[[#This Row],[Language]]="English","English","Other language") -> English | T2922: =Table1[[#This Row],[Gross Revenue]]-Table1[[#This Row],[Budget]] -> -557755 | U2922: =(Table1[[#This Row],[Gross Revenue]]/Table1[[#This Row],[Budget]])-1 -> -0.99599107 | V2922: =IF(J2922="","",IF(J2922<90,"<90 minutes",IF(J2922<=110,"90-110 minutes",IF(J2922<=130,"111-130 minutes",IF(J2922<=150,"131-150 minutes",">150 minutes"))))) -> <90 minutes | W2922: =Table1[[#This Row],[Profit]]/Table1[[#This Row],[Budget]] -> -0.99599107 | X2922: =IF(L2922="","", IF(L2922<Predictability!$B$1,"Low", IF(L2922<=Predictability!$B$2,"Mid","High"))) -> Low | Y2922: =IF(W2922>=0.5,1,0) -> 0
A2923: The Hateful Eight | B2923: Craig Stark | C2923: Quentin Tarantino | D2923: 46000 | E2923: 49912 | F2923: 16000 | G2923: 114000 | H2923: 7.9 | I2923: 596 | J2923: 187 | K2923: 54116191 | L2923: 44000000 | M2923: =VLOOKUP(A2923,Sheet2!$A$1:G6647,2,0) -> 42037 | N2923: =VLOOKUP(A2923,Sheet2!$A$1:G6647,3,0) -> Color | O2923: =VLOOKUP(A2923,Sheet2!$A$1:G6647,4,0) -> Crime | P2923: =VLOOKUP(A2923,Sheet2!$A$1:G6647,5,0) -> English | Q2923: =VLOOKUP(A2923,Sheet2!$A$1:G6647,6,0) -> USA | R2923: =VLOOKUP(A2923,Sheet2!$A$1:G6647,7,0) -> R | S2923: =IF(Table1[[#This Row],[Language]]="English","English","Other language") -> English | T2923: =Table1[[#This Row],[Gross Revenue]]-Table1[[#This Row],[Budget]] -> 10116191 | U2923: =(Table1[[#This Row],[Gross Revenue]]/Table1[[#This Row],[Budget]])-1 -> 0.22991343 | V2923: =IF(J2923="","",IF(J2923<90,"<90 minutes",IF(J2923<=110,"90-110 minutes",IF(J2923<=130,"111-130 minutes",IF(J2923<=150,"131-150 minutes",">150 minutes"))))) -> >150 minutes | W2923: =Table1[[#This Row],[Profit]]/Table1[[#This Row],[Budget]] -> 0.22991343 | X2923: =IF(L2923="","", IF(L2923<Predictability!$B$1,"Low", IF(L2923<=Predictability!$B$2,"Mid","High"))) -> Mid | Y2923: =IF(W2923>=0.5,1,0) -> 0
A2924: The Haunted Mansion | B2924: Marsha Thomason | C2924: Rob Minkoff | D2924: 691 | E2924: 2622 | F2924: 50 | G2924: 988 | H2924: 4.9 | I2924: 122 | J2924: 88 | K2924: 75817994 | L2924: 90000000 | M2924: =VLOOKUP(A2924,Sheet2!$A$1:G6648,2,0) -> 37748 | N2924: =VLOOKUP(A2924,Sheet2!$A$1:G6648,3,0) -> Color | O2924: =VLOOKUP(A2924,Sheet2!$A$1:G6648,4,0) -> Comedy | P2924: =VLOOKUP(A2924,Sheet2!$A$1:G6648,5,0) -> English | Q2924: =VLOOKUP(A2924,Sheet2!$A$1:G6648,6,0) -> USA | R2924: =VLOOKUP(A2924,Sheet2!$A$1:G6648,7,0) -> PG | S2924: =IF(Table1[[#This Row],[Language]]="English","English","Other language") -> English | T2924: =Table1[[#This Row],[Gross Revenue]]-Table1[[#This Row],[Budget]] -> -14182006 | U2924: =(Table1[[#This Row],[Gross Revenue]]/Table1[[#This Row],[Budget]])-1 -> -0.15757784 | V2924: =IF(J2924="","",IF(J2924<90,"<90 minutes",IF(J2924<=110,"90-110 minutes",IF(J2924<=130,"111-130 minutes",IF(J2924<=150,"131-150 minutes",">150 minutes"))))) -> <90 minutes | W2924: =Table1[[#This Row],[Profit]]/Table1[[#This Row],[Budget]] -> -0.15757784 | X2924: =IF(L2924="","", IF(L2924<Predictability!$B$1,"Low", IF(L2924<=Predictability!$B$2,"Mid","High"))) -> High | Y2924: =IF(W2924>=0.5,1,0) -> 0
A2925: The Haunting | B2925: Liam Neeson | C2925: Jan de Bont | D2925: 14000 | E2925: 17786 | F2925: 101 | G2925: 0 | H2925: 4.9 | I2925: 167 | J2925: 113 | K2925: 91188905 | L2925: 80000000 | M2925: =VLOOKUP(A2925,Sheet2!$A$1:G6649,2,0) -> 36354 | N2925: =VLOOKUP(A2925,Sheet2!$A$1:G6649,3,0) -> Color | O2925: =VLOOKUP(A2925,Sheet2!$A$1:G6649,4,0) -> Fantasy | P2925: =VLOOKUP(A2925,Sheet2!$A$1:G6649,5,0) -> English | Q2925: =VLOOKUP(A2925,Sheet2!$A$1:G6649,6,0) -> USA | R2925: =VLOOKUP(A2925,Sheet2!$A$1:G6649,7,0) -> PG-13 | S2925: =IF(Table1[[#This Row],[Language]]="English","English","Other language") -> English | T2925: =Table1[[#This Row],[Gross Revenue]]-Table1[[#This Row],[Budget]] -> 11188905 | U2925: =(Table1[[#This Row],[Gross Revenue]]/Table1[[#This Row],[Budget]])-1 -> 0.13986131 | V2925: =IF(J2925="","",IF(J2925<90,"<90 minutes",IF(J2925<=110,"90-110 minutes",IF(J2925<=130,"111-130 minutes",IF(J2925<=150,"131-150 minutes",">150 minutes"))))) -> 111-130 minutes | W2925: =Table1[[#This Row],[Profit]]/Table1[[#This Row],[Budget]] -> 0.13986131 | X2925: =IF(L2925="","", IF(L2925<Predictability!$B$1,"Low", IF(L2925<=Predictability!$B$2,"Mid","High"))) -> High | Y2925: =IF(W2925>=0.5,1,0) -> 0
A2926: The Haunting of Molly Hartley | B2926: Jessica Lowndes | C2926: Mickey Liddell | D2926: 1000 | E2926: 4856 | F2926: 7 | G2926: 562 | H2926: 3.8 | I2926: 74 | J2926: 82 | K2926: 13350177 | L2926: 5000000 | M2926: =VLOOKUP(A2926,Sheet2!$A$1:G6650,2,0) -> 39593 | N2926: =VLOOKUP(A2926,Sheet2!$A$1:G6650,3,0) -> Color | O2926: =VLOOKUP(A2926,Sheet2!$A$1:G6650,4,0) -> Drama | P2926: =VLOOKUP(A2926,Sheet2!$A$1:G6650,5,0) -> English | Q2926: =VLOOKUP(A2926,Sheet2!$A$1:G6650,6,0) -> USA | R2926: =VLOOKUP(A2926,Sheet2!$A$1:G6650,7,0) -> PG-13 | S2926: =IF(Table1[[#This Row],[Language]]="English","English","Other language") -> English | T2926: =Table1[[#This Row],[Gross Revenue]]-Table1[[#This Row],[Budget]] -> 8350177 | U2926: =(Table1[[#This Row],[Gross Revenue]]/Table1[[#This Row],[Budget]])-1 -> 1.6700354 | V2926: =IF(J2926="","",IF(J2926<90,"<90 minutes",IF(J2926<=110,"90-110 minutes",IF(J2926<=130,"111-130 minutes",IF(J2926<=150,"131-150 minutes",">150 minutes"))))) -> <90 minutes | W2926: =Table1[[#This Row],[Profit]]/Table1[[#This Row],[Budget]] -> 1.6700354 | X2926: =IF(L2926="","", IF(L2926<Predictability!$B$1,"Low", IF(L2926<=Predictability!$B$2,"Mid","High"))) -> Low | Y2926: =IF(W2926>=0.5,1,0) -> 1
A2927: The Heart of Me | B2927: Olivia Williams | C2927: Thaddeus O'Sullivan | D2927: 766 | E2927: 1251 | F2927: 5 | G2927: 97 | H2927: 6.7 | I2927: 39 | J2927: 96 | K2927: 196067 | L2927: 7000000 | M2927: =VLOOKUP(A2927,Sheet2!$A$1:G6651,2,0) -> 37425 | N2927: =VLOOKUP(A2927,Sheet2!$A$1:G6651,3,0) -> Color | O2927: =VLOOKUP(A2927,Sheet2!$A$1:G6651,4,0) -> Drama | P2927: =VLOOKUP(A2927,Sheet2!$A$1:G6651,5,0) -> English | Q2927: =VLOOKUP(A2927,Sheet2!$A$1:G6651,6,0) -> UK | R2927: =VLOOKUP(A2927,Sheet2!$A$1:G6651,7,0) -> R | S2927: =IF(Table1[[#This Row],[Language]]="English","English","Other language") -> English | T2927: =Table1[[#This Row],[Gross Revenue]]-Table1[[#This Row],[Budget]] -> -6803933 | U2927: =(Table1[[#This Row],[Gross Revenue]]/Table1[[#This Row],[Budget]])-1 -> -0.97199043 | V2927: =IF(J2927="","",IF(J2927<90,"<90 minutes",IF(J2927<=110,"90-110 minutes",IF(J2927<=130,"111-130 minutes",IF(J2927<=150,"131-150 minutes",">150 minutes"))))) -> 90-110 minutes | W2927: =Table1[[#This Row],[Profit]]/Table1[[#This Row],[Budget]] -> -0.97199043 | X2927: =IF(L2927="","", IF(L2927<Predictability!$B$1,"Low", IF(L2927<=Predictability!$B$2,"Mid","High"))) -> Low | Y2927: =IF(W2927>=0.5,1,0) -> 0
A2928: The Heat | B2928: Michael Rapaport | C2928: Paul Feig | D2928: 975 | E2928: 4825 | F2928: 176 | G2928: 24000 | H2928: 6.6 | I2928: 270 | J2928: 123 | K2928: 159578352 | L2928: 43000000 | M2928: =VLOOKUP(A2928,Sheet2!$A$1:G6652,2,0) -> 41448 | N2928: =VLOOKUP(A2928,Sheet2!$A$1:G6652,3,0) -> Color | O2928: =VLOOKUP(A2928,Sheet2!$A$1:G6652,4,0) -> Action | P2928: =VLOOKUP(A2928,Sheet2!$A$1:G6652,5,0) -> English | Q2928: =VLOOKUP(A2928,Sheet2!$A$1:G6652,6,0) -> USA | R2928: =VLOOKUP(A2928,Sheet2!$A$1:G6652,7,0) -> R | S2928: =IF(Table1[[#This Row],[Language]]="English","English","Other language") -> English | T2928: =Table1[[#This Row],[Gross Revenue]]-Table1[[#This Row],[Budget]] -> 116578352 | U2928: =(Table1[[#This Row],[Gross Revenue]]/Table1[[#This Row],[Budget]])-1 -> 2.7111245 | V2928: =IF(J2928="","",IF(J2928<90,"<90 minutes",IF(J2928<=110,"90-110 minutes",IF(J2928<=130,"111-130 minutes",IF(J2928<=150,"131-150 minutes",">150 minutes"))))) -> 111-130 minutes | W2928: =Table1[[#This Row],[Profit]]/Table1[[#This Row],[Budget]] -> 2.7111245 | X2928: =IF(L2928="","", IF(L2928<Predictability!$B$1,"Low", IF(L2928<=Predictability!$B$2,"Mid","High"))) -> Mid | Y2928: =IF(W2928>=0.5,1,0) -> 1
A2929: The Hebrew Hammer | B2929: Judy Greer | C2929: Jonathan Kesselman | D2929: 2000 | E2929: 6227 | F2929: 4 | G2929: 3000 | H2929: 6.2 | I2929: 35 | J2929: 87 | K2929: 19539 | L2929: 1000000 | M2929: =VLOOKUP(A2929,Sheet2!$A$1:G6653,2,0) -> 37934 | N2929: =VLOOKUP(A2929,Sheet2!$A$1:G6653,3,0) -> Black and White | O2929: =VLOOKUP(A2929,Sheet2!$A$1:G6653,4,0) -> Comedy | P2929: =VLOOKUP(A2929,Sheet2!$A$1:G6653,5,0) -> English | Q2929: =VLOOKUP(A2929,Sheet2!$A$1:G6653,6,0) -> USA | R2929: =VLOOKUP(A2929,Sheet2!$A$1:G6653,7,0) -> R | S2929: =IF(Table1[[#This Row],[Language]]="English","English","Other language") -> English | T2929: =Table1[[#This Row],[Gross Revenue]]-Table1[[#This Row],[Budget]] -> -980461 | U2929: =(Table1[[#This Row],[Gross Revenue]]/Table1[[#This Row],[Budget]])-1 -> -0.980461 | V2929: =IF(J2929="","",IF(J2929<90,"<90 minutes",IF(J2929<=110,"90-110 minutes",IF(J2929<=130,"111-130 minutes",IF(J2929<=150,"131-150 minutes",">150 minutes"))))) -> <90 minutes | W2929: =Table1[[#This Row],[Profit]]/Table1[[#This Row],[Budget]] -> -0.980461 | X2929: =IF(L2929="","", IF(L2929<Predictability!$B$1,"Low", IF(L2929<=Predictability!$B$2,"Mid","High"))) -> Low | Y2929: =IF(W2929>=0.5,1,0) -> 0
A2930: The Help | B2930: Emma Stone | C2930: Tate Taylor | D2930: 15000 | E2930: 23227 | F2930: 150 | G2930: 75000 | H2930: 8.1 | I2930: 373 | J2930: 146 | K2930: 169705587 | L2930: 25000000 | M2930: =VLOOKUP(A2930,Sheet2!$A$1:G6654,2,0) -> 40590 | N2930: =VLOOKUP(A2930,Sheet2!$A$1:G6654,3,0) -> Color | O2930: =VLOOKUP(A2930,Sheet2!$A$1:G6654,4,0) -> Drama | P2930: =VLOOKUP(A2930,Sheet2!$A$1:G6654,5,0) -> English | Q2930: =VLOOKUP(A2930,Sheet2!$A$1:G6654,6,0) -> USA | R2930: =VLOOKUP(A2930,Sheet2!$A$1:G6654,7,0) -> PG-13 | S2930: =IF(Table1[[#This Row],[Language]]="English","English","Other language") -> English | T2930: =Table1[[#This Row],[Gross Revenue]]-Table1[[#This Row],[Budget]] -> 144705587 | U2930: =(Table1[[#This Row],[Gross Revenue]]/Table1[[#This Row],[Budget]])-1 -> 5.7882235 | V2930: =IF(J2930="","",IF(J2930<90,"<90 minutes",IF(J2930<=110,"90-110 minutes",IF(J2930<=130,"111-130 minutes",IF(J2930<=150,"131-150 minutes",">150 minutes"))))) -> 131-150 minutes | W2930: =Table1[[#This Row],[Profit]]/Table1[[#This Row],[Budget]] -> 5.7882235 | X2930: =IF(L2930="","", IF(L2930<Predictability!$B$1,"Low", IF(L2930<=Predictability!$B$2,"Mid","High"))) -> Mid | Y2930: =IF(W2930>=0.5,1,0) -> 1
A2931: The Hills Have Eyes | B2931: Dan Byrd | C2931: Alexandre Aja | D2931: 1000 | E2931: 4500 | F2931: 192 | G2931: 0 | H2931: 6.4 | I2931: 265 | J2931: 108 | K2931: 41777564 | L2931: 15000000 | M2931: =VLOOKUP(A2931,Sheet2!$A$1:G6655,2,0) -> 38912 | N2931: =VLOOKUP(A2931,Sheet2!$A$1:G6655,3,0) -> Color | O2931: =VLOOKUP(A2931,Sheet2!$A$1:G6655,4,0) -> Horror | P2931: =VLOOKUP(A2931,Sheet2!$A$1:G6655,5,0) -> English | Q2931: =VLOOKUP(A2931,Sheet2!$A$1:G6655,6,0) -> USA | R2931: =VLOOKUP(A2931,Sheet2!$A$1:G6655,7,0) -> R | S2931: =IF(Table1[[#This Row],[Language]]="English","English","Other language") -> English | T2931: =Table1[[#This Row],[Gross Revenue]]-Table1[[#This Row],[Budget]] -> 26777564 | U2931: =(Table1[[#This Row],[Gross Revenue]]/Table1[[#This Row],[Budget]])-1 -> 1.7851709 | V2931: =IF(J2931="","",IF(J2931<90,"<90 minutes",IF(J2931<=110,"90-110 minutes",IF(J2931<=130,"111-130 minutes",IF(J2931<=150,"131-150 minutes",">150 minutes"))))) -> 90-110 minutes | W2931: =Table1[[#This Row],[Profit]]/Table1[[#This Row],[Budget]] -> 1.7851709 | X2931: =IF(L2931="","", IF(L2931<Predictability!$B$1,"Low", IF(L2931<=Predictability!$B$2,"Mid","High"))) -> Mid | Y2931: =IF(W2931>=0.5,1,0) -> 1
A2932: The Hills Have Eyes II | B2932: Jeff Kober | C2932: Martin Weisz | D2932: 919 | E2932: 2559 | F2932: 7 | G2932: 0 | H2932: 5.1 | I2932: 161 | J2932: 89 | K2932: 20801344 | L2932: 15000000 | M2932: =VLOOKUP(A2932,Sheet2!$A$1:G6656,2,0) -> 39167 | N2932: =VLOOKUP(A2932,Sheet2!$A$1:G6656,3,0) -> Color | O2932: =VLOOKUP(A2932,Sheet2!$A$1:G6656,4,0) -> Horror | P2932: =VLOOKUP(A2932,Sheet2!$A$1:G6656,5,0) -> English | Q2932: =VLOOKUP(A2932,Sheet2!$A$1:G6656,6,0) -> USA | R2932: =VLOOKUP(A2932,Sheet2!$A$1:G6656,7,0) -> R | S2932: =IF(Table1[[#This Row],[Language]]="English","English","Other language") -> English | T2932: =Table1[[#This Row],[Gross Revenue]]-Table1[[#This Row],[Budget]] -> 5801344 | U2932: =(Table1[[#This Row],[Gross Revenue]]/Table1[[#This Row],[Budget]])-1 -> 0.38675627 | V2932: =IF(J2932="","",IF(J2932<90,"<90 minutes",IF(J2932<=110,"90-110 minutes",IF(J2932<=130,"111-130 minutes",IF(J2932<=150,"131-150 minutes",">150 minutes"))))) -> <90 minutes | W2932: =Table1[[#This Row],[Profit]]/Table1[[#This Row],[Budget]] -> 0.38675627 | X2932: =IF(L2932="","", IF(L2932<Predictability!$B$1,"Low", IF(L2932<=Predictability!$B$2,"Mid","High"))) -> Mid | Y2932: =IF(W2932>=0.5,1,0) -> 0
A2933: The History Boys | B2933: Dominic Cooper | C2933: Nicholas Hytner | D2933: 3000 | E2933: 5977 | F2933: 13 | G2933: 0 | H2933: 6.9 | I2933: 112 | J2933: 109 | K2933: 2706659 | L2933: 2000000 | M2933: =VLOOKUP(A2933,Sheet2!$A$1:G6657,2,0) -> 38944 | N2933: =VLOOKUP(A2933,Sheet2!$A$1:G6657,3,0) -> Color | O2933: =VLOOKUP(A2933,Sheet2!$A$1:G6657,4,0) -> Comedy | P2933: =VLOOKUP(A2933,Sheet2!$A$1:G6657,5,0) -> English | Q2933: =VLOOKUP(A2933,Sheet2!$A$1:G6657,6,0) -> UK | R2933: =VLOOKUP(A2933,Sheet2!$A$1:G6657,7,0) -> R | S2933: =IF(Table1[[#This Row],[Language]]="English","English","Other language") -> English | T2933: =Table1[[#This Row],[Gross Revenue]]-Table1[[#This Row],[Budget]] -> 706659 | U2933: =(Table1[[#This Row],[Gross Revenue]]/Table1[[#This Row],[Budget]])-1 -> 0.3533295 | V2933: =IF(J2933="","",IF(J2933<90,"<90 minutes",IF(J2933<=110,"90-110 minutes",IF(J2933<=130,"111-130 minutes",IF(J2933<=150,"131-150 minutes",">150 minutes"))))) -> 90-110 minutes | W2933: =Table1[[#This Row],[Profit]]/Table1[[#This Row],[Budget]] -> 0.3533295 | X2933: =IF(L2933="","", IF(L2933<Predictability!$B$1,"Low", IF(L2933<=Predictability!$B$2,"Mid","High"))) -> Low | Y2933: =IF(W2933>=0.5,1,0) -> 0
A2934: The Hitchhiker's Guide to the Galaxy | B2934: Zooey Deschanel | C2934: Garth Jennings | D2934: 11000 | E2934: 14073 | F2934: 37 | G2934: 10000 | H2934: 6.8 | I2934: 276 | J2934: 109 | K2934: 51019112 | L2934: 50000000 | M2934: =VLOOKUP(A2934,Sheet2!$A$1:G6658,2,0) -> 38458 | N2934: =VLOOKUP(A2934,Sheet2!$A$1:G6658,3,0) -> Color | O2934: =VLOOKUP(A2934,Sheet2!$A$1:G6658,4,0) -> Adventure | P2934: =VLOOKUP(A2934,Sheet2!$A$1:G6658,5,0) -> English | Q2934: =VLOOKUP(A2934,Sheet2!$A$1:G6658,6,0) -> USA | R2934: =VLOOKUP(A2934,Sheet2!$A$1:G6658,7,0) -> PG | S2934: =IF(Table1[[#This Row],[Language]]="English","English","Other language") -> English | T2934: =Table1[[#This Row],[Gross Revenue]]-Table1[[#This Row],[Budget]] -> 1019112 | U2934: =(Table1[[#This Row],[Gross Revenue]]/Table1[[#This Row],[Budget]])-1 -> 0.02038224 | V2934: =IF(J2934="","",IF(J2934<90,"<90 minutes",IF(J2934<=110,"90-110 minutes",IF(J2934<=130,"111-130 minutes",IF(J2934<=150,"131-150 minutes",">150 minutes"))))) -> 90-110 minutes | W2934: =Table1[[#This Row],[Profit]]/Table1[[#This Row],[Budget]] -> 0.02038224 | X2934: =IF(L2934="","", IF(L2934<Predictability!$B$1,"Low", IF(L2934<=Predictability!$B$2,"Mid","High"))) -> Mid | Y2934: =IF(W2934>=0.5,1,0) -> 0
... A3726: Zoom | B3726: Kevin Zegers | C3726: Peter Hewitt | D3726: 2000 | E3726: 5022 | F3726: 12 | G3726: 494 | H3726: 4.2 | I3726: 63 | J3726: 83 | K3726: 11631245 | L3726: 35000000 | M3726: =VLOOKUP(A3726,Sheet2!$A$1:G7450,2,0) -> 38810 | N3726: =VLOOKUP(A3726,Sheet2!$A$1:G7450,3,0) -> Color | O3726: =VLOOKUP(A3726,Sheet2!$A$1:G7450,4,0) -> Action | P3726: =VLOOKUP(A3726,Sheet2!$A$1:G7450,5,0) -> English | Q3726: =VLOOKUP(A3726,Sheet2!$A$1:G7450,6,0) -> USA | R3726: =VLOOKUP(A3726,Sheet2!$A$1:G7450,7,0) -> PG | S3726: =IF(Table1[[#This Row],[Language]]="English","English","Other language") -> English | T3726: =Table1[[#This Row],[Gross Revenue]]-Table1[[#This Row],[Budget]] -> -23368755 | U3726: =(Table1[[#This Row],[Gross Revenue]]/Table1[[#This Row],[Budget]])-1 -> -0.66767871 | V3726: =IF(J3726="","",IF(J3726<90,"<90 minutes",IF(J3726<=110,"90-110 minutes",IF(J3726<=130,"111-130 minutes",IF(J3726<=150,"131-150 minutes",">150 minutes"))))) -> <90 minutes | W3726: =Table1[[#This Row],[Profit]]/Table1[[#This Row],[Budget]] -> -0.66767871 | X3726: =IF(L3726="","", IF(L3726<Predictability!$B$1,"Low", IF(L3726<=Predictability!$B$2,"Mid","High"))) -> Mid | Y3726: =IF(W3726>=0.5,1,0) -> 0

Sheet Predictability
A1: P25 Budget | B1: =_xlfn.PERCENTILE.INC(Main!L:L,0.25) -> 9000000 | D1: Mid budget
A2: P75 Budget | B2: =_xlfn.PERCENTILE.INC(Main!L:L,0.75) -> 50000000 | D2: 9000000-50000000
A6: Budget_Tier | B6: r: Cast → ROI | C6: r: Movie → ROI | D6: r: Lead_Actor → ROI | E6: r: Director → ROI
A7: Low | B7: {=_xlfn.LET( _xlpm.tier,$A7, _xlpm.x,_xlfn._xlws.FILTER(Main!$E:$E,(Main!$X:$X=_xlpm.tier)*ISNUMBER(Main!$E:$E)*ISNUMBER(Main!$W:$W)), _xlpm.y,_xlfn._xlws.FILTER(Main!$W:$W,(Main!$X:$X=_xlpm.tier)*ISNUMBER(Main!$E:$E)*ISNUMBER(Main!$W:$W)), IFERROR(CORREL(_xlpm.x,_xlpm.y),"") )} -> -0.025455883 | C7: {=_xlfn.LET( _xlpm.tier,$A7, _xlpm.x,_xlfn._xlws.FILTER(Main!$G:$G,(Main!$X:$X=_xlpm.tier)*ISNUMBER(Main!$G:$G)*ISNUMBER(Main!$W:$W)), _xlpm.y,_xlfn._xlws.FILTER(Main!$W:$W,(Main!$X:$X=_xlpm.tier)*ISNUMBER(Main!$G:$G)*ISNUMBER(Main!$W:$W)), IFERROR(CORREL(_xlpm.x,_xlpm.y),"") )} -> 0.012575939 | D7: {=_xlfn.LET( _xlpm.tier,$A7, _xlpm.x,_xlfn._xlws.FILTER(Main!$D:$D,(Main!$X:$X=_xlpm.tier)*ISNUMBER(Main!$D:$D)*ISNUMBER(Main!$W:$W)), _xlpm.y,_xlfn._xlws.FILTER(Main!$W:$W,(Main!$X:$X=_xlpm.tier)*ISNUMBER(Main!$D:$D)*ISNUMBER(Main!$W:$W)), IFERROR(CORREL(_xlpm.x,_xlpm.y),"") )} -> -0.020580915 | E7: {=_xlfn.LET( _xlpm.tier,$A7, _xlpm.x,_xlfn._xlws.FILTER(Main!$F:$F,(Main!$X:$X=_xlpm.tier)*ISNUMBER(Main!$F:$F)*ISNUMBER(Main!$W:$W)), _xlpm.y,_xlfn._xlws.FILTER(Main!$W:$W,(Main!$X:$X=_xlpm.tier)*ISNUMBER(Main!$F:$F)*ISNUMBER(Main!$W:$W)), IFERROR(CORREL(_xlpm.x,_xlpm.y),"") )} -> -0.0068706769
A8: Mid | B8: {=_xlfn.LET( _xlpm.tier,$A8, _xlpm.x,_xlfn._xlws.FILTER(Main!$E:$E,(Main!$X:$X=_xlpm.tier)*ISNUMBER(Main!$E:$E)*ISNUMBER(Main!$W:$W)), _xlpm.y,_xlfn._xlws.FILTER(Main!$W:$W,(Main!$X:$X=_xlpm.tier)*ISNUMBER(Main!$E:$E)*ISNUMBER(Main!$W:$W)), IFERROR(CORREL(_xlpm.x,_xlpm.y),"") )} -> 0.042609917 | C8: {=_xlfn.LET( _xlpm.tier,$A8, _xlpm.x,_xlfn._xlws.FILTER(Main!$G:$G,(Main!$X:$X=_xlpm.tier)*ISNUMBER(Main!$G:$G)*ISNUMBER(Main!$W:$W)), _xlpm.y,_xlfn._xlws.FILTER(Main!$W:$W,(Main!$X:$X=_xlpm.tier)*ISNUMBER(Main!$G:$G)*ISNUMBER(Main!$W:$W)), IFERROR(CORREL(_xlpm.x,_xlpm.y),"") )} -> 0.17748557 | D8: {=_xlfn.LET( _xlpm.tier,$A8, _xlpm.x,_xlfn._xlws.FILTER(Main!$D:$D,(Main!$X:$X=_xlpm.tier)*ISNUMBER(Main!$D:$D)*ISNUMBER(Main!$W:$W)), _xlpm.y,_xlfn._xlws.FILTER(Main!$W:$W,(Main!$X:$X=_xlpm.tier)*ISNUMBER(Main!$D:$D)*ISNUMBER(Main!$W:$W)), IFERROR(CORREL(_xlpm.x,_xlpm.y),"") )} -> 0.03567474 | E8: {=_xlfn.LET( _xlpm.tier,$A8, _xlpm.x,_xlfn._xlws.FILTER(Main!$F:$F,(Main!$X:$X=_xlpm.tier)*ISNUMBER(Main!$F:$F)*ISNUMBER(Main!$W:$W)), _xlpm.y,_xlfn._xlws.FILTER(Main!$W:$W,(Main!$X:$X=_xlpm.tier)*ISNUMBER(Main!$F:$F)*ISNUMBER(Main!$W:$W)), IFERROR(CORREL(_xlpm.x,_xlpm.y),"") )} -> 0.10865116
A9: High | B9: {=_xlfn.LET( _xlpm.tier,$A9, _xlpm.x,_xlfn._xlws.FILTER(Main!$E:$E,(Main!$X:$X=_xlpm.tier)*ISNUMBER(Main!$E:$E)*ISNUMBER(Main!$W:$W)), _xlpm.y,_xlfn._xlws.FILTER(Main!$W:$W,(Main!$X:$X=_xlpm.tier)*ISNUMBER(Main!$E:$E)*ISNUMBER(Main!$W:$W)), IFERROR(CORREL(_xlpm.x,_xlpm.y),"") )} -> 0.14691975 | C9: {=_xlfn.LET( _xlpm.tier,$A9, _xlpm.x,_xlfn._xlws.FILTER(Main!$G:$G,(Main!$X:$X=_xlpm.tier)*ISNUMBER(Main!$G:$G)*ISNUMBER(Main!$W:$W)), _xlpm.y,_xlfn._xlws.FILTER(Main!$W:$W,(Main!$X:$X=_xlpm.tier)*ISNUMBER(Main!$G:$G)*ISNUMBER(Main!$W:$W)), IFERROR(CORREL(_xlpm.x,_xlpm.y),"") )} -> 0.21787526 | D9: {=_xlfn.LET( _xlpm.tier,$A9, _xlpm.x,_xlfn._xlws.FILTER(Main!$D:$D,(Main!$X:$X=_xlpm.tier)*ISNUMBER(Main!$D:$D)*ISNUMBER(Main!$W:$W)), _xlpm.y,_xlfn._xlws.FILTER(Main!$W:$W,(Main!$X:$X=_xlpm.tier)*ISNUMBER(Main!$D:$D)*ISNUMBER(Main!$W:$W)), IFERROR(CORREL(_xlpm.x,_xlpm.y),"") )} -> 0.082398348 | E9: {=_xlfn.LET( _xlpm.tier,$A9, _xlpm.x,_xlfn._xlws.FILTER(Main!$F:$F,(Main!$X:$X=_xlpm.tier)*ISNUMBER(Main!$F:$F)*ISNUMBER(Main!$W:$W)), _xlpm.y,_xlfn._xlws.FILTER(Main!$W:$W,(Main!$X:$X=_xlpm.tier)*ISNUMBER(Main!$F:$F)*ISNUMBER(Main!$W:$W)), IFERROR(CORREL(_xlpm.x,_xlpm.y),"") )} -> 0.10065681

Sheet top leads actor by FB likes R
A1: Years (Release Date) | B1: (Multiple Items)
A3: Row Labels | B3: Count of Title | C3: Average of Median ROI | D3: Average of Lead Actor FB Likes | E3: Average of IMDb Score (1-10)
A4: Mackenzie Foy | B4: 2 | C4: 1.1909079 | D4: 6000 | E4: 7.7
A5: Bojana Novakovic | B5: 3 | C5: 0.79144341 | D5: 2000 | E5: 6.5
A6: Bradley Cooper | B6: 12 | C6: 0.21717823 | D6: 14000 | E6: 6.4666667
A7: Larry David | B7: 2 | C7: 0.19178668 | D7: 860 | E7: 7.4
A8: ZoÃ« Kravitz | B8: 2 | C8: 0.19178668 | D8: 943 | E8: 6.75
A9: Rob Riggle | B9: 2 | C9: 0.19178668 | D9: 839 | E9: 6.4
A10: Mark Duplass | B10: 2 | C10: 0.19178668 | D10: 830 | E10: 6.65
A11: Busy Philipps | B11: 2 | C11: 0.19178668 | D11: 1000 | E11: 6.45
A12: Clifton Collins Jr. | B12: 3 | C12: 0.19178668 | D12: 968 | E12: 6.5
A13: Janeane Garofalo | B13: 2 | C13: 0.19178668 | D13: 1000 | E13: 6.75
A14: Zachary Gordon | B14: 3 | C14: 0.16694755 | D14: 975 | E14: 6.6333333
A15: Alan Rickman | B15: 2 | C15: 0.15452798 | D15: 25000 | E15: 7.15
... A74: Grand Total | B74: 381 | C74: 0.070021487 | D74: 13399.919 | E74: 6.7965879

Sheet top leads actor by FB likes
A1: Years (Release Date) | B1: (Multiple Items)
A3: Row Labels | B3: Count of Title | C3: Average of Lead Actor FB Likes | D3: Average of IMDb Score (1-10)
A4: Johnny Depp | B4: 16 | C4: 40000 | D4: 6.55
A5: Jennifer Lawrence | B5: 13 | C5: 34000 | D5: 7.0692308
A6: Ryan Gosling | B6: 10 | C6: 33000 | D6: 7.18
A7: Leonardo DiCaprio | B7: 11 | C7: 29000 | D7: 7.8636364
A8: Tom Hardy | B8: 7 | C8: 27000 | D8: 7.4
A9: Chris Hemsworth | B9: 13 | C9: 26000 | D9: 6.9153846
A10: Alan Rickman | B10: 2 | C10: 25000 | D10: 7.15
A11: J.K. Simmons | B11: 19 | C11: 24000 | D11: 6.7368421
A12: Paul Walker | B12: 7 | C12: 23000 | D12: 6.6857143
A13: Christian Bale | B13: 12 | C13: 23000 | D13: 7.4666667
A14: Joseph Gordon-Levitt | B14: 12 | C14: 23000 | D14: 6.8833333
A15: Philip Seymour Hoffman | B15: 7 | C15: 22000 | D15: 7.2571429
... A143: Terry Pheto | B143: 2 | C143: 113 | D143: 7.2
A144: (blank) | B144: 2 | D144: 7.3
A145: Grand Total | B145: 734 | C145: 13272.003 | D145: 6.8666213

Sheet filter table of genere
A1: Years (Release Date) | B1: (Multiple Items)
A2: Country | B2: USA
A3: Is _English | B3: English
A5: Row Labels | B5: Count of Title | C5: Median Of Profit | D5: Average of Profit | E5: Average of Budget | F5: Median of ROI
A6: Comedy | B6: 399 | C6: 1637763 | D6: 14247390 | E6: 25497178 | F6: 0.19178668
A7: Adventure | B7: 156 | C7: 3892693.5 | D7: 26423027 | E7: 81523397 | F7: 0.11726929
A8: Grand Total | B8: 555 | C8: 2271581.3 | D8: 17669731 | E8: 41245088 | F8: 0.17084125

Sheet top leads dirctors
A1: Years (Release Date) | B1: (Multiple Items)
A3: Row Labels | B3: Median Of ROI | C3: Average of Lead Actor FB Likes | D3: Average of IMDb Score (1-10) | E3: Count of Title
A4: Adam McKay | B4: 0.071817633 | C4: 118666.67 | D4: 6.9166667 | E4: 6
A5: Gore Verbinski | B5: 0.033388512 | C5: 33714.286 | D5: 6.9857143 | E5: 7
A6: Martin Scorsese | B6: 0.0011990187 | C6: 27000 | D6: 7.8833333 | E6: 6
A7: Francis Lawrence | B7: 0.029901168 | C7: 26600 | D7: 7 | E7: 5
A8: David O. Russell | B8: 0.05595697 | C8: 26200 | D8: 7.26 | E8: 5
A9: Tim Burton | B9: 0.074548618 | C9: 23117.5 | D9: 6.8125 | E9: 8
A10: David Yates | B10: 0.11726929 | C10: 23000 | D10: 7.5 | E10: 2
A11: Shane Black | B11: 0.071817633 | C11: 21000 | D11: 7.4 | E11: 2
A12: Jason Reitman | B12: 0.074611607 | C12: 21000 | D12: 7.14 | E12: 5
A13: Boaz Yakin | B13: 0.0069888169 | C13: 20000 | D13: 7.0333333 | E13: 3
A14: Matthew Vaughn | B14: 0.003370193 | C14: 19138.25 | D14: 7.65 | E14: 4
A15: Edward Zwick | B15: 0.086968184 | C15: 18000 | D15: 7.4666667 | E15: 3
... A46: Grand Total | B46: 0.067902512 | C46: 20317.006 | D46: 7.1203704 | E46: 162

Sheet budget labels vs med roi & pro
A1: Years (Release Date) | B1: (Multiple Items)
A2: Country | B2: USA
A4: Row Labels | B4: Average of Median ROI | C4: Average of Median Profit | D4: Count of Title
A5: Low | B5: 0.18258996 | C5: 2350888.7 | D5: 410
A6: High | B6: 0.034886851 | C6: 549360.09 | D6: 551
A7: Medium | B7: 0.10188948 | C7: 1295191 | D7: 467
A8: Grand Total | B8: 0.098177878 | C8: 1297149.6 | D8: 1428

Sheet usa as propfit and stable count
A1: Years (Release Date) | B1: (Multiple Items)
A3: Country | B3: Average of %Profit | C3: Average of Median ROI
A4: Australia | B4: -0.21351567 | C4: 0.05646534
A5: Canada | B5: -0.040151882 | C5: 0.15264831
A6: France | B6: 0.44402451 | C6: 0.033925533
A7: Germany | B7: 0.063230393 | C7: 0.076430959
A8: India | B8: -0.39097743 | C8: 0.0082337692
A9: Spain | B9: -0.36495258 | C9: 0.10412077
A10: UK | B10: 0.17608435 | C10: 0.018934553
A11: USA | B11: 5.9820499 | C11: 0.094741277
A12: Grand Total | B12: 4.9113839 | C12: 0.086275288

Sheet Count of movies by years
A2: Years (Release Date) | B2: (Multiple Items)
A3: Country | B3: USA
A5: Genre | B5: Average of Movie FB Likes | C5: Average of Budget | D5: Average of ROI | E5: StdDev of ROI
A6: Biography | B6: 12882.517 | C6: 13241379 | D6: 0.29115927 | E6: 1.7162808
A7: Crime | B7: 10635.121 | C7: 11621212 | D7: 0.34657862 | E7: 1.5301509
A8: Adventure | B8: 10058.686 | C8: 15542857 | D8: 0.79998917 | E8: 1.4098576
A9: Horror | B9: 9266.28 | C9: 11649900 | D9: 2.7105793 | E9: 3.9143176
A10: Drama | B10: 6359.7358 | C10: 12966981 | D10: 0.62479401 | E10: 1.7609228
A11: Action | B11: 4921.3 | C11: 14787500 | D11: 0.58171894 | E11: 1.7720312
A12: Comedy | B12: 4085.8808 | C12: 13222798 | D12: 1.1998821 | E12: 4.0184939
A13: Grand Total | B13: 6583.2901 | C13: 13193405 | D13: 1.0380318 | E13: 3.1227711

Sheet NEW DIRECTORS VS ROI 
A1: Years (Release Date) | B1: (Multiple Items)
A2: Country | B2: USA
A4: Directors | B4: Count of Title
A5: Drama | B5: 14
A6: Angelina Jolie Pitt | B6: 2
A7: Christopher Nolan | B7: 1
A8: Clint Eastwood | B8: 4
A9: David Fincher | B9: 1
A10: Ethan Coen | B10: 1
A11: Quentin Tarantino | B11: 1
A12: Ron Howard | B12: 1
A13: Steven Spielberg | B13: 2
A14: Woody Allen | B14: 1
A15: Action | B15: 10
A16: Christopher Nolan | B16: 3
... A50: Grand Total | B50: 58

Sheet NEW ACTORS VS ROI (2)
A1: Years (Release Date) | B1: (Multiple Items)
A2: Country | B2: USA
A4: Row Labels | B4: Average of Lead Actor FB Likes | C4: Count of Title | D4: Average of ROI
A5: Shailene Woodley | B5: 8000 | C5: 3 | D5: 4.7592574
A6: QuvenzhanÃ© Wallis | B6: 2000 | C6: 3 | D6: 2.752516
A7: Benh Zeitlin | B7: 2000 | C7: 1 | D7: 6.1024428
A8: Steve McQueen | B8: 2000 | C8: 1 | D8: 1.8333935
A9: Will Gluck | B9: 2000 | C9: 1 | D9: 0.32171172
A10: Steve Carell | B10: 7000 | C10: 7 | D10: 2.650453
A11: Jonathan Dayton | B11: 7000 | C11: 1 | D11: 6.4862435
A12: Kyle Balda | B12: 7000 | C12: 1 | D12: 3.54094
A13: Lorene Scafaria | B13: 7000 | C13: 1 | D13: -0.3380827
A14: Nat Faxon | B14: 7000 | C14: 1 | D14: 3.3002196
A15: Peter Sollett | B15: 7000 | C15: 1 | D15: -0.92385886
A16: Pierre Coffin | B16: 7000 | C16: 2 | D16: 3.2438549
... A706: Grand Total | B706: 15967.643 | C706: 649 | D706: 0.60900613

Sheet NEW ACTORS VS ROI
A1: Years (Release Date) | B1: (Multiple Items)
A2: Country | B2: USA
A4: Row Labels | B4: Average of Lead Actor FB Likes | C4: Count of Title | D4: Average of ROI
A5: Shailene Woodley | B5: 8000 | C5: 3 | D5: 4.7592574
A6: QuvenzhanÃ© Wallis | B6: 2000 | C6: 3 | D6: 2.752516
A7: Steve Carell | B7: 7000 | C7: 7 | D7: 2.650453
A8: Jennifer Lawrence | B8: 34000 | C8: 12 | D8: 2.5739128
A9: Natalie Portman | B9: 20000 | C9: 4 | D9: 2.1450919
A10: Tina Fey | B10: 2000 | C10: 4 | D10: 2.1210753
A11: Robert Pattinson | B11: 21000 | C11: 5 | D11: 2.1047124
A12: Channing Tatum | B12: 17000 | C12: 15 | D12: 2.0335113
A13: Bradley Cooper | B13: 14000 | C13: 12 | D13: 1.8849913
A14: Emma Stone | B14: 15000 | C14: 11 | D14: 1.8606405
A15: Olivia Wilde | B15: 10000 | C15: 4 | D15: 1.6725053
A16: Josh Hutcherson | B16: 14000 | C16: 6 | D16: 1.6293859
... A107: Grand Total | B107: 15967.643 | C107: 649 | D107: 0.60900613

Sheet Main (2) - Median
A1: Title | B1: Lead Actor | C1: Director Name | D1: Lead Actor FB Likes | E1: Cast FB Likes | F1: Director FB Likes | G1: Movie FB Likes | H1: IMDb Score (1-10) | I1: Total Reviews | J1: Duration (min) | K1: Gross Revenue | L1: Budget | M1: Release Date | N1: Color/B&W | O1: Genre | P1: Language | Q1: Country | R1: Rating | S1: Is _English | T1: Profit | U1: %Profit | V1: Duration_Class | W1: ROI | X1: Median Profit | Y1: Median ROI | Z1: Budget Tier
A2: [Rec] 2 | B2: Jonathan D. Mellor | C2: Jaume BalaguerÃ³ | D2: 37 | E2: 73 | F2: 57 | G2: 4000 | H2: 6.6 | I2: 222 | J2: 85 | K2: 27024 | L2: 5600000 | M2: =VLOOKUP(A2,Sheet2!$A$1:G3726,2,0) -> 39921 | N2: =VLOOKUP(A2,Sheet2!$A$1:G3726,3,0) -> Color | O2: =VLOOKUP(A2,Sheet2!$A$1:G3726,4,0) -> Horror | P2: =VLOOKUP(A2,Sheet2!$A$1:G3726,5,0) -> Spanish | Q2: =VLOOKUP(A2,Sheet2!$A$1:G3726,6,0) -> Spain | R2: =VLOOKUP(A2,Sheet2!$A$1:G3726,7,0) -> R | S2: =IF(Table19[[#This Row],[Language]]="English","English","Other language") -> Other language | T2: =Table19[[#This Row],[Gross Revenue]]-Table19[[#This Row],[Budget]] -> -5572976 | U2: =(Table19[[#This Row],[Gross Revenue]]/Table19[[#This Row],[Budget]])-1 -> -0.99517429 | V2: =IF(J2="","",IF(J2<90,"<90 minutes",IF(J2<=110,"90-110 minutes",IF(J2<=130,"111-130 minutes",IF(J2<=150,"131-150 minutes",">150 minutes"))))) -> <90 minutes | W2: =Table19[[#This Row],[Profit]]/Table19[[#This Row],[Budget]]*100 -> -99.517429 | X2: 16235088 | Y2: 1.1909079 | Z2: =IF(L2="","",IF(L2<=$AA$26,"Low",IF(L2<=$AA$28,"Medium","High"))) -> Low
A3: 10 Days in a Madhouse | B3: Christopher Lambert | C3: Timothy Hines | D3: 1000 | E3: 2059 | F3: 0 | G3: 26000 | H3: 7.5 | I3: 1 | J3: 111 | K3: 14616 | L3: 12000000 | M3: =VLOOKUP(A3,Sheet2!$A$1:G3727,2,0) -> 42130 | N3: =VLOOKUP(A3,Sheet2!$A$1:G3727,3,0) -> Color | O3: =VLOOKUP(A3,Sheet2!$A$1:G3727,4,0) -> Drama | P3: =VLOOKUP(A3,Sheet2!$A$1:G3727,5,0) -> English | Q3: =VLOOKUP(A3,Sheet2!$A$1:G3727,6,0) -> USA | R3: =VLOOKUP(A3,Sheet2!$A$1:G3727,7,0) -> R | S3: =IF(Table19[[#This Row],[Language]]="English","English","Other language") -> English | T3: =Table19[[#This Row],[Gross Revenue]]-Table19[[#This Row],[Budget]] -> -11985384 | U3: =(Table19[[#This Row],[Gross Revenue]]/Table19[[#This Row],[Budget]])-1 -> -0.998782 | V3: =IF(J3="","",IF(J3<90,"<90 minutes",IF(J3<=110,"90-110 minutes",IF(J3<=130,"111-130 minutes",IF(J3<=150,"131-150 minutes",">150 minutes"))))) -> 111-130 minutes | W3: =Table19[[#This Row],[Profit]]/Table19[[#This Row],[Budget]]*100 -> -99.8782 | X3: -434215.5 | Y3: -0.10115101 | Z3: =IF(L3="","",IF(L3<=$AA$26,"Low",IF(L3<=$AA$28,"Medium","High"))) -> Low
A4: 10 Things I Hate About You | B4: Joseph Gordon-Levitt | C4: Gil Junger | D4: 23000 | E4: 37907 | F4: 19 | G4: 10000 | H4: 7.2 | I4: 133 | J4: 97 | K4: 38176108 | L4: 16000000 | M4: =VLOOKUP(A4,Sheet2!$A$1:G3728,2,0) -> 36245 | N4: =VLOOKUP(A4,Sheet2!$A$1:G3728,3,0) -> Color | O4: =VLOOKUP(A4,Sheet2!$A$1:G3728,4,0) -> Comedy | P4: =VLOOKUP(A4,Sheet2!$A$1:G3728,5,0) -> English | Q4: =VLOOKUP(A4,Sheet2!$A$1:G3728,6,0) -> USA | R4: =VLOOKUP(A4,Sheet2!$A$1:G3728,7,0) -> PG-13 | S4: =IF(Table19[[#This Row],[Language]]="English","English","Other language") -> English | T4: =Table19[[#This Row],[Gross Revenue]]-Table19[[#This Row],[Budget]] -> 22176108 | U4: =(Table19[[#This Row],[Gross Revenue]]/Table19[[#This Row],[Budget]])-1 -> 1.3860067 | V4: =IF(J4="","",IF(J4<90,"<90 minutes",IF(J4<=110,"90-110 minutes",IF(J4<=130,"111-130 minutes",IF(J4<=150,"131-150 minutes",">150 minutes"))))) -> 90-110 minutes | W4: =Table19[[#This Row],[Profit]]/Table19[[#This Row],[Budget]]*100 -> 138.60067 | X4: 1637763 | Y4: 0.19178668 | Z4: =IF(L4="","",IF(L4<=$AA$26,"Low",IF(L4<=$AA$28,"Medium","High"))) -> Medium | AA4: Genre | AB4: Median Profit | AC4: Median ROI
A5: 102 Dalmatians | B5: Ioan Gruffudd | C5: Kevin Lima | D5: 2000 | E5: 4182 | F5: 36 | G5: 372 | H5: 4.8 | I5: 84 | J5: 100 | K5: 66941559 | L5: 85000000 | M5: =VLOOKUP(A5,Sheet2!$A$1:G3729,2,0) -> 36715 | N5: =VLOOKUP(A5,Sheet2!$A$1:G3729,3,0) -> Color | O5: =VLOOKUP(A5,Sheet2!$A$1:G3729,4,0) -> Adventure | P5: =VLOOKUP(A5,Sheet2!$A$1:G3729,5,0) -> English | Q5: =VLOOKUP(A5,Sheet2!$A$1:G3729,6,0) -> USA | R5: =VLOOKUP(A5,Sheet2!$A$1:G3729,7,0) -> G | S5: =IF(Table19[[#This Row],[Language]]="English","English","Other language") -> English | T5: =Table19[[#This Row],[Gross Revenue]]-Table19[[#This Row],[Budget]] -> -18058441 | U5: =(Table19[[#This Row],[Gross Revenue]]/Table19[[#This Row],[Budget]])-1 -> -0.21245225 | V5: =IF(J5="","",IF(J5<90,"<90 minutes",IF(J5<=110,"90-110 minutes",IF(J5<=130,"111-130 minutes",IF(J5<=150,"131-150 minutes",">150 minutes"))))) -> 90-110 minutes | W5: =Table19[[#This Row],[Profit]]/Table19[[#This Row],[Budget]]*100 -> -21.245225 | X5: 3892693.5 | Y5: 0.11726929 | Z5: =IF(L5="","",IF(L5<=$AA$26,"Low",IF(L5<=$AA$28,"Medium","High"))) -> High | AA5: horror | AB5: {=MEDIAN(IF(Table19[Genre]=AA5,Table19[Profit]))} -> 16235088 | AC5: {=MEDIAN(IF(Table19[Genre]=AA5,Table19[ROI]))} -> 119.09079
A6: 10th & Wolf | B6: Brian Dennehy | C6: Robert Moresco | D6: 954 | E6: 2512 | F6: 53 | G6: 294 | H6: 6.4 | I6: 26 | J6: 107 | K6: 53481 | L6: 8000000 | M6: =VLOOKUP(A6,Sheet2!$A$1:G3730,2,0) -> 38850 | N6: =VLOOKUP(A6,Sheet2!$A$1:G3730,3,0) -> Color | O6: =VLOOKUP(A6,Sheet2!$A$1:G3730,4,0) -> Crime | P6: =VLOOKUP(A6,Sheet2!$A$1:G3730,5,0) -> English | Q6: =VLOOKUP(A6,Sheet2!$A$1:G3730,6,0) -> USA | R6: =VLOOKUP(A6,Sheet2!$A$1:G3730,7,0) -> R | S6: =IF(Table19[[#This Row],[Language]]="English","English","Other language") -> English | T6: =Table19[[#This Row],[Gross Revenue]]-Table19[[#This Row],[Budget]] -> -7946519 | U6: =(Table19[[#This Row],[Gross Revenue]]/Table19[[#This Row],[Budget]])-1 -> -0.99331488 | V6: =IF(J6="","",IF(J6<90,"<90 minutes",IF(J6<=110,"90-110 minutes",IF(J6<=130,"111-130 minutes",IF(J6<=150,"131-150 minutes",">150 minutes"))))) -> 90-110 minutes | W6: =Table19[[#This Row],[Profit]]/Table19[[#This Row],[Budget]]*100 -> -99.331488 | X6: -74533.5 | Y6: -0.0074856786 | Z6: =IF(L6="","",IF(L6<=$AA$26,"Low",IF(L6<=$AA$28,"Medium","High"))) -> Low | AA6: action | AB6: {=MEDIAN(IF(Table19[Genre]=AA6,Table19[Profit]))} -> -1289919.5 | AC6: {=MEDIAN(IF(Table19[Genre]=AA6,Table19[ROI]))} -> -4.8151418
A7: 12 Rounds | B7: Taylor Cole | C7: Renny Harlin | D7: 969 | E7: 2799 | F7: 212 | G7: 0 | H7: 5.6 | I7: 113 | J7: 108 | K7: 12232937 | L7: 22000000 | M7: =VLOOKUP(A7,Sheet2!$A$1:G3731,2,0) -> 40137 | N7: =VLOOKUP(A7,Sheet2!$A$1:G3731,3,0) -> Color | O7: =VLOOKUP(A7,Sheet2!$A$1:G3731,4,0) -> Action | P7: =VLOOKUP(A7,Sheet2!$A$1:G3731,5,0) -> English | Q7: =VLOOKUP(A7,Sheet2!$A$1:G3731,6,0) -> USA | R7: =VLOOKUP(A7,Sheet2!$A$1:G3731,7,0) -> PG-13 | S7: =IF(Table19[[#This Row],[Language]]="English","English","Other language") -> English | T7: =Table19[[#This Row],[Gross Revenue]]-Table19[[#This Row],[Budget]] -> -9767063 | U7: =(Table19[[#This Row],[Gross Revenue]]/Table19[[#This Row],[Budget]])-1 -> -0.44395741 | V7: =IF(J7="","",IF(J7<90,"<90 minutes",IF(J7<=110,"90-110 minutes",IF(J7<=130,"111-130 minutes",IF(J7<=150,"131-150 minutes",">150 minutes"))))) -> 90-110 minutes | W7: =Table19[[#This Row],[Profit]]/Table19[[#This Row],[Budget]]*100 -> -44.395741 | X7: -1289919.5 | Y7: -0.048151418 | Z7: =IF(L7="","",IF(L7<=$AA$26,"Low",IF(L7<=$AA$28,"Medium","High"))) -> Medium | AA7: adventure | AB7: {=MEDIAN(IF(Table19[Genre]=AA7,Table19[Profit]))} -> 3892693.5 | AC7: {=MEDIAN(IF(Table19[Genre]=AA7,Table19[ROI]))} -> 11.726929
A8: 12 Years a Slave | B8: QuvenzhanÃ© Wallis | C8: Steve McQueen | D8: 2000 | E8: 4251 | F8: 0 | G8: 83000 | H8: 8.1 | I8: 597 | J8: 134 | K8: 56667870 | L8: 20000000 | M8: =VLOOKUP(A8,Sheet2!$A$1:G3732,2,0) -> 41587 | N8: =VLOOKUP(A8,Sheet2!$A$1:G3732,3,0) -> Color | O8: =VLOOKUP(A8,Sheet2!$A$1:G3732,4,0) -> Biography | P8: =VLOOKUP(A8,Sheet2!$A$1:G3732,5,0) -> English | Q8: =VLOOKUP(A8,Sheet2!$A$1:G3732,6,0) -> USA | R8: =VLOOKUP(A8,Sheet2!$A$1:G3732,7,0) -> R | S8: =IF(Table19[[#This Row],[Language]]="English","English","Other language") -> English | T8: =Table19[[#This Row],[Gross Revenue]]-Table19[[#This Row],[Budget]] -> 36667870 | U8: =(Table19[[#This Row],[Gross Revenue]]/Table19[[#This Row],[Budget]])-1 -> 1.8333935 | V8: =IF(J8="","",IF(J8<90,"<90 minutes",IF(J8<=110,"90-110 minutes",IF(J8<=130,"111-130 minutes",IF(J8<=150,"131-150 minutes",">150 minutes"))))) -> 131-150 minutes | W8: =Table19[[#This Row],[Profit]]/Table19[[#This Row],[Budget]]*100 -> 183.33935 | X8: -1289919.5 | Y8: -0.048151418 | Z8: =IF(L8="","",IF(L8<=$AA$26,"Low",IF(L8<=$AA$28,"Medium","High"))) -> Medium | AA8: biography | AB8: {=MEDIAN(IF(Table19[Genre]=AA8,Table19[Profit]))} -> -650566 | AC8: {=MEDIAN(IF(Table19[Genre]=AA8,Table19[ROI]))} -> -6.3233891
A9: 127 Hours | B9: James Franco | C9: Danny Boyle | D9: 11000 | E9: 11984 | F9: 0 | G9: 63000 | H9: 7.6 | I9: 450 | J9: 94 | K9: 18329466 | L9: 18000000 | M9: =VLOOKUP(A9,Sheet2!$A$1:G3733,2,0) -> 40312 | N9: =VLOOKUP(A9,Sheet2!$A$1:G3733,3,0) -> Color | O9: =VLOOKUP(A9,Sheet2!$A$1:G3733,4,0) -> Adventure | P9: =VLOOKUP(A9,Sheet2!$A$1:G3733,5,0) -> English | Q9: =VLOOKUP(A9,Sheet2!$A$1:G3733,6,0) -> USA | R9: =VLOOKUP(A9,Sheet2!$A$1:G3733,7,0) -> R | S9: =IF(Table19[[#This Row],[Language]]="English","English","Other language") -> English | T9: =Table19[[#This Row],[Gross Revenue]]-Table19[[#This Row],[Budget]] -> 329466 | U9: =(Table19[[#This Row],[Gross Revenue]]/Table19[[#This Row],[Budget]])-1 -> 0.018303667 | V9: =IF(J9="","",IF(J9<90,"<90 minutes",IF(J9<=110,"90-110 minutes",IF(J9<=130,"111-130 minutes",IF(J9<=150,"131-150 minutes",">150 minutes"))))) -> 90-110 minutes | W9: =Table19[[#This Row],[Profit]]/Table19[[#This Row],[Budget]]*100 -> 1.8303667 | X9: 3892693.5 | Y9: 0.11726929 | Z9: =IF(L9="","",IF(L9<=$AA$26,"Low",IF(L9<=$AA$28,"Medium","High"))) -> Medium | AA9: drama | AB9: {=MEDIAN(IF(Table19[Genre]=AA9,Table19[Profit]))} -> -434215.5 | AC9: {=MEDIAN(IF(Table19[Genre]=AA9,Table19[ROI]))} -> -10.115101
A10: 13 Going on 30 | B10: Jennifer Garner | C10: Gary Winick | D10: 3000 | E10: 6742 | F10: 56 | G10: 0 | H10: 6.1 | I10: 119 | J10: 98 | K10: 56044241 | L10: 37000000 | M10: =VLOOKUP(A10,Sheet2!$A$1:G3734,2,0) -> 38154 | N10: =VLOOKUP(A10,Sheet2!$A$1:G3734,3,0) -> Color | O10: =VLOOKUP(A10,Sheet2!$A$1:G3734,4,0) -> Comedy | P10: =VLOOKUP(A10,Sheet2!$A$1:G3734,5,0) -> English | Q10: =VLOOKUP(A10,Sheet2!$A$1:G3734,6,0) -> USA | R10: =VLOOKUP(A10,Sheet2!$A$1:G3734,7,0) -> PG-13 | S10: =IF(Table19[[#This Row],[Language]]="English","English","Other language") -> English | T10: =Table19[[#This Row],[Gross Revenue]]-Table19[[#This Row],[Budget]] -> 19044241 | U10: =(Table19[[#This Row],[Gross Revenue]]/Table19[[#This Row],[Budget]])-1 -> 0.51470922 | V10: =IF(J10="","",IF(J10<90,"<90 minutes",IF(J10<=110,"90-110 minutes",IF(J10<=130,"111-130 minutes",IF(J10<=150,"131-150 minutes",">150 minutes"))))) -> 90-110 minutes | W10: =Table19[[#This Row],[Profit]]/Table19[[#This Row],[Budget]]*100 -> 51.470922 | X10: 1637763 | Y10: 0.19178668 | Z10: =IF(L10="","",IF(L10<=$AA$26,"Low",IF(L10<=$AA$28,"Medium","High"))) -> Medium | AA10: comedy | AB10: {=MEDIAN(IF(Table19[Genre]=AA10,Table19[Profit]))} -> 1637763 | AC10: {=MEDIAN(IF(Table19[Genre]=AA10,Table19[ROI]))} -> 19.178668
A11: 1408 | B11: Drew Powell | C11: Mikael HÃ¥fstrÃ¶m | D11: 129 | E11: 214 | F11: 101 | G11: 11000 | H11: 6.8 | I11: 314 | J11: 114 | K11: 71975611 | L11: 25000000 | M11: =VLOOKUP(A11,Sheet2!$A$1:G3735,2,0) -> 39152 | N11: =VLOOKUP(A11,Sheet2!$A$1:G3735,3,0) -> Color | O11: =VLOOKUP(A11,Sheet2!$A$1:G3735,4,0) -> Fantasy | P11: =VLOOKUP(A11,Sheet2!$A$1:G3735,5,0) -> English | Q11: =VLOOKUP(A11,Sheet2!$A$1:G3735,6,0) -> USA | R11: =VLOOKUP(A11,Sheet2!$A$1:G3735,7,0) -> PG-13 | S11: =IF(Table19[[#This Row],[Language]]="English","English","Other language") -> English | T11: =Table19[[#This Row],[Gross Revenue]]-Table19[[#This Row],[Budget]] -> 46975611 | U11: =(Table19[[#This Row],[Gross Revenue]]/Table19[[#This Row],[Budget]])-1 -> 1.8790244 | V11: =IF(J11="","",IF(J11<90,"<90 minutes",IF(J11<=110,"90-110 minutes",IF(J11<=130,"111-130 minutes",IF(J11<=150,"131-150 minutes",">150 minutes"))))) -> 111-130 minutes | W11: =Table19[[#This Row],[Profit]]/Table19[[#This Row],[Budget]]*100 -> 187.90244 | Z11: =IF(L11="","",IF(L11<=$AA$26,"Low",IF(L11<=$AA$28,"Medium","High"))) -> Medium | AA11: crime | AB11: {=MEDIAN(IF(Table19[Genre]=AA11,Table19[Profit]))} -> -74533.5 | AC11: {=MEDIAN(IF(Table19[Genre]=AA11,Table19[ROI]))} -> -0.74856786
A12: 15 Minutes | B12: Robert De Niro | C12: John Herzfeld | D12: 22000 | E12: 33585 | F12: 17 | G12: 748 | H12: 6.1 | I12: 151 | J12: 120 | K12: 24375436 | L12: 42000000 | M12: =VLOOKUP(A12,Sheet2!$A$1:G3736,2,0) -> 36908 | N12: =VLOOKUP(A12,Sheet2!$A$1:G3736,3,0) -> Color | O12: =VLOOKUP(A12,Sheet2!$A$1:G3736,4,0) -> Action | P12: =VLOOKUP(A12,Sheet2!$A$1:G3736,5,0) -> English | Q12: =VLOOKUP(A12,Sheet2!$A$1:G3736,6,0) -> USA | R12: =VLOOKUP(A12,Sheet2!$A$1:G3736,7,0) -> R | S12: =IF(Table19[[#This Row],[Language]]="English","English","Other language") -> English | T12: =Table19[[#This Row],[Gross Revenue]]-Table19[[#This Row],[Budget]] -> -17624564 | U12: =(Table19[[#This Row],[Gross Revenue]]/Table19[[#This Row],[Budget]])-1 -> -0.41963248 | V12: =IF(J12="","",IF(J12<90,"<90 minutes",IF(J12<=110,"90-110 minutes",IF(J12<=130,"111-130 minutes",IF(J12<=150,"131-150 minutes",">150 minutes"))))) -> 111-130 minutes | W12: =Table19[[#This Row],[Profit]]/Table19[[#This Row],[Budget]]*100 -> -41.963248 | X12: -1289919.5 | Y12: -0.048151418 | Z12: =IF(L12="","",IF(L12<=$AA$26,"Low",IF(L12<=$AA$28,"Medium","High"))) -> High
A13: 16 Blocks | B13: Bruce Willis | C13: Richard Donner | D13: 13000 | E13: 15053 | F13: 503 | G13: 0 | H13: 6.6 | I13: 199 | J13: 102 | K13: 36883539 | L13: 52000000 | M13: =VLOOKUP(A13,Sheet2!$A$1:G3737,2,0) -> 39029 | N13: =VLOOKUP(A13,Sheet2!$A$1:G3737,3,0) -> Color | O13: =VLOOKUP(A13,Sheet2!$A$1:G3737,4,0) -> Action | P13: =VLOOKUP(A13,Sheet2!$A$1:G3737,5,0) -> English | Q13: =VLOOKUP(A13,Sheet2!$A$1:G3737,6,0) -> Germany | R13: =VLOOKUP(A13,Sheet2!$A$1:G3737,7,0) -> PG-13 | S13: =IF(Table19[[#This Row],[Language]]="English","English","Other language") -> English | T13: =Table19[[#This Row],[Gross Revenue]]-Table19[[#This Row],[Budget]] -> -15116461 | U13: =(Table19[[#This Row],[Gross Revenue]]/Table19[[#This Row],[Budget]])-1 -> -0.29070117 | V13: =IF(J13="","",IF(J13<90,"<90 minutes",IF(J13<=110,"90-110 minutes",IF(J13<=130,"111-130 minutes",IF(J13<=150,"131-150 minutes",">150 minutes"))))) -> 90-110 minutes | W13: =Table19[[#This Row],[Profit]]/Table19[[#This Row],[Budget]]*100 -> -29.070117 | X13: -1289919.5 | Y13: -0.048151418 | Z13: =IF(L13="","",IF(L13<=$AA$26,"Low",IF(L13<=$AA$28,"Medium","High"))) -> High
A14: 17 Again | B14: Matthew Perry | C14: Burr Steers | D14: 2000 | E14: 7009 | F14: 23 | G14: 0 | H14: 6.4 | I14: 191 | J14: 102 | K14: 64149837 | L14: 20000000 | M14: =VLOOKUP(A14,Sheet2!$A$1:G3738,2,0) -> 39958 | N14: =VLOOKUP(A14,Sheet2!$A$1:G3738,3,0) -> Color | O14: =VLOOKUP(A14,Sheet2!$A$1:G3738,4,0) -> Comedy | P14: =VLOOKUP(A14,Sheet2!$A$1:G3738,5,0) -> English | Q14: =VLOOKUP(A14,Sheet2!$A$1:G3738,6,0) -> USA | R14: =VLOOKUP(A14,Sheet2!$A$1:G3738,7,0) -> PG-13 | S14: =IF(Table19[[#This Row],[Language]]="English","English","Other language") -> English | T14: =Table19[[#This Row],[Gross Revenue]]-Table19[[#This Row],[Budget]] -> 44149837 | U14: =(Table19[[#This Row],[Gross Revenue]]/Table19[[#This Row],[Budget]])-1 -> 2.2074918 | V14: =IF(J14="","",IF(J14<90,"<90 minutes",IF(J14<=110,"90-110 minutes",IF(J14<=130,"111-130 minutes",IF(J14<=150,"131-150 minutes",">150 minutes"))))) -> 90-110 minutes | W14: =Table19[[#This Row],[Profit]]/Table19[[#This Row],[Budget]]*100 -> 220.74918 | X14: 1637763 | Y14: 0.19178668 | Z14: =IF(L14="","",IF(L14<=$AA$26,"Low",IF(L14<=$AA$28,"Medium","High"))) -> Medium
A15: 1911 | B15: Bingbing Li | C15: Li Zhang | D15: 974 | E15: 1887 | F15: 0 | G15: 0 | H15: 6 | I15: 63 | J15: 121 | K15: 127437 | L15: 18000000 | M15: =VLOOKUP(A15,Sheet2!$A$1:G3739,2,0) -> 40858 | N15: =VLOOKUP(A15,Sheet2!$A$1:G3739,3,0) -> Color | O15: =VLOOKUP(A15,Sheet2!$A$1:G3739,4,0) -> Action | P15: =VLOOKUP(A15,Sheet2!$A$1:G3739,5,0) -> Mandarin | Q15: =VLOOKUP(A15,Sheet2!$A$1:G3739,6,0) -> China | R15: =VLOOKUP(A15,Sheet2!$A$1:G3739,7,0) -> R | S15: =IF(Table19[[#This Row],[Language]]="English","English","Other language") -> Other language | T15: =Table19[[#This Row],[Gross Revenue]]-Table19[[#This Row],[Budget]] -> -17872563 | U15: =(Table19[[#This Row],[Gross Revenue]]/Table19[[#This Row],[Budget]])-1 -> -0.99292017 | V15: =IF(J15="","",IF(J15<90,"<90 minutes",IF(J15<=110,"90-110 minutes",IF(J15<=130,"111-130 minutes",IF(J15<=150,"131-150 minutes",">150 minutes"))))) -> 111-130 minutes | W15: =Table19[[#This Row],[Profit]]/Table19[[#This Row],[Budget]]*100 -> -99.292017 | X15: -1289919.5 | Y15: -0.048151418 | Z15: =IF(L15="","",IF(L15<=$AA$26,"Low",IF(L15<=$AA$28,"Medium","High"))) -> Medium | AA15: Genre | AB15: Median Profit | AC15: Median ROI
A16: 2 Fast 2 Furious | B16: Paul Walker | C16: John Singleton | D16: 23000 | E16: 25296 | F16: 309 | G16: 0 | H16: 5.9 | I16: 150 | J16: 107 | K16: 127083765 | L16: 76000000 | M16: =VLOOKUP(A16,Sheet2!$A$1:G3740,2,0) -> 37649 | N16: =VLOOKUP(A16,Sheet2!$A$1:G3740,3,0) -> Color | O16: =VLOOKUP(A16,Sheet2!$A$1:G3740,4,0) -> Action | P16: =VLOOKUP(A16,Sheet2!$A$1:G3740,5,0) -> English | Q16: =VLOOKUP(A16,Sheet2!$A$1:G3740,6,0) -> USA | R16: =VLOOKUP(A16,Sheet2!$A$1:G3740,7,0) -> PG-13 | S16: =IF(Table19[[#This Row],[Language]]="English","English","Other language") -> English | T16: =Table19[[#This Row],[Gross Revenue]]-Table19[[#This Row],[Budget]] -> 51083765 | U16: =(Table19[[#This Row],[Gross Revenue]]/Table19[[#This Row],[Budget]])-1 -> 0.6721548 | V16: =IF(J16="","",IF(J16<90,"<90 minutes",IF(J16<=110,"90-110 minutes",IF(J16<=130,"111-130 minutes",IF(J16<=150,"131-150 minutes",">150 minutes"))))) -> 90-110 minutes | W16: =Table19[[#This Row],[Profit]]/Table19[[#This Row],[Budget]]*100 -> 67.21548 | X16: -1289919.5 | Y16: -0.048151418 | Z16: =IF(L16="","",IF(L16<=$AA$26,"Low",IF(L16<=$AA$28,"Medium","High"))) -> High | AA16: horror | AB16: 16235088 | AC16: 1.1909079
A17: 2 Guns | B17: Denzel Washington | C17: Baltasar KormÃ¡kur | D17: 18000 | E17: 20148 | F17: 175 | G17: 22000 | H17: 6.7 | I17: 265 | J17: 109 | K17: 75573300 | L17: 61000000 | M17: =VLOOKUP(A17,Sheet2!$A$1:G3741,2,0) -> 41615 | N17: =VLOOKUP(A17,Sheet2!$A$1:G3741,3,0) -> Color | O17: =VLOOKUP(A17,Sheet2!$A$1:G3741,4,0) -> Action | P17: =VLOOKUP(A17,Sheet2!$A$1:G3741,5,0) -> English | Q17: =VLOOKUP(A17,Sheet2!$A$1:G3741,6,0) -> USA | R17: =VLOOKUP(A17,Sheet2!$A$1:G3741,7,0) -> R | S17: =IF(Table19[[#This Row],[Language]]="English","English","Other language") -> English | T17: =Table19[[#This Row],[Gross Revenue]]-Table19[[#This Row],[Budget]] -> 14573300 | U17: =(Table19[[#This Row],[Gross Revenue]]/Table19[[#This Row],[Budget]])-1 -> 0.23890656 | V17: =IF(J17="","",IF(J17<90,"<90 minutes",IF(J17<=110,"90-110 minutes",IF(J17<=130,"111-130 minutes",IF(J17<=150,"131-150 minutes",">150 minutes"))))) -> 90-110 minutes | W17: =Table19[[#This Row],[Profit]]/Table19[[#This Row],[Budget]]*100 -> 23.890656 | X17: -1289919.5 | Y17: -0.048151418 | Z17: =IF(L17="","",IF(L17<=$AA$26,"Low",IF(L17<=$AA$28,"Medium","High"))) -> High | AA17: action | AB17: -1289919.5 | AC17: -0.048151418
A18: 20 Dates | B18: Tia Carrere | C18: Myles Berkowitz | D18: 1000 | E18: 1362 | F18: 0 | G18: 30 | H18: 5.3 | I18: 32 | J18: 87 | K18: 536767 | L18: 60000 | M18: =VLOOKUP(A18,Sheet2!$A$1:G3742,2,0) -> 35974 | N18: =VLOOKUP(A18,Sheet2!$A$1:G3742,3,0) -> Color | O18: =VLOOKUP(A18,Sheet2!$A$1:G3742,4,0) -> Biography | P18: =VLOOKUP(A18,Sheet2!$A$1:G3742,5,0) -> English | Q18: =VLOOKUP(A18,Sheet2!$A$1:G3742,6,0) -> USA | R18: =VLOOKUP(A18,Sheet2!$A$1:G3742,7,0) -> R | S18: =IF(Table19[[#This Row],[Language]]="English","English","Other language") -> English | T18: =Table19[[#This Row],[Gross Revenue]]-Table19[[#This Row],[Budget]] -> 476767 | U18: =(Table19[[#This Row],[Gross Revenue]]/Table19[[#This Row],[Budget]])-1 -> 7.9461167 | V18: =IF(J18="","",IF(J18<90,"<90 minutes",IF(J18<=110,"90-110 minutes",IF(J18<=130,"111-130 minutes",IF(J18<=150,"131-150 minutes",">150 minutes"))))) -> <90 minutes | W18: =Table19[[#This Row],[Profit]]/Table19[[#This Row],[Budget]]*100 -> 794.61167 | X18: -1289919.5 | Y18: -0.048151418 | Z18: =IF(L18="","",IF(L18<=$AA$26,"Low",IF(L18<=$AA$28,"Medium","High"))) -> Low | AA18: adventure | AB18: 3892693.5 | AC18: 0.11726929
A19: 20 Feet from Stardom | B19: Sheryl Crow | C19: Morgan Neville | D19: 130 | E19: 198 | F19: 9 | G19: 14000 | H19: 7.4 | I19: 149 | J19: 91 | K19: 4946250 | L19: 1000000 | M19: =VLOOKUP(A19,Sheet2!$A$1:G3743,2,0) -> 41299 | N19: =VLOOKUP(A19,Sheet2!$A$1:G3743,3,0) -> Color | O19: =VLOOKUP(A19,Sheet2!$A$1:G3743,4,0) -> Documentary | P19: =VLOOKUP(A19,Sheet2!$A$1:G3743,5,0) -> English | Q19: =VLOOKUP(A19,Sheet2!$A$1:G3743,6,0) -> USA | R19: =VLOOKUP(A19,Sheet2!$A$1:G3743,7,0) -> PG-13 | S19: =IF(Table19[[#This Row],[Language]]="English","English","Other language") -> English | T19: =Table19[[#This Row],[Gross Revenue]]-Table19[[#This Row],[Budget]] -> 3946250 | U19: =(Table19[[#This Row],[Gross Revenue]]/Table19[[#This Row],[Budget]])-1 -> 3.94625 | V19: =IF(J19="","",IF(J19<90,"<90 minutes",IF(J19<=110,"90-110 minutes",IF(J19<=130,"111-130 minutes",IF(J19<=150,"131-150 minutes",">150 minutes"))))) -> 90-110 minutes | W19: =Table19[[#This Row],[Profit]]/Table19[[#This Row],[Budget]]*100 -> 394.625 | Z19: =IF(L19="","",IF(L19<=$AA$26,"Low",IF(L19<=$AA$28,"Medium","High"))) -> Low | AA19: biography | AB19: -650566 | AC19: -0.063233891
A20: 200 Cigarettes | B20: Janeane Garofalo | C20: Risa Bramon Garcia | D20: 1000 | E20: 2697 | F20: 112 | G20: 0 | H20: 5.9 | I20: 67 | J20: 101 | K20: 6851636 | L20: 6000000 | M20: =VLOOKUP(A20,Sheet2!$A$1:G3744,2,0) -> 36288 | N20: =VLOOKUP(A20,Sheet2!$A$1:G3744,3,0) -> Color | O20: =VLOOKUP(A20,Sheet2!$A$1:G3744,4,0) -> Comedy | P20: =VLOOKUP(A20,Sheet2!$A$1:G3744,5,0) -> English | Q20: =VLOOKUP(A20,Sheet2!$A$1:G3744,6,0) -> USA | R20: =VLOOKUP(A20,Sheet2!$A$1:G3744,7,0) -> R | S20: =IF(Table19[[#This Row],[Language]]="English","English","Other language") -> English | T20: =Table19[[#This Row],[Gross Revenue]]-Table19[[#This Row],[Budget]] -> 851636 | U20: =(Table19[[#This Row],[Gross Revenue]]/Table19[[#This Row],[Budget]])-1 -> 0.14193933 | V20: =IF(J20="","",IF(J20<90,"<90 minutes",IF(J20<=110,"90-110 minutes",IF(J20<=130,"111-130 minutes",IF(J20<=150,"131-150 minutes",">150 minutes"))))) -> 90-110 minutes | W20: =Table19[[#This Row],[Profit]]/Table19[[#This Row],[Budget]]*100 -> 14.193933 | X20: 1637763 | Y20: 0.19178668 | Z20: =IF(L20="","",IF(L20<=$AA$26,"Low",IF(L20<=$AA$28,"Medium","High"))) -> Low | AA20: drama | AB20: -434215.5 | AC20: -0.10115101
A21: 2001: A Space Odyssey | B21: Keir Dullea | C21: Stanley Kubrick | D21: 273 | E21: 727 | F21: 0 | G21: 24000 | H21: 8.3 | I21: 285 | J21: 161 | K21: 56715371 | L21: 12000000 | M21: =VLOOKUP(A21,Sheet2!$A$1:G3745,2,0) -> 25031 | N21: =VLOOKUP(A21,Sheet2!$A$1:G3745,3,0) -> Color | O21: =VLOOKUP(A21,Sheet2!$A$1:G3745,4,0) -> Adventure | P21: =VLOOKUP(A21,Sheet2!$A$1:G3745,5,0) -> English | Q21: =VLOOKUP(A21,Sheet2!$A$1:G3745,6,0) -> UK | R21: =VLOOKUP(A21,Sheet2!$A$1:G3745,7,0) -> G | S21: =IF(Table19[[#This Row],[Language]]="English","English","Other language") -> English | T21: =Table19[[#This Row],[Gross Revenue]]-Table19[[#This Row],[Budget]] -> 44715371 | U21: =(Table19[[#This Row],[Gross Revenue]]/Table19[[#This Row],[Budget]])-1 -> 3.7262809 | V21: =IF(J21="","",IF(J21<90,"<90 minutes",IF(J21<=110,"90-110 minutes",IF(J21<=130,"111-130 minutes",IF(J21<=150,"131-150 minutes",">150 minutes"))))) -> >150 minutes | W21: =Table19[[#This Row],[Profit]]/Table19[[#This Row],[Budget]]*100 -> 372.62809 | X21: 3892693.5 | Y21: 0.11726929 | Z21: =IF(L21="","",IF(L21<=$AA$26,"Low",IF(L21<=$AA$28,"Medium","High"))) -> Low | AA21: comedy | AB21: 1637763 | AC21: 0.19178668
A22: 2012 | B22: Oliver Platt | C22: Roland Emmerich | D22: 1000 | E22: 2144 | F22: 776 | G22: 13000 | H22: 5.8 | I22: 367 | J22: 158 | K22: 166112167 | L22: 200000000 | M22: =VLOOKUP(A22,Sheet2!$A$1:G3746,2,0) -> 39865 | N22: =VLOOKUP(A22,Sheet2!$A$1:G3746,3,0) -> Color | O22: =VLOOKUP(A22,Sheet2!$A$1:G3746,4,0) -> Action | P22: =VLOOKUP(A22,Sheet2!$A$1:G3746,5,0) -> English | Q22: =VLOOKUP(A22,Sheet2!$A$1:G3746,6,0) -> USA | R22: =VLOOKUP(A22,Sheet2!$A$1:G3746,7,0) -> PG-13 | S22: =IF(Table19[[#This Row],[Language]]="English","English","Other language") -> English | T22: =Table19[[#This Row],[Gross Revenue]]-Table19[[#This Row],[Budget]] -> -33887833 | U22: =(Table19[[#This Row],[Gross Revenue]]/Table19[[#This Row],[Budget]])-1 -> -0.16943917 | V22: =IF(J22="","",IF(J22<90,"<90 minutes",IF(J22<=110,"90-110 minutes",IF(J22<=130,"111-130 minutes",IF(J22<=150,"131-150 minutes",">150 minutes"))))) -> >150 minutes | W22: =Table19[[#This Row],[Profit]]/Table19[[#This Row],[Budget]]*100 -> -16.943917 | X22: -1289919.5 | Y22: -0.048151418 | Z22: =IF(L22="","",IF(L22<=$AA$26,"Low",IF(L22<=$AA$28,"Medium","High"))) -> High | AA22: crime | AB22: -74533.5 | AC22: -0.0074856786
A23: 2016: Obama's America | B23: Barack Obama | C23: Dinesh D'Souza | D23: 871 | E23: 1111 | F23: 67 | G23: 0 | H23: 5.1 | I23: 30 | J23: 87 | K23: 33349949 | L23: 2500000 | M23: =VLOOKUP(A23,Sheet2!$A$1:G3747,2,0) -> 41014 | N23: =VLOOKUP(A23,Sheet2!$A$1:G3747,3,0) -> Color | O23: =VLOOKUP(A23,Sheet2!$A$1:G3747,4,0) -> Documentary | P23: =VLOOKUP(A23,Sheet2!$A$1:G3747,5,0) -> English | Q23: =VLOOKUP(A23,Sheet2!$A$1:G3747,6,0) -> USA | R23: =VLOOKUP(A23,Sheet2!$A$1:G3747,7,0) -> PG | S23: =IF(Table19[[#This Row],[Language]]="English","English","Other language") -> English | T23: =Table19[[#This Row],[Gross Revenue]]-Table19[[#This Row],[Budget]] -> 30849949 | U23: =(Table19[[#This Row],[Gross Revenue]]/Table19[[#This Row],[Budget]])-1 -> 12.33998 | V23: =IF(J23="","",IF(J23<90,"<90 minutes",IF(J23<=110,"90-110 minutes",IF(J23<=130,"111-130 minutes",IF(J23<=150,"131-150 minutes",">150 minutes"))))) -> <90 minutes | W23: =Table19[[#This Row],[Profit]]/Table19[[#This Row],[Budget]]*100 -> 1233.998 | Z23: =IF(L23="","",IF(L23<=$AA$26,"Low",IF(L23<=$AA$28,"Medium","High"))) -> Low
A24: 2046 | B24: Li Gong | C24: Kar-Wai Wong | D24: 878 | E24: 2378 | F24: 0 | G24: 0 | H24: 7.5 | I24: 194 | J24: 129 | K24: 261481 | L24: 12000000 | M24: =VLOOKUP(A24,Sheet2!$A$1:G3748,2,0) -> 38325 | N24: =VLOOKUP(A24,Sheet2!$A$1:G3748,3,0) -> Black and White | O24: =VLOOKUP(A24,Sheet2!$A$1:G3748,4,0) -> Drama | P24: =VLOOKUP(A24,Sheet2!$A$1:G3748,5,0) -> Cantonese | Q24: =VLOOKUP(A24,Sheet2!$A$1:G3748,6,0) -> Hong Kong | R24: =VLOOKUP(A24,Sheet2!$A$1:G3748,7,0) -> R | S24: =IF(Table19[[#This Row],[Language]]="English","English","Other language") -> Other language | T24: =Table19[[#This Row],[Gross Revenue]]-Table19[[#This Row],[Budget]] -> -11738519 | U24: =(Table19[[#This Row],[Gross Revenue]]/Table19[[#This Row],[Budget]])-1 -> -0.97820992 | V24: =IF(J24="","",IF(J24<90,"<90 minutes",IF(J24<=110,"90-110 minutes",IF(J24<=130,"111-130 minutes",IF(J24<=150,"131-150 minutes",">150 minutes"))))) -> 111-130 minutes | W24: =Table19[[#This Row],[Profit]]/Table19[[#This Row],[Budget]]*100 -> -97.820992 | X24: -434215.5 | Y24: -0.10115101 | Z24: =IF(L24="","",IF(L24<=$AA$26,"Low",IF(L24<=$AA$28,"Medium","High"))) -> Low
A25: 21 | B25: Kevin Spacey | C25: Robert Luketic | D25: 18000 | E25: 25661 | F25: 126 | G25: 0 | H25: 6.8 | I25: 144 | J25: 123 | K25: 81159365 | L25: 35000000 | M25: =VLOOKUP(A25,Sheet2!$A$1:G3749,2,0) -> 39703 | N25: =VLOOKUP(A25,Sheet2!$A$1:G3749,3,0) -> Color | O25: =VLOOKUP(A25,Sheet2!$A$1:G3749,4,0) -> Crime | P25: =VLOOKUP(A25,Sheet2!$A$1:G3749,5,0) -> English | Q25: =VLOOKUP(A25,Sheet2!$A$1:G3749,6,0) -> USA | R25: =VLOOKUP(A25,Sheet2!$A$1:G3749,7,0) -> PG-13 | S25: =IF(Table19[[#This Row],[Language]]="English","English","Other language") -> English | T25: =Table19[[#This Row],[Gross Revenue]]-Table19[[#This Row],[Budget]] -> 46159365 | U25: =(Table19[[#This Row],[Gross Revenue]]/Table19[[#This Row],[Budget]])-1 -> 1.318839 | V25: =IF(J25="","",IF(J25<90,"<90 minutes",IF(J25<=110,"90-110 minutes",IF(J25<=130,"111-130 minutes",IF(J25<=150,"131-150 minutes",">150 minutes"))))) -> 111-130 minutes | W25: =Table19[[#This Row],[Profit]]/Table19[[#This Row],[Budget]]*100 -> 131.8839 | X25: -74533.5 | Y25: -0.0074856786 | Z25: =IF(L25="","",IF(L25<=$AA$26,"Low",IF(L25<=$AA$28,"Medium","High"))) -> Medium
A26: 21 & Over | B26: Justin Chon | C26: Jon Lucas | D26: 552 | E26: 2730 | F26: 24 | G26: 11000 | H26: 5.9 | I26: 168 | J26: 93 | K26: 25675765 | L26: 13000000 | M26: =VLOOKUP(A26,Sheet2!$A$1:G3750,2,0) -> 41390 | N26: =VLOOKUP(A26,Sheet2!$A$1:G3750,3,0) -> Color | O26: =VLOOKUP(A26,Sheet2!$A$1:G3750,4,0) -> Comedy | P26: =VLOOKUP(A26,Sheet2!$A$1:G3750,5,0) -> English | Q26: =VLOOKUP(A26,Sheet2!$A$1:G3750,6,0) -> USA | R26: =VLOOKUP(A26,Sheet2!$A$1:G3750,7,0) -> R | S26: =IF(Table19[[#This Row],[Language]]="English","English","Other language") -> English | T26: =Table19[[#This Row],[Gross Revenue]]-Table19[[#This Row],[Budget]] -> 12675765 | U26: =(Table19[[#This Row],[Gross Revenue]]/Table19[[#This Row],[Budget]])-1 -> 0.97505885 | V26: =IF(J26="","",IF(J26<90,"<90 minutes",IF(J26<=110,"90-110 minutes",IF(J26<=130,"111-130 minutes",IF(J26<=150,"131-150 minutes",">150 minutes"))))) -> 90-110 minutes | W26: =Table19[[#This Row],[Profit]]/Table19[[#This Row],[Budget]]*100 -> 97.505885 | X26: 1637763 | Y26: 0.19178668 | Z26: =IF(L26="","",IF(L26<=$AA$26,"Low",IF(L26<=$AA$28,"Medium","High"))) -> Low | AA26: =_xlfn.PERCENTILE.INC($L:$L,1/3) -> 13000000
A27: 21 Grams | B27: Naomi Watts | C27: Alejandro G. IÃ±Ã¡rritu | D27: 6000 | E27: 7567 | F27: 0 | G27: 0 | H27: 7.7 | I27: 192 | J27: 124 | K27: 16248701 | L27: 20000000 | M27: =VLOOKUP(A27,Sheet2!$A$1:G3751,2,0) -> 37788 | N27: =VLOOKUP(A27,Sheet2!$A$1:G3751,3,0) -> Color | O27: =VLOOKUP(A27,Sheet2!$A$1:G3751,4,0) -> Drama | P27: =VLOOKUP(A27,Sheet2!$A$1:G3751,5,0) -> English | Q27: =VLOOKUP(A27,Sheet2!$A$1:G3751,6,0) -> USA | R27: =VLOOKUP(A27,Sheet2!$A$1:G3751,7,0) -> R | S27: =IF(Table19[[#This Row],[Language]]="English","English","Other language") -> English | T27: =Table19[[#This Row],[Gross Revenue]]-Table19[[#This Row],[Budget]] -> -3751299 | U27: =(Table19[[#This Row],[Gross Revenue]]/Table19[[#This Row],[Budget]])-1 -> -0.18756495 | V27: =IF(J27="","",IF(J27<90,"<90 minutes",IF(J27<=110,"90-110 minutes",IF(J27<=130,"111-130 minutes",IF(J27<=150,"131-150 minutes",">150 minutes"))))) -> 111-130 minutes | W27: =Table19[[#This Row],[Profit]]/Table19[[#This Row],[Budget]]*100 -> -18.756495 | X27: -434215.5 | Y27: -0.10115101 | Z27: =IF(L27="","",IF(L27<=$AA$26,"Low",IF(L27<=$AA$28,"Medium","High"))) -> Medium
A28: 21 Jump Street | B28: Channing Tatum | C28: Phil Lord | D28: 17000 | E28: 19968 | F28: 97 | G28: 39000 | H28: 7.2 | I28: 375 | J28: 109 | K28: 138447667 | L28: 42000000 | M28: =VLOOKUP(A28,Sheet2!$A$1:G3752,2,0) -> 41218 | N28: =VLOOKUP(A28,Sheet2!$A$1:G3752,3,0) -> Color | O28: =VLOOKUP(A28,Sheet2!$A$1:G3752,4,0) -> Action | P28: =VLOOKUP(A28,Sheet2!$A$1:G3752,5,0) -> English | Q28: =VLOOKUP(A28,Sheet2!$A$1:G3752,6,0) -> USA | R28: =VLOOKUP(A28,Sheet2!$A$1:G3752,7,0) -> R | S28: =IF(Table19[[#This Row],[Language]]="English","English","Other language") -> English | T28: =Table19[[#This Row],[Gross Revenue]]-Table19[[#This Row],[Budget]] -> 96447667 | U28: =(Table19[[#This Row],[Gross Revenue]]/Table19[[#This Row],[Budget]])-1 -> 2.296373 | V28: =IF(J28="","",IF(J28<90,"<90 minutes",IF(J28<=110,"90-110 minutes",IF(J28<=130,"111-130 minutes",IF(J28<=150,"131-150 minutes",">150 minutes"))))) -> 90-110 minutes | W28: =Table19[[#This Row],[Profit]]/Table19[[#This Row],[Budget]]*100 -> 229.6373 | X28: -1289919.5 | Y28: -0.048151418 | Z28: =IF(L28="","",IF(L28<=$AA$26,"Low",IF(L28<=$AA$28,"Medium","High"))) -> High | AA28: =_xlfn.PERCENTILE.INC($L:$L,2/3) -> 38000000
A29: 22 Jump Street | B29: Channing Tatum | C29: Phil Lord | D29: 17000 | E29: 19428 | F29: 97 | G29: 24000 | H29: 7.1 | I29: 330 | J29: 112 | K29: 191616238 | L29: 50000000 | M29: =VLOOKUP(A29,Sheet2!$A$1:G3753,2,0) -> 41962 | N29: =VLOOKUP(A29,Sheet2!$A$1:G3753,3,0) -> Color | O29: =VLOOKUP(A29,Sheet2!$A$1:G3753,4,0) -> Action | P29: =VLOOKUP(A29,Sheet2!$A$1:G3753,5,0) -> English | Q29: =VLOOKUP(A29,Sheet2!$A$1:G3753,6,0) -> USA | R29: =VLOOKUP(A29,Sheet2!$A$1:G3753,7,0) -> R | S29: =IF(Table19[[#This Row],[Language]]="English","English","Other language") -> English | T29: =Table19[[#This Row],[Gross Revenue]]-Table19[[#This Row],[Budget]] -> 141616238 | U29: =(Table19[[#This Row],[Gross Revenue]]/Table19[[#This Row],[Budget]])-1 -> 2.8323248 | V29: =IF(J29="","",IF(J29<90,"<90 minutes",IF(J29<=110,"90-110 minutes",IF(J29<=130,"111-130 minutes",IF(J29<=150,"131-150 minutes",">150 minutes"))))) -> 111-130 minutes | W29: =Table19[[#This Row],[Profit]]/Table19[[#This Row],[Budget]]*100 -> 283.23248 | X29: -1289919.5 | Y29: -0.048151418 | Z29: =IF(L29="","",IF(L29<=$AA$26,"Low",IF(L29<=$AA$28,"Medium","High"))) -> High
A30: 25th Hour | B30: Philip Seymour Hoffman | C30: Spike Lee | D30: 22000 | E30: 26050 | F30: 0 | G30: 0 | H30: 7.7 | I30: 202 | J30: 108 | K30: 13060843 | L30: 15000000 | M30: =VLOOKUP(A30,Sheet2!$A$1:G3754,2,0) -> 37455 | N30: =VLOOKUP(A30,Sheet2!$A$1:G3754,3,0) -> Color | O30: =VLOOKUP(A30,Sheet2!$A$1:G3754,4,0) -> Drama | P30: =VLOOKUP(A30,Sheet2!$A$1:G3754,5,0) -> English | Q30: =VLOOKUP(A30,Sheet2!$A$1:G3754,6,0) -> USA | R30: =VLOOKUP(A30,Sheet2!$A$1:G3754,7,0) -> R | S30: =IF(Table19[[#This Row],[Language]]="English","English","Other language") -> English | T30: =Table19[[#This Row],[Gross Revenue]]-Table19[[#This Row],[Budget]] -> -1939157 | U30: =(Table19[[#This Row],[Gross Revenue]]/Table19[[#This Row],[Budget]])-1 -> -0.12927713 | V30: =IF(J30="","",IF(J30<90,"<90 minutes",IF(J30<=110,"90-110 minutes",IF(J30<=130,"111-130 minutes",IF(J30<=150,"131-150 minutes",">150 minutes"))))) -> 90-110 minutes | W30: =Table19[[#This Row],[Profit]]/Table19[[#This Row],[Budget]]*100 -> -12.927713 | X30: -434215.5 | Y30: -0.10115101 | Z30: =IF(L30="","",IF(L30<=$AA$26,"Low",IF(L30<=$AA$28,"Medium","High"))) -> Medium | AA30: Corr actor,ROI | AB30: Corr director,ROI
A31: 27 Dresses | B31: Judy Greer | C31: Anne Fletcher | D31: 2000 | E31: 2978 | F31: 98 | G31: 0 | H31: 6.1 | I31: 175 | J31: 111 | K31: 76806312 | L31: 30000000 | M31: =VLOOKUP(A31,Sheet2!$A$1:G3755,2,0) -> 39784 | N31: =VLOOKUP(A31,Sheet2!$A$1:G3755,3,0) -> Color | O31: =VLOOKUP(A31,Sheet2!$A$1:G3755,4,0) -> Comedy | P31: =VLOOKUP(A31,Sheet2!$A$1:G3755,5,0) -> English | Q31: =VLOOKUP(A31,Sheet2!$A$1:G3755,6,0) -> USA | R31: =VLOOKUP(A31,Sheet2!$A$1:G3755,7,0) -> PG-13 | S31: =IF(Table19[[#This Row],[Language]]="English","English","Other language") -> English | T31: =Table19[[#This Row],[Gross Revenue]]-Table19[[#This Row],[Budget]] -> 46806312 | U31: =(Table19[[#This Row],[Gross Revenue]]/Table19[[#This Row],[Budget]])-1 -> 1.5602104 | V31: =IF(J31="","",IF(J31<90,"<90 minutes",IF(J31<=110,"90-110 minutes",IF(J31<=130,"111-130 minutes",IF(J31<=150,"131-150 minutes",">150 minutes"))))) -> 111-130 minutes | W31: =Table19[[#This Row],[Profit]]/Table19[[#This Row],[Budget]]*100 -> 156.02104 | X31: 1637763 | Y31: 0.19178668 | Z31: =IF(L31="","",IF(L31<=$AA$26,"Low",IF(L31<=$AA$28,"Medium","High"))) -> Medium | AA31: =CORREL(D:D,W:W) -> -0.014989918 | AB31: =CORREL(F:F,W:W) -> -0.0061883667
A32: 28 Days | B32: Steve Buscemi | C32: Betty Thomas | D32: 12000 | E32: 23864 | F32: 84 | G32: 0 | H32: 6 | I32: 116 | J32: 103 | K32: 37035515 | L32: 43000000 | M32: =VLOOKUP(A32,Sheet2!$A$1:G3756,2,0) -> 36730 | N32: =VLOOKUP(A32,Sheet2!$A$1:G3756,3,0) -> Color | O32: =VLOOKUP(A32,Sheet2!$A$1:G3756,4,0) -> Comedy | P32: =VLOOKUP(A32,Sheet2!$A$1:G3756,5,0) -> English | Q32: =VLOOKUP(A32,Sheet2!$A$1:G3756,6,0) -> USA | R32: =VLOOKUP(A32,Sheet2!$A$1:G3756,7,0) -> PG-13 | S32: =IF(Table19[[#This Row],[Language]]="English","English","Other language") -> English | T32: =Table19[[#This Row],[Gross Revenue]]-Table19[[#This Row],[Budget]] -> -5964485 | U32: =(Table19[[#This Row],[Gross Revenue]]/Table19[[#This Row],[Budget]])-1 -> -0.13870895 | V32: =IF(J32="","",IF(J32<90,"<90 minutes",IF(J32<=110,"90-110 minutes",IF(J32<=130,"111-130 minutes",IF(J32<=150,"131-150 minutes",">150 minutes"))))) -> 90-110 minutes | W32: =Table19[[#This Row],[Profit]]/Table19[[#This Row],[Budget]]*100 -> -13.870895 | X32: 1637763 | Y32: 0.19178668 | Z32: =IF(L32="","",IF(L32<=$AA$26,"Low",IF(L32<=$AA$28,"Medium","High"))) -> High
A33: 28 Days Later... | B33: Noah Huntley | C33: Danny Boyle | D33: 133 | E33: 241 | F33: 0 | G33: 11000 | H33: 7.6 | I33: 224 | J33: 113 | K33: 45063889 | L33: 8000000 | M33: =VLOOKUP(A33,Sheet2!$A$1:G3757,2,0) -> 37326 | N33: =VLOOKUP(A33,Sheet2!$A$1:G3757,3,0) -> Color | O33: =VLOOKUP(A33,Sheet2!$A$1:G3757,4,0) -> Drama | P33: =VLOOKUP(A33,Sheet2!$A$1:G3757,5,0) -> English | Q33: =VLOOKUP(A33,Sheet2!$A$1:G3757,6,0) -> UK | R33: =VLOOKUP(A33,Sheet2!$A$1:G3757,7,0) -> R | S33: =IF(Table19[[#This Row],[Language]]="English","English","Other language") -> English | T33: =Table19[[#This Row],[Gross Revenue]]-Table19[[#This Row],[Budget]] -> 37063889 | U33: =(Table19[[#This Row],[Gross Revenue]]/Table19[[#This Row],[Budget]])-1 -> 4.6329861 | V33: =IF(J33="","",IF(J33<90,"<90 minutes",IF(J33<=110,"90-110 minutes",IF(J33<=130,"111-130 minutes",IF(J33<=150,"131-150 minutes",">150 minutes"))))) -> 111-130 minutes | W33: =Table19[[#This Row],[Profit]]/Table19[[#This Row],[Budget]]*100 -> 463.29861 | X33: -434215.5 | Y33: -0.10115101 | Z33: =IF(L33="","",IF(L33<=$AA$26,"Low",IF(L33<=$AA$28,"Medium","High"))) -> Low | AA33: =CORREL(H:H,W:W) -> 0.0087393311
A34: 28 Weeks Later | B34: Jeremy Renner | C34: Juan Carlos Fresnadillo | D34: 10000 | E34: 11471 | F34: 35 | G34: 0 | H34: 7 | I34: 274 | J34: 100 | K34: 28637507 | L34: 15000000 | M34: =VLOOKUP(A34,Sheet2!$A$1:G3758,2,0) -> 39356 | N34: =VLOOKUP(A34,Sheet2!$A$1:G3758,3,0) -> Color | O34: =VLOOKUP(A34,Sheet2!$A$1:G3758,4,0) -> Drama | P34: =VLOOKUP(A34,Sheet2!$A$1:G3758,5,0) -> English | Q34: =VLOOKUP(A34,Sheet2!$A$1:G3758,6,0) -> UK | R34: =VLOOKUP(A34,Sheet2!$A$1:G3758,7,0) -> R | S34: =IF(Table19[[#This Row],[Language]]="English","English","Other language") -> English | T34: =Table19[[#This Row],[Gross Revenue]]-Table19[[#This Row],[Budget]] -> 13637507 | U34: =(Table19[[#This Row],[Gross Revenue]]/Table19[[#This Row],[Budget]])-1 -> 0.90916713 | V34: =IF(J34="","",IF(J34<90,"<90 minutes",IF(J34<=110,"90-110 minutes",IF(J34<=130,"111-130 minutes",IF(J34<=150,"131-150 minutes",">150 minutes"))))) -> 90-110 minutes | W34: =Table19[[#This Row],[Profit]]/Table19[[#This Row],[Budget]]*100 -> 90.916713 | X34: -434215.5 | Y34: -0.10115101 | Z34: =IF(L34="","",IF(L34<=$AA$26,"Low",IF(L34<=$AA$28,"Medium","High"))) -> Medium | AA34: =CORREL(H:H,Y:Y) -> -0.20106434
A35: 3 Days to Kill | B35: Connie Nielsen | C35: McG | D35: 933 | E35: 1286 | F35: 368 | G35: 10000 | H35: 6.2 | I35: 211 | J35: 123 | K35: 30688364 | L35: 28000000 | M35: =VLOOKUP(A35,Sheet2!$A$1:G3759,2,0) -> 41815 | N35: =VLOOKUP(A35,Sheet2!$A$1:G3759,3,0) -> Color | O35: =VLOOKUP(A35,Sheet2!$A$1:G3759,4,0) -> Action | P35: =VLOOKUP(A35,Sheet2!$A$1:G3759,5,0) -> English | Q35: =VLOOKUP(A35,Sheet2!$A$1:G3759,6,0) -> USA | R35: =VLOOKUP(A35,Sheet2!$A$1:G3759,7,0) -> PG-13 | S35: =IF(Table19[[#This Row],[Language]]="English","English","Other language") -> English | T35: =Table19[[#This Row],[Gross Revenue]]-Table19[[#This Row],[Budget]] -> 2688364 | U35: =(Table19[[#This Row],[Gross Revenue]]/Table19[[#This Row],[Budget]])-1 -> 0.096013 | V35: =IF(J35="","",IF(J35<90,"<90 minutes",IF(J35<=110,"90-110 minutes",IF(J35<=130,"111-130 minutes",IF(J35<=150,"131-150 minutes",">150 minutes"))))) -> 111-130 minutes | W35: =Table19[[#This Row],[Profit]]/Table19[[#This Row],[Budget]]*100 -> 9.6013 | X35: -1289919.5 | Y35: -0.048151418 | Z35: =IF(L35="","",IF(L35<=$AA$26,"Low",IF(L35<=$AA$28,"Medium","High"))) -> Medium | AA35: =CORREL(I:I,W:W) -> 0.033760264
A36: 3 Men and a Baby | B36: Tom Selleck | C36: Leonard Nimoy | D36: 19000 | E36: 21499 | F36: 12000 | G36: 3000 | H36: 5.9 | I36: 21 | J36: 102 | K36: 167780960 | L36: 11000000 | M36: =VLOOKUP(A36,Sheet2!$A$1:G3760,2,0) -> 31968 | N36: =VLOOKUP(A36,Sheet2!$A$1:G3760,3,0) -> Color | O36: =VLOOKUP(A36,Sheet2!$A$1:G3760,4,0) -> Comedy | P36: =VLOOKUP(A36,Sheet2!$A$1:G3760,5,0) -> English | Q36: =VLOOKUP(A36,Sheet2!$A$1:G3760,6,0) -> USA | R36: =VLOOKUP(A36,Sheet2!$A$1:G3760,7,0) -> PG | S36: =IF(Table19[[#This Row],[Language]]="English","English","Other language") -> English | T36: =Table19[[#This Row],[Gross Revenue]]-Table19[[#This Row],[Budget]] -> 156780960 | U36: =(Table19[[#This Row],[Gross Revenue]]/Table19[[#This Row],[Budget]])-1 -> 14.252815 | V36: =IF(J36="","",IF(J36<90,"<90 minutes",IF(J36<=110,"90-110 minutes",IF(J36<=130,"111-130 minutes",IF(J36<=150,"131-150 minutes",">150 minutes"))))) -> 90-110 minutes | W36: =Table19[[#This Row],[Profit]]/Table19[[#This Row],[Budget]]*100 -> 1425.2815 | X36: 1637763 | Y36: 0.19178668 | Z36: =IF(L36="","",IF(L36<=$AA$26,"Low",IF(L36<=$AA$28,"Medium","High"))) -> Low | AA36: =CORREL(G:G,W:W) -> -0.0018301621
A37: 3 Ninjas Kick Back | B37: Victor Wong | C37: Charles T. Kanganis | D37: 400 | E37: 1151 | F37: 18 | G37: 444 | H37: 4.3 | I37: 5 | J37: 93 | K37: 11784000 | L37: 20000000 | M37: =VLOOKUP(A37,Sheet2!$A$1:G3761,2,0) -> 34641 | N37: =VLOOKUP(A37,Sheet2!$A$1:G3761,3,0) -> Color | O37: =VLOOKUP(A37,Sheet2!$A$1:G3761,4,0) -> Action | P37: =VLOOKUP(A37,Sheet2!$A$1:G3761,5,0) -> English | Q37: =VLOOKUP(A37,Sheet2!$A$1:G3761,6,0) -> USA | R37: =VLOOKUP(A37,Sheet2!$A$1:G3761,7,0) -> PG | S37: =IF(Table19[[#This Row],[Language]]="English","English","Other language") -> English | T37: =Table19[[#This Row],[Gross Revenue]]-Table19[[#This Row],[Budget]] -> -8216000 | U37: =(Table19[[#This Row],[Gross Revenue]]/Table19[[#This Row],[Budget]])-1 -> -0.4108 | V37: =IF(J37="","",IF(J37<90,"<90 minutes",IF(J37<=110,"90-110 minutes",IF(J37<=130,"111-130 minutes",IF(J37<=150,"131-150 minutes",">150 minutes"))))) -> 90-110 minutes | W37: =Table19[[#This Row],[Profit]]/Table19[[#This Row],[Budget]]*100 -> -41.08 | X37: -1289919.5 | Y37: -0.048151418 | Z37: =IF(L37="","",IF(L37<=$AA$26,"Low",IF(L37<=$AA$28,"Medium","High"))) -> Medium
A38: 3 Strikes | B38: Mo'Nique | C38: DJ Pooh | D38: 939 | E38: 3354 | F38: 69 | G38: 118 | H38: 4 | I38: 22 | J38: 82 | K38: 9821335 | L38: 6000000 | M38: =VLOOKUP(A38,Sheet2!$A$1:G3762,2,0) -> 36835 | N38: =VLOOKUP(A38,Sheet2!$A$1:G3762,3,0) -> Color | O38: =VLOOKUP(A38,Sheet2!$A$1:G3762,4,0) -> Comedy | P38: =VLOOKUP(A38,Sheet2!$A$1:G3762,5,0) -> English | Q38: =VLOOKUP(A38,Sheet2!$A$1:G3762,6,0) -> USA | R38: =VLOOKUP(A38,Sheet2!$A$1:G3762,7,0) -> R | S38: =IF(Table19[[#This Row],[Language]]="English","English","Other language") -> English | T38: =Table19[[#This Row],[Gross Revenue]]-Table19[[#This Row],[Budget]] -> 3821335 | U38: =(Table19[[#This Row],[Gross Revenue]]/Table19[[#This Row],[Budget]])-1 -> 0.63688917 | V38: =IF(J38="","",IF(J38<90,"<90 minutes",IF(J38<=110,"90-110 minutes",IF(J38<=130,"111-130 minutes",IF(J38<=150,"131-150 minutes",">150 minutes"))))) -> <90 minutes | W38: =Table19[[#This Row],[Profit]]/Table19[[#This Row],[Budget]]*100 -> 63.688917 | X38: 1637763 | Y38: 0.19178668 | Z38: =IF(L38="","",IF(L38<=$AA$26,"Low",IF(L38<=$AA$28,"Medium","High"))) -> Low
A39: 3:10 to Yuma | B39: Christian Bale | C39: James Mangold | D39: 23000 | E39: 33548 | F39: 446 | G39: 0 | H39: 7.8 | I39: 295 | J39: 122 | K39: 53574088 | L39: 55000000 | M39: =VLOOKUP(A39,Sheet2!$A$1:G3763,2,0) -> 39112 | N39: =VLOOKUP(A39,Sheet2!$A$1:G3763,3,0) -> Color | O39: =VLOOKUP(A39,Sheet2!$A$1:G3763,4,0) -> Adventure | P39: =VLOOKUP(A39,Sheet2!$A$1:G3763,5,0) -> English | Q39: =VLOOKUP(A39,Sheet2!$A$1:G3763,6,0) -> USA | R39: =VLOOKUP(A39,Sheet2!$A$1:G3763,7,0) -> R | S39: =IF(Table19[[#This Row],[Language]]="English","English","Other language") -> English | T39: =Table19[[#This Row],[Gross Revenue]]-Table19[[#This Row],[Budget]] -> -1425912 | U39: =(Table19[[#This Row],[Gross Revenue]]/Table19[[#This Row],[Budget]])-1 -> -0.025925673 | V39: =IF(J39="","",IF(J39<90,"<90 minutes",IF(J39<=110,"90-110 minutes",IF(J39<=130,"111-130 minutes",IF(J39<=150,"131-150 minutes",">150 minutes"))))) -> 111-130 minutes | W39: =Table19[[#This Row],[Profit]]/Table19[[#This Row],[Budget]]*100 -> -2.5925673 | X39: 3892693.5 | Y39: 0.11726929 | Z39: =IF(L39="","",IF(L39<=$AA$26,"Low",IF(L39<=$AA$28,"Medium","High"))) -> High
A40: 30 Days of Night | B40: Danny Huston | C40: David Slade | D40: 430 | E40: 814 | F40: 171 | G40: 0 | H40: 6.6 | I40: 304 | J40: 113 | K40: 39568996 | L40: 32000000 | M40: =VLOOKUP(A40,Sheet2!$A$1:G3764,2,0) -> 39392 | N40: =VLOOKUP(A40,Sheet2!$A$1:G3764,3,0) -> Color | O40: =VLOOKUP(A40,Sheet2!$A$1:G3764,4,0) -> Horror | P40: =VLOOKUP(A40,Sheet2!$A$1:G3764,5,0) -> English | Q40: =VLOOKUP(A40,Sheet2!$A$1:G3764,6,0) -> USA | R40: =VLOOKUP(A40,Sheet2!$A$1:G3764,7,0) -> R | S40: =IF(Table19[[#This Row],[Language]]="English","English","Other language") -> English | T40: =Table19[[#This Row],[Gross Revenue]]-Table19[[#This Row],[Budget]] -> 7568996 | U40: =(Table19[[#This Row],[Gross Revenue]]/Table19[[#This Row],[Budget]])-1 -> 0.23653112 | V40: =IF(J40="","",IF(J40<90,"<90 minutes",IF(J40<=110,"90-110 minutes",IF(J40<=130,"111-130 minutes",IF(J40<=150,"131-150 minutes",">150 minutes"))))) -> 111-130 minutes | W40: =Table19[[#This Row],[Profit]]/Table19[[#This Row],[Budget]]*100 -> 23.653113 | X40: 16235088 | Y40: 1.1909079 | Z40: =IF(L40="","",IF(L40<=$AA$26,"Low",IF(L40<=$AA$28,"Medium","High"))) -> Medium
A41: 30 Minutes or Less | B41: Bianca Kajlich | C41: Ruben Fleischer | D41: 731 | E41: 1987 | F41: 181 | G41: 0 | H41: 6.1 | I41: 220 | J41: 83 | K41: 37053924 | L41: 28000000 | M41: =VLOOKUP(A41,Sheet2!$A$1:G3765,2,0) -> 40817 | N41: =VLOOKUP(A41,Sheet2!$A$1:G3765,3,0) -> Color | O41: =VLOOKUP(A41,Sheet2!$A$1:G3765,4,0) -> Action | P41: =VLOOKUP(A41,Sheet2!$A$1:G3765,5,0) -> English | Q41: =VLOOKUP(A41,Sheet2!$A$1:G3765,6,0) -> Germany | R41: =VLOOKUP(A41,Sheet2!$A$1:G3765,7,0) -> R | S41: =IF(Table19[[#This Row],[Language]]="English","English","Other language") -> English | T41: =Table19[[#This Row],[Gross Revenue]]-Table19[[#This Row],[Budget]] -> 9053924 | U41: =(Table19[[#This Row],[Gross Revenue]]/Table19[[#This Row],[Budget]])-1 -> 0.32335443 | V41: =IF(J41="","",IF(J41<90,"<90 minutes",IF(J41<=110,"90-110 minutes",IF(J41<=130,"111-130 minutes",IF(J41<=150,"131-150 minutes",">150 minutes"))))) -> <90 minutes | W41: =Table19[[#This Row],[Profit]]/Table19[[#This Row],[Budget]]*100 -> 32.335443 | X41: -1289919.5 | Y41: -0.048151418 | Z41: =IF(L41="","",IF(L41<=$AA$26,"Low",IF(L41<=$AA$28,"Medium","High"))) -> Medium
A42: 300 | B42: Gerard Butler | C42: Zack Snyder | D42: 18000 | E42: 32360 | F42: 0 | G42: 13000 | H42: 7.7 | I42: 460 | J42: 117 | K42: 210592590 | L42: 65000000 | M42: =VLOOKUP(A42,Sheet2!$A$1:G3766,2,0) -> 38907 | N42: =VLOOKUP(A42,Sheet2!$A$1:G3766,3,0) -> Color | O42: =VLOOKUP(A42,Sheet2!$A$1:G3766,4,0) -> Action | P42: =VLOOKUP(A42,Sheet2!$A$1:G3766,5,0) -> English | Q42: =VLOOKUP(A42,Sheet2!$A$1:G3766,6,0) -> USA | R42: =VLOOKUP(A42,Sheet2!$A$1:G3766,7,0) -> R | S42: =IF(Table19[[#This Row],[Language]]="English","English","Other language") -> English | T42: =Table19[[#This Row],[Gross Revenue]]-Table19[[#This Row],[Budget]] -> 145592590 | U42: =(Table19[[#This Row],[Gross Revenue]]/Table19[[#This Row],[Budget]])-1 -> 2.239886 | V42: =IF(J42="","",IF(J42<90,"<90 minutes",IF(J42<=110,"90-110 minutes",IF(J42<=130,"111-130 minutes",IF(J42<=150,"131-150 minutes",">150 minutes"))))) -> 111-130 minutes | W42: =Table19[[#This Row],[Profit]]/Table19[[#This Row],[Budget]]*100 -> 223.9886 | X42: -1289919.5 | Y42: -0.048151418 | Z42: =IF(L42="","",IF(L42<=$AA$26,"Low",IF(L42<=$AA$28,"Medium","High"))) -> High
A43: 300: Rise of an Empire | B43: Eva Green | C43: Noam Murro | D43: 6000 | E43: 10583 | F43: 263 | G43: 71000 | H43: 6.2 | I43: 366 | J43: 102 | K43: 106369117 | L43: 110000000 | M43: =VLOOKUP(A43,Sheet2!$A$1:G3767,2,0) -> 41988 | N43: =VLOOKUP(A43,Sheet2!$A$1:G3767,3,0) -> Color | O43: =VLOOKUP(A43,Sheet2!$A$1:G3767,4,0) -> Action | P43: =VLOOKUP(A43,Sheet2!$A$1:G3767,5,0) -> English | Q43: =VLOOKUP(A43,Sheet2!$A$1:G3767,6,0) -> USA | R43: =VLOOKUP(A43,Sheet2!$A$1:G3767,7,0) -> R | S43: =IF(Table19[[#This Row],[Language]]="English","English","Other language") -> English | T43: =Table19[[#This Row],[Gross Revenue]]-Table19[[#This Row],[Budget]] -> -3630883 | U43: =(Table19[[#This Row],[Gross Revenue]]/Table19[[#This Row],[Budget]])-1 -> -0.033008027 | V43: =IF(J43="","",IF(J43<90,"<90 minutes",IF(J43<=110,"90-110 minutes",IF(J43<=130,"111-130 minutes",IF(J43<=150,"131-150 minutes",">150 minutes"))))) -> 90-110 minutes | W43: =Table19[[#This Row],[Profit]]/Table19[[#This Row],[Budget]]*100 -> -3.3008027 | X43: -1289919.5 | Y43: -0.048151418 | Z43: =IF(L43="","",IF(L43<=$AA$26,"Low",IF(L43<=$AA$28,"Medium","High"))) -> High
A44: 3000 Miles to Graceland | B44: Jon Lovitz | C44: Demian Lichtenstein | D44: 11000 | E44: 14536 | F44: 11 | G44: 0 | H44: 5.9 | I44: 113 | J44: 125 | K44: 15738632 | L44: 42000000 | M44: =VLOOKUP(A44,Sheet2!$A$1:G3768,2,0) -> 37148 | N44: =VLOOKUP(A44,Sheet2!$A$1:G3768,3,0) -> Color | O44: =VLOOKUP(A44,Sheet2!$A$1:G3768,4,0) -> Action | P44: =VLOOKUP(A44,Sheet2!$A$1:G3768,5,0) -> English | Q44: =VLOOKUP(A44,Sheet2!$A$1:G3768,6,0) -> USA | R44: =VLOOKUP(A44,Sheet2!$A$1:G3768,7,0) -> R | S44: =IF(Table19[[#This Row],[Language]]="English","English","Other language") -> English | T44: =Table19[[#This Row],[Gross Revenue]]-Table19[[#This Row],[Budget]] -> -26261368 | U44: =(Table19[[#This Row],[Gross Revenue]]/Table19[[#This Row],[Budget]])-1 -> -0.62527067 | V44: =IF(J44="","",IF(J44<90,"<90 minutes",IF(J44<=110,"90-110 minutes",IF(J44<=130,"111-130 minutes",IF(J44<=150,"131-150 minutes",">150 minutes"))))) -> 111-130 minutes | W44: =Table19[[#This Row],[Profit]]/Table19[[#This Row],[Budget]]*100 -> -62.527067 | X44: -1289919.5 | Y44: -0.048151418 | Z44: =IF(L44="","",IF(L44<=$AA$26,"Low",IF(L44<=$AA$28,"Medium","High"))) -> High
A45: 4 Months, 3 Weeks and 2 Days | B45: Anamaria Marinca | C45: Cristian Mungiu | D45: 131 | E45: 264 | F45: 163 | G45: 14000 | H45: 7.9 | I45: 233 | J45: 113 | K45: 1185783 | L45: 590000 | M45: =VLOOKUP(A45,Sheet2!$A$1:G3769,2,0) -> 39242 | N45: =VLOOKUP(A45,Sheet2!$A$1:G3769,3,0) -> Color | O45: =VLOOKUP(A45,Sheet2!$A$1:G3769,4,0) -> Drama | P45: =VLOOKUP(A45,Sheet2!$A$1:G3769,5,0) -> Romanian | Q45: =VLOOKUP(A45,Sheet2!$A$1:G3769,6,0) -> Romania | R45: =VLOOKUP(A45,Sheet2!$A$1:G3769,7,0) -> Not Rated | S45: =IF(Table19[[#This Row],[Language]]="English","English","Other language") -> Other language | T45: =Table19[[#This Row],[Gross Revenue]]-Table19[[#This Row],[Budget]] -> 595783 | U45: =(Table19[[#This Row],[Gross Revenue]]/Table19[[#This Row],[Budget]])-1 -> 1.0098017 | V45: =IF(J45="","",IF(J45<90,"<90 minutes",IF(J45<=110,"90-110 minutes",IF(J45<=130,"111-130 minutes",IF(J45<=150,"131-150 minutes",">150 minutes"))))) -> 111-130 minutes | W45: =Table19[[#This Row],[Profit]]/Table19[[#This Row],[Budget]]*100 -> 100.98017 | X45: -434215.5 | Y45: -0.10115101 | Z45: =IF(L45="","",IF(L45<=$AA$26,"Low",IF(L45<=$AA$28,"Medium","High"))) -> Low
A46: 40 Days and 40 Nights | B46: Emmanuelle Vaugier | C46: Michael Lehmann | D46: 1000 | E46: 3294 | F46: 36 | G46: 2000 | H46: 5.6 | I46: 140 | J46: 96 | K46: 37939782 | L46: 17000000 | M46: =VLOOKUP(A46,Sheet2!$A$1:G3770,2,0) -> 37304 | N46: =VLOOKUP(A46,Sheet2!$A$1:G3770,3,0) -> Color | O46: =VLOOKUP(A46,Sheet2!$A$1:G3770,4,0) -> Comedy | P46: =VLOOKUP(A46,Sheet2!$A$1:G3770,5,0) -> English | Q46: =VLOOKUP(A46,Sheet2!$A$1:G3770,6,0) -> USA | R46: =VLOOKUP(A46,Sheet2!$A$1:G3770,7,0) -> R | S46: =IF(Table19[[#This Row],[Language]]="English","English","Other language") -> English | T46: =Table19[[#This Row],[Gross Revenue]]-Table19[[#This Row],[Budget]] -> 20939782 | U46: =(Table19[[#This Row],[Gross Revenue]]/Table19[[#This Row],[Budget]])-1 -> 1.2317519 | V46: =IF(J46="","",IF(J46<90,"<90 minutes",IF(J46<=110,"90-110 minutes",IF(J46<=130,"111-130 minutes",IF(J46<=150,"131-150 minutes",">150 minutes"))))) -> 90-110 minutes | W46: =Table19[[#This Row],[Profit]]/Table19[[#This Row],[Budget]]*100 -> 123.17519 | X46: 1637763 | Y46: 0.19178668 | Z46: =IF(L46="","",IF(L46<=$AA$26,"Low",IF(L46<=$AA$28,"Medium","High"))) -> Medium
A47: 42 | B47: Harrison Ford | C47: Brian Helgeland | D47: 11000 | E47: 16911 | F47: 241 | G47: 28000 | H47: 7.5 | I47: 216 | J47: 128 | K47: 95001343 | L47: 40000000 | M47: =VLOOKUP(A47,Sheet2!$A$1:G3771,2,0) -> 41296 | N47: =VLOOKUP(A47,Sheet2!$A$1:G3771,3,0) -> Color | O47: =VLOOKUP(A47,Sheet2!$A$1:G3771,4,0) -> Biography | P47: =VLOOKUP(A47,Sheet2!$A$1:G3771,5,0) -> English | Q47: =VLOOKUP(A47,Sheet2!$A$1:G3771,6,0) -> USA | R47: =VLOOKUP(A47,Sheet2!$A$1:G3771,7,0) -> PG-13 | S47: =IF(Table19[[#This Row],[Language]]="English","English","Other language") -> English | T47: =Table19[[#This Row],[Gross Revenue]]-Table19[[#This Row],[Budget]] -> 55001343 | U47: =(Table19[[#This Row],[Gross Revenue]]/Table19[[#This Row],[Budget]])-1 -> 1.3750336 | V47: =IF(J47="","",IF(J47<90,"<90 minutes",IF(J47<=110,"90-110 minutes",IF(J47<=130,"111-130 minutes",IF(J47<=150,"131-150 minutes",">150 minutes"))))) -> 111-130 minutes | W47: =Table19[[#This Row],[Profit]]/Table19[[#This Row],[Budget]]*100 -> 137.50336 | X47: -1289919.5 | Y47: -0.048151418 | Z47: =IF(L47="","",IF(L47<=$AA$26,"Low",IF(L47<=$AA$28,"Medium","High"))) -> High
A48: 42nd Street | B48: Ginger Rogers | C48: Lloyd Bacon | D48: 610 | E48: 995 | F48: 24 | G48: 439 | H48: 7.7 | I48: 65 | J48: 89 | K48: 2300000 | L48: 439000 | M48: =VLOOKUP(A48,Sheet2!$A$1:G3772,2,0) -> 12295 | N48: =VLOOKUP(A48,Sheet2!$A$1:G3772,3,0) -> Black and White | O48: =VLOOKUP(A48,Sheet2!$A$1:G3772,4,0) -> Comedy | P48: =VLOOKUP(A48,Sheet2!$A$1:G3772,5,0) -> English | Q48: =VLOOKUP(A48,Sheet2!$A$1:G3772,6,0) -> USA | R48: =VLOOKUP(A48,Sheet2!$A$1:G3772,7,0) -> Unrated | S48: =IF(Table19[[#This Row],[Language]]="English","English","Other language") -> English | T48: =Table19[[#This Row],[Gross Revenue]]-Table19[[#This Row],[Budget]] -> 1861000 | U48: =(Table19[[#This Row],[Gross Revenue]]/Table19[[#This Row],[Budget]])-1 -> 4.23918 | V48: =IF(J48="","",IF(J48<90,"<90 minutes",IF(J48<=110,"90-110 minutes",IF(J48<=130,"111-130 minutes",IF(J48<=150,"131-150 minutes",">150 minutes"))))) -> <90 minutes | W48: =Table19[[#This Row],[Profit]]/Table19[[#This Row],[Budget]]*100 -> 423.918 | X48: 1637763 | Y48: 0.19178668 | Z48: =IF(L48="","",IF(L48<=$AA$26,"Low",IF(L48<=$AA$28,"Medium","High"))) -> Low
... A57: 8 Women | B57: Catherine Deneuve | C57: FranÃ§ois Ozon | D57: 963 | E57: 3543 | F57: 341 | G57: 0 | H57: 7.1 | I57: 128 | J57: 111 | K57: 3076425 | L57: 8000000 | M57: =VLOOKUP(A57,Sheet2!$A$1:G3781,2,0) -> 37378 | N57: =VLOOKUP(A57,Sheet2!$A$1:G3781,3,0) -> Color | O57: =VLOOKUP(A57,Sheet2!$A$1:G3781,4,0) -> Comedy | P57: =VLOOKUP(A57,Sheet2!$A$1:G3781,5,0) -> French | Q57: =VLOOKUP(A57,Sheet2!$A$1:G3781,6,0) -> France | R57: =VLOOKUP(A57,Sheet2!$A$1:G3781,7,0) -> R | S57: =IF(Table19[[#This Row],[Language]]="English","English","Other language") -> Other language | T57: =Table19[[#This Row],[Gross Revenue]]-Table19[[#This Row],[Budget]] -> -4923575 | U57: =(Table19[[#This Row],[Gross Revenue]]/Table19[[#This Row],[Budget]])-1 -> -0.61544687 | V57: =IF(J57="","",IF(J57<90,"<90 minutes",IF(J57<=110,"90-110 minutes",IF(J57<=130,"111-130 minutes",IF(J57<=150,"131-150 minutes",">150 minutes"))))) -> 111-130 minutes | W57: =Table19[[#This Row],[Profit]]/Table19[[#This Row],[Budget]]*100 -> -61.544687 | X57: 1637763 | Y57: 0.19178668 | Z57: =IF(L57="","",IF(L57<=$AA$26,"Low",IF(L57<=$AA$28,"Medium","High"))) -> Low
A58: 8: The Mormon Proposition | B58: Dustin Lance Black | C58: Reed Cowan | D58: 191 | E58: 210 | F58: 0 | G58: 0 | H58: 7.1 | I58: 28 | J58: 80 | K58: 99851 | L58: 2500000 | M58: =VLOOKUP(A58,Sheet2!$A$1:G3782,2,0) -> 40190 | N58: =VLOOKUP(A58,Sheet2!$A$1:G3782,3,0) -> Color | O58: =VLOOKUP(A58,Sheet2!$A$1:G3782,4,0) -> Documentary | P58: =VLOOKUP(A58,Sheet2!$A$1:G3782,5,0) -> English | Q58: =VLOOKUP(A58,Sheet2!$A$1:G3782,6,0) -> USA | R58: =VLOOKUP(A58,Sheet2!$A$1:G3782,7,0) -> R | S58: =IF(Table19[[#This Row],[Language]]="English","English","Other language") -> English | T58: =Table19[[#This Row],[Gross Revenue]]-Table19[[#This Row],[Budget]] -> -2400149 | U58: =(Table19[[#This Row],[Gross Revenue]]/Table19[[#This Row],[Budget]])-1 -> -0.9600596 | V58: =IF(J58="","",IF(J58<90,"<90 minutes",IF(J58<=110,"90-110 minutes",IF(J58<=130,"111-130 minutes",IF(J58<=150,"131-150 minutes",">150 minutes"))))) -> <90 minutes | W58: =Table19[[#This Row],[Profit]]/Table19[[#This Row],[Budget]]*100 -> -96.00596 | Z58: =IF(L58="","",IF(L58<=$AA$26,"Low",IF(L58<=$AA$28,"Medium","High"))) -> Low
A59: 88 Minutes | B59: Al Pacino | C59: Jon Avnet | D59: 14000 | E59: 16722 | F59: 50 | G59: 0 | H59: 5.9 | I59: 158 | J59: 108 | K59: 16930884 | L59: 30000000 | M59: =VLOOKUP(A59,Sheet2!$A$1:G3783,2,0) -> 39367 | N59: =VLOOKUP(A59,Sheet2!$A$1:G3783,3,0) -> Color | O59: =VLOOKUP(A59,Sheet2!$A$1:G3783,4,0) -> Crime | P59: =VLOOKUP(A59,Sheet2!$A$1:G3783,5,0) -> English | Q59: =VLOOKUP(A59,Sheet2!$A$1:G3783,6,0) -> USA | R59: =VLOOKUP(A59,Sheet2!$A$1:G3783,7,0) -> R | S59: =IF(Table19[[#This Row],[Language]]="English","English","Other language") -> English | T59: =Table19[[#This Row],[Gross Revenue]]-Table19[[#This Row],[Budget]] -> -13069116 | U59: =(Table19[[#This Row],[Gross Revenue]]/Table19[[#This Row],[Budget]])-1 -> -0.4356372 | V59: =IF(J59="","",IF(J59<90,"<90 minutes",IF(J59<=110,"90-110 minutes",IF(J59<=130,"111-130 minutes",IF(J59<=150,"131-150 minutes",">150 minutes"))))) -> 90-110 minutes | W59: =Table19[[#This Row],[Profit]]/Table19[[#This Row],[Budget]]*100 -> -43.56372 | X59: -74533.5 | Y59: -0.0074856786 | Z59: =IF(L59="","",IF(L59<=$AA$26,"Low",IF(L59<=$AA$28,"Medium","High"))) -> Medium
A60: 8MM | B60: Nicolas Cage | C60: Joel Schumacher | D60: 12000 | E60: 12970 | F60: 541 | G60: 0 | H60: 6.5 | I60: 138 | J60: 123 | K60: 36283504 | L60: 40000000 | M60: =VLOOKUP(A60,Sheet2!$A$1:G3784,2,0) -> 36208 | N60: =VLOOKUP(A60,Sheet2!$A$1:G3784,3,0) -> Color | O60: =VLOOKUP(A60,Sheet2!$A$1:G3784,4,0) -> Mystery | P60: =VLOOKUP(A60,Sheet2!$A$1:G3784,5,0) -> English | Q60: =VLOOKUP(A60,Sheet2!$A$1:G3784,6,0) -> Germany | R60: =VLOOKUP(A60,Sheet2!$A$1:G3784,7,0) -> R | S60: =IF(Table19[[#This Row],[Language]]="English","English","Other language") -> English | T60: =Table19[[#This Row],[Gross Revenue]]-Table19[[#This Row],[Budget]] -> -3716496 | U60: =(Table19[[#This Row],[Gross Revenue]]/Table19[[#This Row],[Budget]])-1 -> -0.0929124 | V60: =IF(J60="","",IF(J60<90,"<90 minutes",IF(J60<=110,"90-110 minutes",IF(J60<=130,"111-130 minutes",IF(J60<=150,"131-150 minutes",">150 minutes"))))) -> 111-130 minutes | W60: =Table19[[#This Row],[Profit]]/Table19[[#This Row],[Budget]]*100 -> -9.29124 | Z60: =IF(L60="","",IF(L60<=$AA$26,"Low",IF(L60<=$AA$28,"Medium","High"))) -> High
A61: 9 | B61: Martin Landau | C61: Shane Acker | D61: 940 | E61: 1594 | F61: 30 | G61: 13000 | H61: 7.1 | I61: 263 | J61: 79 | K61: 31743332 | L61: 30000000 | M61: =VLOOKUP(A61,Sheet2!$A$1:G3785,2,0) -> 39954 | N61: =VLOOKUP(A61,Sheet2!$A$1:G3785,3,0) -> Color | O61: =VLOOKUP(A61,Sheet2!$A$1:G3785,4,0) -> Action | P61: =VLOOKUP(A61,Sheet2!$A$1:G3785,5,0) -> English | Q61: =VLOOKUP(A61,Sheet2!$A$1:G3785,6,0) -> USA | R61: =VLOOKUP(A61,Sheet2!$A$1:G3785,7,0) -> PG-13 | S61: =IF(Table19[[#This Row],[Language]]="English","English","Other language") -> English | T61: =Table19[[#This Row],[Gross Revenue]]-Table19[[#This Row],[Budget]] -> 1743332 | U61: =(Table19[[#This Row],[Gross Revenue]]/Table19[[#This Row],[Budget]])-1 -> 0.058111067 | V61: =IF(J61="","",IF(J61<90,"<90 minutes",IF(J61<=110,"90-110 minutes",IF(J61<=130,"111-130 minutes",IF(J61<=150,"131-150 minutes",">150 minutes"))))) -> <90 minutes | W61: =Table19[[#This Row],[Profit]]/Table19[[#This Row],[Budget]]*100 -> 5.8111067 | X61: -1289919.5 | Y61: -0.048151418 | Z61: =IF(L61="","",IF(L61<=$AA$26,"Low",IF(L61<=$AA$28,"Medium","High"))) -> Medium
A62: 90 Minutes in Heaven | B62: Hayden Christensen | C62: Michael Polish | D62: 4000 | E62: 6617 | F62: 35 | G62: 0 | H62: 4.6 | I62: 12 | J62: 121 | K62: 4700361 | L62: 5000000 | M62: =VLOOKUP(A62,Sheet2!$A$1:G3786,2,0) -> 42276 | N62: =VLOOKUP(A62,Sheet2!$A$1:G3786,3,0) -> Color | O62: =VLOOKUP(A62,Sheet2!$A$1:G3786,4,0) -> Drama | P62: =VLOOKUP(A62,Sheet2!$A$1:G3786,5,0) -> English | Q62: =VLOOKUP(A62,Sheet2!$A$1:G3786,6,0) -> USA | R62: =VLOOKUP(A62,Sheet2!$A$1:G3786,7,0) -> PG-13 | S62: =IF(Table19[[#This Row],[Language]]="English","English","Other language") -> English | T62: =Table19[[#This Row],[Gross Revenue]]-Table19[[#This Row],[Budget]] -> -299639 | U62: =(Table19[[#This Row],[Gross Revenue]]/Table19[[#This Row],[Budget]])-1 -> -0.0599278 | V62: =IF(J62="","",IF(J62<90,"<90 minutes",IF(J62<=110,"90-110 minutes",IF(J62<=130,"111-130 minutes",IF(J62<=150,"131-150 minutes",">150 minutes"))))) -> 111-130 minutes | W62: =Table19[[#This Row],[Profit]]/Table19[[#This Row],[Budget]]*100 -> -5.99278 | X62: -434215.5 | Y62: -0.10115101 | Z62: =IF(L62="","",IF(L62<=$AA$26,"Low",IF(L62<=$AA$28,"Medium","High"))) -> Low
A63: 9Â½ Weeks | B63: David Margulies | C63: Adrian Lyne | D63: 567 | E63: 711 | F63: 213 | G63: 0 | H63: 5.9 | I63: 38 | J63: 112 | K63: 6734844 | L63: 17000000 | M63: =VLOOKUP(A63,Sheet2!$A$1:G3787,2,0) -> 31489 | N63: =VLOOKUP(A63,Sheet2!$A$1:G3787,3,0) -> Color | O63: =VLOOKUP(A63,Sheet2!$A$1:G3787,4,0) -> Drama | P63: =VLOOKUP(A63,Sheet2!$A$1:G3787,5,0) -> English | Q63: =VLOOKUP(A63,Sheet2!$A$1:G3787,6,0) -> USA | R63: =VLOOKUP(A63,Sheet2!$A$1:G3787,7,0) -> R | S63: =IF(Table19[[#This Row],[Language]]="English","English","Other language") -> English | T63: =Table19[[#This Row],[Gross Revenue]]-Table19[[#This Row],[Budget]] -> -10265156 | U63: =(Table19[[#This Row],[Gross Revenue]]/Table19[[#This Row],[Budget]])-1 -> -0.60383271 | V63: =IF(J63="","",IF(J63<90,"<90 minutes",IF(J63<=110,"90-110 minutes",IF(J63<=130,"111-130 minutes",IF(J63<=150,"131-150 minutes",">150 minutes"))))) -> 111-130 minutes | W63: =Table19[[#This Row],[Profit]]/Table19[[#This Row],[Budget]]*100 -> -60.383271 | X63: -434215.5 | Y63: -0.10115101 | Z63: =IF(L63="","",IF(L63<=$AA$26,"Low",IF(L63<=$AA$28,"Medium","High"))) -> Medium
A64: A Beautiful Mind | B64: Adam Goldberg | C64: Ron Howard | D64: 1000 | E64: 2827 | F64: 2000 | G64: 29000 | H64: 8.2 | I64: 205 | J64: 135 | K64: 170708996 | L64: 58000000 | M64: =VLOOKUP(A64,Sheet2!$A$1:G3788,2,0) -> 37123 | N64: =VLOOKUP(A64,Sheet2!$A$1:G3788,3,0) -> Color | O64: =VLOOKUP(A64,Sheet2!$A$1:G3788,4,0) -> Biography | P64: =VLOOKUP(A64,Sheet2!$A$1:G3788,5,0) -> English | Q64: =VLOOKUP(A64,Sheet2!$A$1:G3788,6,0) -> USA | R64: =VLOOKUP(A64,Sheet2!$A$1:G3788,7,0) -> PG-13 | S64: =IF(Table19[[#This Row],[Language]]="English","English","Other language") -> English | T64: =Table19[[#This Row],[Gross Revenue]]-Table19[[#This Row],[Budget]] -> 112708996 | U64: =(Table19[[#This Row],[Gross Revenue]]/Table19[[#This Row],[Budget]])-1 -> 1.9432586 | V64: =IF(J64="","",IF(J64<90,"<90 minutes",IF(J64<=110,"90-110 minutes",IF(J64<=130,"111-130 minutes",IF(J64<=150,"131-150 minutes",">150 minutes"))))) -> 131-150 minutes | W64: =Table19[[#This Row],[Profit]]/Table19[[#This Row],[Budget]]*100 -> 194.32586 | X64: -1289919.5 | Y64: -0.048151418 | Z64: =IF(L64="","",IF(L64<=$AA$26,"Low",IF(L64<=$AA$28,"Medium","High"))) -> High
A65: A Better Life | B65: DemiÃ¡n Bichir | C65: Chris Weitz | D65: 749 | E65: 2214 | F65: 129 | G65: 0 | H65: 7.2 | I65: 94 | J65: 98 | K65: 1754319 | L65: 10000000 | M65: =VLOOKUP(A65,Sheet2!$A$1:G3789,2,0) -> 40805 | N65: =VLOOKUP(A65,Sheet2!$A$1:G3789,3,0) -> Color | O65: =VLOOKUP(A65,Sheet2!$A$1:G3789,4,0) -> Drama | P65: =VLOOKUP(A65,Sheet2!$A$1:G3789,5,0) -> English | Q65: =VLOOKUP(A65,Sheet2!$A$1:G3789,6,0) -> USA | R65: =VLOOKUP(A65,Sheet2!$A$1:G3789,7,0) -> PG-13 | S65: =IF(Table19[[#This Row],[Language]]="English","English","Other language") -> English | T65: =Table19[[#This Row],[Gross Revenue]]-Table19[[#This Row],[Budget]] -> -8245681 | U65: =(Table19[[#This Row],[Gross Revenue]]/Table19[[#This Row],[Budget]])-1 -> -0.8245681 | V65: =IF(J65="","",IF(J65<90,"<90 minutes",IF(J65<=110,"90-110 minutes",IF(J65<=130,"111-130 minutes",IF(J65<=150,"131-150 minutes",">150 minutes"))))) -> 90-110 minutes | W65: =Table19[[#This Row],[Profit]]/Table19[[#This Row],[Budget]]*100 -> -82.45681 | X65: -434215.5 | Y65: -0.10115101 | Z65: =IF(L65="","",IF(L65<=$AA$26,"Low",IF(L65<=$AA$28,"Medium","High"))) -> Low
A66: A Bridge Too Far | B66: Ryan O'Neal | C66: Richard Attenborough | D66: 385 | E66: 669 | F66: 0 | G66: 0 | H66: 7.4 | I66: 56 | J66: 175 | K66: 50800000 | L66: 26000000 | M66: =VLOOKUP(A66,Sheet2!$A$1:G3790,2,0) -> 28358 | N66: =VLOOKUP(A66,Sheet2!$A$1:G3790,3,0) -> Black and White | O66: =VLOOKUP(A66,Sheet2!$A$1:G3790,4,0) -> Drama | P66: =VLOOKUP(A66,Sheet2!$A$1:G3790,5,0) -> English | Q66: =VLOOKUP(A66,Sheet2!$A$1:G3790,6,0) -> USA | R66: =VLOOKUP(A66,Sheet2!$A$1:G3790,7,0) -> PG | S66: =IF(Table19[[#This Row],[Language]]="English","English","Other language") -> English | T66: =Table19[[#This Row],[Gross Revenue]]-Table19[[#This Row],[Budget]] -> 24800000 | U66: =(Table19[[#This Row],[Gross Revenue]]/Table19[[#This Row],[Budget]])-1 -> 0.95384615 | V66: =IF(J66="","",IF(J66<90,"<90 minutes",IF(J66<=110,"90-110 minutes",IF(J66<=130,"111-130 minutes",IF(J66<=150,"131-150 minutes",">150 minutes"))))) -> >150 minutes | W66: =Table19[[#This Row],[Profit]]/Table19[[#This Row],[Budget]]*100 -> 95.384615 | X66: -434215.5 | Y66: -0.10115101 | Z66: =IF(L66="","",IF(L66<=$AA$26,"Low",IF(L66<=$AA$28,"Medium","High"))) -> Medium
A67: A Bug's Life | B67: Kevin Spacey | C67: John Lasseter | D67: 18000 | E67: 24205 | F67: 487 | G67: 0 | H67: 7.2 | I67: 117 | J67: 95 | K67: 162792677 | L67: 120000000 | M67: =VLOOKUP(A67,Sheet2!$A$1:G3791,2,0) -> 36121 | N67: =VLOOKUP(A67,Sheet2!$A$1:G3791,3,0) -> Color | O67: =VLOOKUP(A67,Sheet2!$A$1:G3791,4,0) -> Adventure | P67: =VLOOKUP(A67,Sheet2!$A$1:G3791,5,0) -> English | Q67: =VLOOKUP(A67,Sheet2!$A$1:G3791,6,0) -> USA | R67: =VLOOKUP(A67,Sheet2!$A$1:G3791,7,0) -> G | S67: =IF(Table19[[#This Row],[Language]]="English","English","Other language") -> English | T67: =Table19[[#This Row],[Gross Revenue]]-Table19[[#This Row],[Budget]] -> 42792677 | U67: =(Table19[[#This Row],[Gross Revenue]]/Table19[[#This Row],[Budget]])-1 -> 0.35660564 | V67: =IF(J67="","",IF(J67<90,"<90 minutes",IF(J67<=110,"90-110 minutes",IF(J67<=130,"111-130 minutes",IF(J67<=150,"131-150 minutes",">150 minutes"))))) -> 90-110 minutes | W67: =Table19[[#This Row],[Profit]]/Table19[[#This Row],[Budget]]*100 -> 35.660564 | X67: 3892693.5 | Y67: 0.11726929 | Z67: =IF(L67="","",IF(L67<=$AA$26,"Low",IF(L67<=$AA$28,"Medium","High"))) -> High
A68: A Christmas Carol | B68: Robin Wright | C68: Robert Zemeckis | D68: 18000 | E68: 48878 | F68: 0 | G68: 0 | H68: 6.8 | I68: 240 | J68: 96 | K68: 137850096 | L68: 200000000 | M68: =VLOOKUP(A68,Sheet2!$A$1:G3792,2,0) -> 39990 | N68: =VLOOKUP(A68,Sheet2!$A$1:G3792,3,0) -> Color | O68: =VLOOKUP(A68,Sheet2!$A$1:G3792,4,0) -> Animation | P68: =VLOOKUP(A68,Sheet2!$A$1:G3792,5,0) -> English | Q68: =VLOOKUP(A68,Sheet2!$A$1:G3792,6,0) -> USA | R68: =VLOOKUP(A68,Sheet2!$A$1:G3792,7,0) -> PG | S68: =IF(Table19[[#This Row],[Language]]="English","English","Other language") -> English | T68: =Table19[[#This Row],[Gross Revenue]]-Table19[[#This Row],[Budget]] -> -62149904 | U68: =(Table19[[#This Row],[Gross Revenue]]/Table19[[#This Row],[Budget]])-1 -> -0.31074952 | V68: =IF(J68="","",IF(J68<90,"<90 minutes",IF(J68<=110,"90-110 minutes",IF(J68<=130,"111-130 minutes",IF(J68<=150,"131-150 minutes",">150 minutes"))))) -> 90-110 minutes | W68: =Table19[[#This Row],[Profit]]/Table19[[#This Row],[Budget]]*100 -> -31.074952 | Z68: =IF(L68="","",IF(L68<=$AA$26,"Low",IF(L68<=$AA$28,"Medium","High"))) -> High
A69: A Cinderella Story | B69: Dan Byrd | C69: Mark Rosman | D69: 1000 | E69: 3092 | F69: 15 | G69: 0 | H69: 5.9 | I69: 69 | J69: 95 | K69: 51431160 | L69: 20000000 | M69: =VLOOKUP(A69,Sheet2!$A$1:G3793,2,0) -> 38154 | N69: =VLOOKUP(A69,Sheet2!$A$1:G3793,3,0) -> Color | O69: =VLOOKUP(A69,Sheet2!$A$1:G3793,4,0) -> Comedy | P69: =VLOOKUP(A69,Sheet2!$A$1:G3793,5,0) -> English | Q69: =VLOOKUP(A69,Sheet2!$A$1:G3793,6,0) -> USA | R69: =VLOOKUP(A69,Sheet2!$A$1:G3793,7,0) -> PG | S69: =IF(Table19[[#This Row],[Language]]="English","English","Other language") -> English | T69: =Table19[[#This Row],[Gross Revenue]]-Table19[[#This Row],[Budget]] -> 31431160 | U69: =(Table19[[#This Row],[Gross Revenue]]/Table19[[#This Row],[Budget]])-1 -> 1.571558 | V69: =IF(J69="","",IF(J69<90,"<90 minutes",IF(J69<=110,"90-110 minutes",IF(J69<=130,"111-130 minutes",IF(J69<=150,"131-150 minutes",">150 minutes"))))) -> 90-110 minutes | W69: =Table19[[#This Row],[Profit]]/Table19[[#This Row],[Budget]]*100 -> 157.1558 | X69: 1637763 | Y69: 0.19178668 | Z69: =IF(L69="","",IF(L69<=$AA$26,"Low",IF(L69<=$AA$28,"Medium","High"))) -> Medium
A70: A Civil Action | B70: Robert Duvall | C70: Steven Zaillian | D70: 3000 | E70: 4713 | F70: 234 | G70: 1000 | H70: 6.5 | I70: 110 | J70: 115 | K70: 56702901 | L70: 60000000 | M70: =VLOOKUP(A70,Sheet2!$A$1:G3794,2,0) -> 36080 | N70: =VLOOKUP(A70,Sheet2!$A$1:G3794,3,0) -> Color | O70: =VLOOKUP(A70,Sheet2!$A$1:G3794,4,0) -> Drama | P70: =VLOOKUP(A70,Sheet2!$A$1:G3794,5,0) -> English | Q70: =VLOOKUP(A70,Sheet2!$A$1:G3794,6,0) -> USA | R70: =VLOOKUP(A70,Sheet2!$A$1:G3794,7,0) -> PG-13 | S70: =IF(Table19[[#This Row],[Language]]="English","English","Other language") -> English | T70: =Table19[[#This Row],[Gross Revenue]]-Table19[[#This Row],[Budget]] -> -3297099 | U70: =(Table19[[#This Row],[Gross Revenue]]/Table19[[#This Row],[Budget]])-1 -> -0.05495165 | V70: =IF(J70="","",IF(J70<90,"<90 minutes",IF(J70<=110,"90-110 minutes",IF(J70<=130,"111-130 minutes",IF(J70<=150,"131-150 minutes",">150 minutes"))))) -> 111-130 minutes | W70: =Table19[[#This Row],[Profit]]/Table19[[#This Row],[Budget]]*100 -> -5.495165 | X70: -434215.5 | Y70: -0.10115101 | Z70: =IF(L70="","",IF(L70<=$AA$26,"Low",IF(L70<=$AA$28,"Medium","High"))) -> High
A71: A Dangerous Method | B71: Michael Fassbender | C71: David Cronenberg | D71: 13000 | E71: 23755 | F71: 0 | G71: 36000 | H71: 6.5 | I71: 345 | J71: 99 | K71: 5702083 | L71: 15000000 | M71: =VLOOKUP(A71,Sheet2!$A$1:G3795,2,0) -> 40691 | N71: =VLOOKUP(A71,Sheet2!$A$1:G3795,3,0) -> Color | O71: =VLOOKUP(A71,Sheet2!$A$1:G3795,4,0) -> Biography | P71: =VLOOKUP(A71,Sheet2!$A$1:G3795,5,0) -> English | Q71: =VLOOKUP(A71,Sheet2!$A$1:G3795,6,0) -> UK | R71: =VLOOKUP(A71,Sheet2!$A$1:G3795,7,0) -> R | S71: =IF(Table19[[#This Row],[Language]]="English","English","Other language") -> English | T71: =Table19[[#This Row],[Gross Revenue]]-Table19[[#This Row],[Budget]] -> -9297917 | U71: =(Table19[[#This Row],[Gross Revenue]]/Table19[[#This Row],[Budget]])-1 -> -0.61986113 | V71: =IF(J71="","",IF(J71<90,"<90 minutes",IF(J71<=110,"90-110 minutes",IF(J71<=130,"111-130 minutes",IF(J71<=150,"131-150 minutes",">150 minutes"))))) -> 90-110 minutes | W71: =Table19[[#This Row],[Profit]]/Table19[[#This Row],[Budget]]*100 -> -61.986113 | X71: -1289919.5 | Y71: -0.048151418 | Z71: =IF(L71="","",IF(L71<=$AA$26,"Low",IF(L71<=$AA$28,"Medium","High"))) -> Medium
A72: A Dog of Flanders | B72: Bruce McGill | C72: Kevin Brodie | D72: 655 | E72: 1906 | F72: 0 | G72: 157 | H72: 6.3 | I72: 25 | J72: 100 | K72: 2148212 | L72: 7000000 | M72: =VLOOKUP(A72,Sheet2!$A$1:G3796,2,0) -> 36190 | N72: =VLOOKUP(A72,Sheet2!$A$1:G3796,3,0) -> Color | O72: =VLOOKUP(A72,Sheet2!$A$1:G3796,4,0) -> Drama | P72: =VLOOKUP(A72,Sheet2!$A$1:G3796,5,0) -> English | Q72: =VLOOKUP(A72,Sheet2!$A$1:G3796,6,0) -> USA | R72: =VLOOKUP(A72,Sheet2!$A$1:G3796,7,0) -> PG | S72: =IF(Table19[[#This Row],[Language]]="English","English","Other language") -> English | T72: =Table19[[#This Row],[Gross Revenue]]-Table19[[#This Row],[Budget]] -> -4851788 | U72: =(Table19[[#This Row],[Gross Revenue]]/Table19[[#This Row],[Budget]])-1 -> -0.69311257 | V72: =IF(J72="","",IF(J72<90,"<90 minutes",IF(J72<=110,"90-110 minutes",IF(J72<=130,"111-130 minutes",IF(J72<=150,"131-150 minutes",">150 minutes"))))) -> 90-110 minutes | W72: =Table19[[#This Row],[Profit]]/Table19[[#This Row],[Budget]]*100 -> -69.311257 | X72: -434215.5 | Y72: -0.10115101 | Z72: =IF(L72="","",IF(L72<=$AA$26,"Low",IF(L72<=$AA$28,"Medium","High"))) -> Low
A73: A Few Good Men | B73: Tom Cruise | C73: Rob Reiner | D73: 10000 | E73: 14619 | F73: 0 | G73: 0 | H73: 7.6 | I73: 81 | J73: 138 | K73: 141340178 | L73: 40000000 | M73: =VLOOKUP(A73,Sheet2!$A$1:G3797,2,0) -> 33765 | N73: =VLOOKUP(A73,Sheet2!$A$1:G3797,3,0) -> Color | O73: =VLOOKUP(A73,Sheet2!$A$1:G3797,4,0) -> Drama | P73: =VLOOKUP(A73,Sheet2!$A$1:G3797,5,0) -> English | Q73: =VLOOKUP(A73,Sheet2!$A$1:G3797,6,0) -> USA | R73: =VLOOKUP(A73,Sheet2!$A$1:G3797,7,0) -> R | S73: =IF(Table19[[#This Row],[Language]]="English","English","Other language") -> English | T73: =Table19[[#This Row],[Gross Revenue]]-Table19[[#This Row],[Budget]] -> 101340178 | U73: =(Table19[[#This Row],[Gross Revenue]]/Table19[[#This Row],[Budget]])-1 -> 2.5335045 | V73: =IF(J73="","",IF(J73<90,"<90 minutes",IF(J73<=110,"90-110 minutes",IF(J73<=130,"111-130 minutes",IF(J73<=150,"131-150 minutes",">150 minutes"))))) -> 131-150 minutes | W73: =Table19[[#This Row],[Profit]]/Table19[[#This Row],[Budget]]*100 -> 253.35045 | X73: -434215.5 | Y73: -0.10115101 | Z73: =IF(L73="","",IF(L73<=$AA$26,"Low",IF(L73<=$AA$28,"Medium","High"))) -> High
A74: A Fistful of Dollars | B74: Clint Eastwood | C74: Sergio Leone | D74: 16000 | E74: 16534 | F74: 0 | G74: 0 | H74: 8 | I74: 122 | J74: 99 | K74: 3500000 | L74: 200000 | M74: =VLOOKUP(A74,Sheet2!$A$1:G3798,2,0) -> 23389 | N74: =VLOOKUP(A74,Sheet2!$A$1:G3798,3,0) -> Color | O74: =VLOOKUP(A74,Sheet2!$A$1:G3798,4,0) -> Action | P74: =VLOOKUP(A74,Sheet2!$A$1:G3798,5,0) -> Italian | Q74: =VLOOKUP(A74,Sheet2!$A$1:G3798,6,0) -> Italy | R74: =VLOOKUP(A74,Sheet2!$A$1:G3798,7,0) -> R | S74: =IF(Table19[[#This Row],[Language]]="English","English","Other language") -> Other language | T74: =Table19[[#This Row],[Gross Revenue]]-Table19[[#This Row],[Budget]] -> 3300000 | U74: =(Table19[[#This Row],[Gross Revenue]]/Table19[[#This Row],[Budget]])-1 -> 16.5 | V74: =IF(J74="","",IF(J74<90,"<90 minutes",IF(J74<=110,"90-110 minutes",IF(J74<=130,"111-130 minutes",IF(J74<=150,"131-150 minutes",">150 minutes"))))) -> 90-110 minutes | W74: =Table19[[#This Row],[Profit]]/Table19[[#This Row],[Budget]]*100 -> 1650 | X74: -1289919.5 | Y74: -0.048151418 | Z74: =IF(L74="","",IF(L74<=$AA$26,"Low",IF(L74<=$AA$28,"Medium","High"))) -> Low
A75: A Good Day to Die Hard | B75: Bruce Willis | C75: John Moore | D75: 13000 | E75: 15481 | F75: 212 | G75: 66000 | H75: 5.3 | I75: 412 | J75: 101 | K75: 67344392 | L75: 92000000 | M75: =VLOOKUP(A75,Sheet2!$A$1:G3799,2,0) -> 41278 | N75: =VLOOKUP(A75,Sheet2!$A$1:G3799,3,0) -> Color | O75: =VLOOKUP(A75,Sheet2!$A$1:G3799,4,0) -> Action | P75: =VLOOKUP(A75,Sheet2!$A$1:G3799,5,0) -> English | Q75: =VLOOKUP(A75,Sheet2!$A$1:G3799,6,0) -> USA | R75: =VLOOKUP(A75,Sheet2!$A$1:G3799,7,0) -> R | S75: =IF(Table19[[#This Row],[Language]]="English","English","Other language") -> English | T75: =Table19[[#This Row],[Gross Revenue]]-Table19[[#This Row],[Budget]] -> -24655608 | U75: =(Table19[[#This Row],[Gross Revenue]]/Table19[[#This Row],[Budget]])-1 -> -0.26799574 | V75: =IF(J75="","",IF(J75<90,"<90 minutes",IF(J75<=110,"90-110 minutes",IF(J75<=130,"111-130 minutes",IF(J75<=150,"131-150 minutes",">150 minutes"))))) -> 90-110 minutes | W75: =Table19[[#This Row],[Profit]]/Table19[[#This Row],[Budget]]*100 -> -26.799574 | X75: -1289919.5 | Y75: -0.048151418 | Z75: =IF(L75="","",IF(L75<=$AA$26,"Low",IF(L75<=$AA$28,"Medium","High"))) -> High
A76: A Good Year | B76: Archie Panjabi | C76: Ridley Scott | D76: 883 | E76: 3611 | F76: 0 | G76: 9000 | H76: 6.9 | I76: 147 | J76: 117 | K76: 7458269 | L76: 35000000 | M76: =VLOOKUP(A76,Sheet2!$A$1:G3800,2,0) -> 38756 | N76: =VLOOKUP(A76,Sheet2!$A$1:G3800,3,0) -> Color | O76: =VLOOKUP(A76,Sheet2!$A$1:G3800,4,0) -> Comedy | P76: =VLOOKUP(A76,Sheet2!$A$1:G3800,5,0) -> English | Q76: =VLOOKUP(A76,Sheet2!$A$1:G3800,6,0) -> USA | R76: =VLOOKUP(A76,Sheet2!$A$1:G3800,7,0) -> PG-13 | S76: =IF(Table19[[#This Row],[Language]]="English","English","Other language") -> English | T76: =Table19[[#This Row],[Gross Revenue]]-Table19[[#This Row],[Budget]] -> -27541731 | U76: =(Table19[[#This Row],[Gross Revenue]]/Table19[[#This Row],[Budget]])-1 -> -0.7869066 | V76: =IF(J76="","",IF(J76<90,"<90 minutes",IF(J76<=110,"90-110 minutes",IF(J76<=130,"111-130 minutes",IF(J76<=150,"131-150 minutes",">150 minutes"))))) -> 111-130 minutes | W76: =Table19[[#This Row],[Profit]]/Table19[[#This Row],[Budget]]*100 -> -78.69066 | X76: 1637763 | Y76: 0.19178668 | Z76: =IF(L76="","",IF(L76<=$AA$26,"Low",IF(L76<=$AA$28,"Medium","High"))) -> Medium
A77: A Guy Thing | B77: Thomas Lennon | C77: Chris Koch | D77: 651 | E77: 2698 | F77: 13 | G77: 401 | H77: 5.6 | I77: 81 | J77: 101 | K77: 15408822 | L77: 20000000 | M77: =VLOOKUP(A77,Sheet2!$A$1:G3801,2,0) -> 37759 | N77: =VLOOKUP(A77,Sheet2!$A$1:G3801,3,0) -> Color | O77: =VLOOKUP(A77,Sheet2!$A$1:G3801,4,0) -> Comedy | P77: =VLOOKUP(A77,Sheet2!$A$1:G3801,5,0) -> English | Q77: =VLOOKUP(A77,Sheet2!$A$1:G3801,6,0) -> USA | R77: =VLOOKUP(A77,Sheet2!$A$1:G3801,7,0) -> PG-13 | S77: =IF(Table19[[#This Row],[Language]]="English","English","Other language") -> English | T77: =Table19[[#This Row],[Gross Revenue]]-Table19[[#This Row],[Budget]] -> -4591178 | U77: =(Table19[[#This Row],[Gross Revenue]]/Table19[[#This Row],[Budget]])-1 -> -0.2295589 | V77: =IF(J77="","",IF(J77<90,"<90 minutes",IF(J77<=110,"90-110 minutes",IF(J77<=130,"111-130 minutes",IF(J77<=150,"131-150 minutes",">150 minutes"))))) -> 90-110 minutes | W77: =Table19[[#This Row],[Profit]]/Table19[[#This Row],[Budget]]*100 -> -22.95589 | X77: 1637763 | Y77: 0.19178668 | Z77: =IF(L77="","",IF(L77<=$AA$26,"Low",IF(L77<=$AA$28,"Medium","High"))) -> Medium
A78: A Hard Day's Night | B78: Paul McCartney | C78: Richard Lester | D78: 785 | E78: 2538 | F78: 44 | G78: 0 | H78: 7.7 | I78: 105 | J78: 87 | K78: 515005 | L78: 560000 | M78: =VLOOKUP(A78,Sheet2!$A$1:G3802,2,0) -> 23519 | N78: =VLOOKUP(A78,Sheet2!$A$1:G3802,3,0) -> Black and White | O78: =VLOOKUP(A78,Sheet2!$A$1:G3802,4,0) -> Comedy | P78: =VLOOKUP(A78,Sheet2!$A$1:G3802,5,0) -> English | Q78: =VLOOKUP(A78,Sheet2!$A$1:G3802,6,0) -> UK | R78: =VLOOKUP(A78,Sheet2!$A$1:G3802,7,0) -> Approved | S78: =IF(Table19[[#This Row],[Language]]="English","English","Other language") -> English | T78: =Table19[[#This Row],[Gross Revenue]]-Table19[[#This Row],[Budget]] -> -44995 | U78: =(Table19[[#This Row],[Gross Revenue]]/Table19[[#This Row],[Budget]])-1 -> -0.080348214 | V78: =IF(J78="","",IF(J78<90,"<90 minutes",IF(J78<=110,"90-110 minutes",IF(J78<=130,"111-130 minutes",IF(J78<=150,"131-150 minutes",">150 minutes"))))) -> <90 minutes | W78: =Table19[[#This Row],[Profit]]/Table19[[#This Row],[Budget]]*100 -> -8.0348214 | X78: 1637763 | Y78: 0.19178668 | Z78: =IF(L78="","",IF(L78<=$AA$26,"Low",IF(L78<=$AA$28,"Medium","High"))) -> Low
